Workbook
Name л: #REF!
Name л: #REF!
Name о: #REF!
Name о: #REF!
Name Сумма: #REF!
Name Сумма: #REF!
Name Сумма: #REF!
Name Сумма1: #REF!
Name Сумма1: #REF!
Name Сумма1: #REF!

Sheet HeadRock
A7: Сентябрь 2026 | K7: =G806 -> 0
A8: Изображение | B8: Артикул | C8: Наименование | D8: Единиц в комплекте | E8: Штук/ комплектов во внутр. коробке | F8: Штук/ комплектов в коробке | G8: Цена за штуку/комплект в руб. с НДС) | H8: Минимальное количество заказа | I8: Ваш заказ, штук/комплектов | J8: Комплекты в штуках | K8: Сумма заказа | L8: Штрих-код (штука) | M8: Штрих-код (комплект) | N8: Штрих-код (коробка)
B9: Бур по бетону SDS+
B10: 402-010-6110 | C10: Бур по бетону SDS+ (6x110) | D10: 1 | E10: 50 | F10: 500 | G10: ='-'!G10 -> 47.18 | J10: - | K10: =G10*I10 -> 0 | L10: 4673732410025 | N10: 4673732410032
B11: 402-010-6160 | C11: Бур по бетону SDS+ (6x160) | D11: 1 | E11: 50 | F11: 500 | G11: ='-'!G11 -> 50.05 | J11: - | K11: =G11*I11 -> 0 | L11: 4673732410049 | N11: 4673732410056
B12: 402-010-6210 | C12: Бур по бетону SDS+ (6x210) | D12: 1 | E12: 50 | F12: 300 | G12: ='-'!G12 -> 61.88 | J12: - | K12: =G12*I12 -> 0 | L12: 4673732410063 | N12: 4673732410070
B13: 402-010-6260 | C13: Бур по бетону SDS+ (6x260) | D13: 1 | E13: 50 | F13: 250 | G13: ='-'!G13 -> 76.86 | J13: - | K13: =G13*I13 -> 0 | L13: 4673732410087 | N13: 4673732410094
B14: 402-010-6310 | C14: Бур по бетону SDS+ (6x310) | D14: 1 | E14: 50 | F14: 200 | G14: ='-'!G14 -> 83.19 | J14: - | K14: =G14*I14 -> 0 | L14: 4673732410100 | N14: 4673732410117
B15: 402-010-6350 | C15: Бур по бетону SDS+ (6x350) | D15: 1 | E15: 50 | F15: 200 | G15: ='-'!G15 -> 96.51 | J15: - | K15: =G15*I15 -> 0 | L15: 4673732410124 | N15: 4673732410131
B16: 402-010-6410 | C16: Бур по бетону SDS+ (6x410) РАСПРОДАЖА! | D16: 1 | E16: 50 | F16: 200 | G16: ='-'!G16 -> 102.69 | J16: - | K16: =G16*I16 -> 0 | L16: 4673732410148 | N16: 4673732410155
B17: 402-010-8110 | C17: Бур по бетону SDS+ (8x110) | D17: 1 | E17: 50 | F17: 500 | G17: ='-'!G17 -> 47.5 | J17: - | K17: =G17*I17 -> 0 | L17: 4673732410162 | N17: 4673732410179
B18: 402-010-8160 | C18: Бур по бетону SDS+ (8x160) | D18: 1 | E18: 50 | F18: 500 | G18: ='-'!G18 -> 61.88 | J18: - | K18: =G18*I18 -> 0 | L18: 4673732410186 | N18: 4673732410193
B19: 402-010-8210 | C19: Бур по бетону SDS+ (8x210) | D19: 1 | E19: 50 | F19: 250 | G19: ='-'!G19 -> 75.13 | J19: - | K19: =G19*I19 -> 0 | L19: 4673732410209 | N19: 4673732410216
B20: 402-010-8260 | C20: Бур по бетону SDS+ (8x260) | D20: 1 | E20: 50 | F20: 200 | G20: ='-'!G20 -> 78.75 | J20: - | K20: =G20*I20 -> 0 | L20: 4673732410223 | N20: 4673732410230
B21: 402-010-8310 | C21: Бур по бетону SDS+ (8x310) | D21: 1 | E21: 50 | F21: 100 | G21: ='-'!G21 -> 86.25 | J21: - | K21: =G21*I21 -> 0 | L21: 4673732410247 | N21: 4673732410254
... B92: 402-010-22460 | C92: Бур по бетону SDS+ (22х460) | D92: 1 | E92: 25 | F92: 25 | G92: ='-'!G92 -> 372.64 | J92: - | K92: =G92*I92 -> 0 | L92: 4673759127746 | N92: 4673759127753
B93: Зубило SDS+
B94: 411-010-1425020 | C94: Зубило SDS+ (14x250x20) | D94: 1 | E94: 10 | F94: 100 | G94: ='-'!G94 -> 126.39 | J94: - | K94: =G94*I94 -> 0 | L94: 4673732410780 | N94: 4673732410797
B95: 411-010-1425050 | C95: Зубило SDS+ (14x250x50) | D95: 1 | E95: 10 | F95: 100 | G95: ='-'!G95 -> 183.48 | J95: - | K95: =G95*I95 -> 0 | L95: 4673732410803 | N95: 4673732410810
B96: 411-010-1440020 | C96: Зубило SDS+ (14x400x20) | D96: 1 | E96: 10 | F96: 50 | G96: ='-'!G96 -> 216.25 | J96: - | K96: =G96*I96 -> 0 | L96: 4673768180541 | N96: 4673768180558
B97: 411-010-1440050 | C97: Зубило SDS+ (14x400x50) | D97: 1 | E97: 10 | F97: 50 | G97: ='-'!G97 -> 287.56 | J97: - | K97: =G97*I97 -> 0 | L97: 4673768180565 | N97: 4673768180572
B98: 411-010-1460020 | C98: Зубило SDS+ (14x600x20) | D98: 1 | E98: 5 | F98: 25 | G98: ='-'!G98 -> 310.56 | J98: - | K98: =G98*I98 -> 0 | L98: 4673768180589 | N98: 4673768180596
B99: 411-010-1460050 | C99: Зубило SDS+ (14x600x50) | D99: 1 | E99: 5 | F99: 25 | G99: ='-'!G99 -> 411.9 | J99: - | K99: =G99*I99 -> 0 | L99: 4673768180602 | N99: 4673768180619
B100: Коронка по бетону SDS+
B101: 422-010-30 | C101: Коронка по бетону SDS+ D30 | D101: 1 | E101: / | F101: 50 | G101: ='-'!G101 -> 351.13 | J101: - | K101: =G101*I101 -> 0 | L101: 4673759127760 | N101: 4673759127777
B102: 422-010-35 | C102: Коронка по бетону SDS+ D35 | D102: 1 | E102: / | F102: 50 | G102: ='-'!G102 -> 364.48 | J102: - | K102: =G102*I102 -> 0 | L102: 4673759127784 | N102: 4673759127791
B103: 422-010-40 | C103: Коронка по бетону SDS+ D40 | D103: 1 | E103: / | F103: 50 | G103: ='-'!G103 -> 438.6 | J103: - | K103: =G103*I103 -> 0 | L103: 4673759127807 | N103: 4673759127814
B104: 422-010-45 | C104: Коронка по бетону SDS+ D45 | D104: 1 | E104: / | F104: 50 | G104: ='-'!G104 -> 547 | J104: - | K104: =G104*I104 -> 0 | L104: 4673732414535 | N104: 4673732414542
B105: 422-010-50 | C105: Коронка по бетону SDS+ D50 | D105: 1 | E105: / | F105: 50 | G105: ='-'!G105 -> 586.84 | J105: - | K105: =G105*I105 -> 0 | L105: 4673732414566 | N105: 4673732414559
B106: 422-010-55 | C106: Коронка по бетону SDS+ D55 | D106: 1 | E106: / | F106: 20 | G106: ='-'!G106 -> 481.84 | J106: - | K106: =G106*I106 -> 0 | L106: 4673732414597 | N106: 4673732414603
B107: 422-010-60 | C107: Коронка по бетону SDS+ D60 | D107: 1 | E107: / | F107: 20 | G107: ='-'!G107 -> 506.55 | J107: - | K107: =G107*I107 -> 0 | L107: 4673732414610 | N107: 4673732414627
B108: 422-010-65 | C108: Коронка по бетону SDS+ D65 | D108: 1 | E108: / | F108: 20 | G108: ='-'!G108 -> 647.19 | J108: - | K108: =G108*I108 -> 0 | L108: 4673732410827 | N108: 4673732410834
B109: 422-010-68 | C109: Коронка по бетону SDS+ D68 | D109: 1 | E109: / | F109: 20 | G109: ='-'!G109 -> 700.16 | J109: - | K109: =G109*I109 -> 0 | L109: 4673732410841 | N109: 4673732410858
B110: 422-010-70 | C110: Коронка по бетону SDS+ D70 | D110: 1 | E110: / | F110: 20 | G110: ='-'!G110 -> 734.95 | J110: - | K110: =G110*I110 -> 0 | L110: 4673732410865 | N110: 4673732410872
B111: 422-010-75 | C111: Коронка по бетону SDS+ D75 | D111: 1 | E111: / | F111: 20 | G111: ='-'!G111 -> 630.09 | J111: - | K111: =G111*I111 -> 0 | L111: 4673732410889 | N111: 4673732410896
B112: 422-010-100 | C112: Коронка по бетону SDS+ D100 | D112: 1 | E112: / | F112: 10 | G112: ='-'!G112 -> 1114.4 | J112: - | K112: =G112*I112 -> 0 | L112: 4673732410902 | N112: 4673732410919
... B116: 422-010-150 | C116: Коронка по бетону SDS+ D150 | D116: 1 | E116: / | F116: 10 | G116: ='-'!G116 -> 1985.66 | J116: - | K116: =G116*I116 -> 0 | L116: 4673759127845 | N116: 4673759127852
B117: Коронка алмазная по бетону (безударные)
B118: 634-708-068 | C118: Коронка алмазная по бетону 68мм (безударная) | D118: 1 | E118: / | F118: 30 | G118: ='-'!G118 -> 1876.56 | J118: - | K118: =G118*I118 -> 0 | L118: 4673768180626 | N118: 4673768180633
B119: 634-708-072 | C119: Коронка алмазная по бетону 72мм (безударная) | D119: 1 | E119: / | F119: 30 | G119: ='-'!G119 -> 2024.4 | J119: - | K119: =G119*I119 -> 0 | L119: 4673768180640 | N119: 4673768180657
B120: 634-708-082 | C120: Коронка алмазная по бетону 82мм (безударная) | D120: 1 | E120: / | F120: 30 | G120: ='-'!G120 -> 1840.36 | J120: - | K120: =G120*I120 -> 0 | L120: 4673768180664 | N120: 4673768180671
B121: Коронки по керамической плитке
B122: 695-704-337 | C122: Набор коронок по керамической плитке (4 предм.: 33,53,67,73) | D122: 1 | E122: 5 | F122: 20 | G122: ='-'!G122 -> 1410.94 | J122: - | K122: =G122*I122 -> 0 | L122: 4673743524988 | N122: 4673743524995
B123: Коронка по стеклу с центрирующим сверлом
B124: 822-808-02055 | C124: Коронка по стеклу с центрирующим сверлом D 20 Х H 55 | D124: 1 | E124: 16 | F124: 400 | G124: ='-'!G124 -> 152.58 | J124: - | K124: =G124*I124 -> 0 | L124: 4673743520874 | N124: 4673743520843
B125: 822-808-02255 | C125: Коронка по стеклу с центрирующим сверлом D 22 Х H 55 РАСПРОДАЖА! | D125: 1 | E125: 16 | F125: 400 | G125: ='-'!G125 -> 118.75 | J125: - | K125: =G125*I125 -> 0 | L125: 4673743520881 | N125: 4673743520898
B126: 822-808-02555 | C126: Коронка по стеклу с центрирующим сверлом D 25 Х H 55 | D126: 1 | E126: 16 | F126: 288 | G126: ='-'!G126 -> 197.18 | J126: - | K126: =G126*I126 -> 0 | L126: 4673743521208 | N126: 4673743521215
B127: 822-808-02855 | C127: Коронка по стеклу с центрирующим сверлом D 28 Х H 55 | D127: 1 | E127: 16 | F127: 192 | G127: ='-'!G127 -> 217.69 | J127: - | K127: =G127*I127 -> 0 | L127: 4673743521222 | N127: 4673743521239
B128: 822-808-03055 | C128: Коронка по стеклу с центрирующим сверлом D 30 Х H 55 | D128: 1 | E128: 16 | F128: 192 | G128: ='-'!G128 -> 234.74 | J128: - | K128: =G128*I128 -> 0 | L128: 4673743521246 | N128: 4673743521253
B129: 822-808-03255 | C129: Коронка по стеклу с центрирующим сверлом D 32 Х H 55 | D129: 1 | E129: 10 | F129: 160 | G129: ='-'!G129 -> 257.57 | J129: - | K129: =G129*I129 -> 0 | L129: 4673743521260 | N129: 4673743521277
B130: 822-808-03555 | C130: Коронка по стеклу с центрирующим сверлом D 35 Х H 55 | D130: 1 | E130: 10 | F130: 160 | G130: ='-'!G130 -> 275.83 | J130: - | K130: =G130*I130 -> 0 | L130: 4673743521284 | N130: 4673743521291
B131: 822-808-04055 | C131: Коронка по стеклу с центрирующим сверлом D 40 Х H 55 | D131: 1 | E131: 8 | F131: 128 | G131: ='-'!G131 -> 324.82 | J131: - | K131: =G131*I131 -> 0 | L131: 4673743521307 | N131: 4673743521314
B132: 822-808-04255 | C132: Коронка по стеклу с центрирующим сверлом D 42 Х H 55 | D132: 1 | E132: 16 | F132: 128 | G132: ='-'!G132 -> 334.68 | J132: - | K132: =G132*I132 -> 0 | L132: 4673743521321 | N132: 4673743521338
B133: 822-808-04555 | C133: Коронка по стеклу с центрирующим сверлом D 45 Х H 55 | D133: 1 | E133: 16 | F133: 128 | G133: ='-'!G133 -> 369.72 | J133: - | K133: =G133*I133 -> 0 | L133: 4673743521345 | N133: 4673743521352
B134: 822-808-05055 | C134: Коронка по стеклу с центрирующим сверлом D 50 Х H 55 | D134: 1 | E134: 6 | F134: 96 | G134: ='-'!G134 -> 379.11 | J134: - | K134: =G134*I134 -> 0 | L134: 4673743521369 | N134: 4673743521376
B135: 822-808-05555 | C135: Коронка по стеклу с центрирующим сверлом D 55 Х H 55 | D135: 1 | E135: 10 | F135: 100 | G135: ='-'!G135 -> 455.49 | J135: - | K135: =G135*I135 -> 0 | L135: 4673743521383 | N135: 4673743521390
... B149: 822-808-12055 | C149: Коронка по стеклу с центрирующим сверлом D 120 Х H 55 | D149: 1 | E149: 10 | F149: 50 | G149: ='-'!G149 -> 1024.65 | J149: - | K149: =G149*I149 -> 0 | L149: 4673743521666 | N149: 4673743521673
B150: Пика SDS+
B151: 427-010-14250 | C151: Пика SDS+ (14X250) | D151: 1 | E151: 10 | F151: 100 | G151: ='-'!G151 -> 120.85 | J151: - | K151: =G151*I151 -> 0 | L151: 4673732411008 | N151: 4673732411015
B152: 427-010-14400 | C152: Пика SDS+ (14X400) | D152: 1 | E152: 10 | F152: 50 | G152: ='-'!G152 -> 199.53 | J152: - | K152: =G152*I152 -> 0 | L152: 4673732411022 | N152: 4673732411039
B153: Пика SDS MAX
B154: 425-010-18280 | C154: Пика SDS MAX (18X280) | D154: 1 | E154: 10 | F154: 50 | G154: ='-'!G154 -> 261.04 | J154: - | K154: =G154*I154 -> 0 | L154: 4673732410964 | N154: 4673732410971
B155: 425-010-18400 | C155: Пика SDS MAX (18X400) | D155: 1 | E155: 5 | F155: 25 | G155: ='-'!G155 -> 326.91 | J155: - | K155: =G155*I155 -> 0 | L155: 4673732410988 | N155: 4673732410995
B156: Сверло по стеклу цилиндрический хвостовик
B157: 432-010-06 | C157: Сверло по стеклу ц/х D6 | D157: 1 | E157: 50 | F157: 500 | G157: ='-'!G157 -> 81.72 | J157: - | K157: =G157*I157 -> 0 | L157: 4673732411046 | N157: 4673732411053
B158: 432-010-08 | C158: Сверло по стеклу ц/х D8 | D158: 1 | E158: 50 | F158: 500 | G158: ='-'!G158 -> 103.81 | J158: - | K158: =G158*I158 -> 0 | L158: 4673732411060 | N158: 4673732411077
B159: 432-010-10 | C159: Сверло по стеклу ц/х D10 | D159: 1 | E159: 50 | F159: 500 | G159: ='-'!G159 -> 137.2 | J159: - | K159: =G159*I159 -> 0 | L159: 4673759127869 | N159: 4673759127876
B160: 432-010-12 | C160: Сверло по стеклу ц/х D12 | D160: 1 | E160: 50 | F160: 500 | G160: ='-'!G160 -> 146.43 | J160: - | K160: =G160*I160 -> 0 | L160: 4673759127883 | N160: 4673759127890
B161: Сверло по стеклу шестигранный хвостовик (4х резцовое)
B162: 433-010-06 | C162: Сверло по стеклу ш/х 4х резц. D6 | D162: 1 | E162: 50 | F162: 500 | G162: ='-'!G162 -> 143.03 | J162: - | K162: =G162*I162 -> 0 | L162: 4673732411084 | N162: 4673732411091
B163: 433-010-08 | C163: Сверло по стеклу ш/х 4х резц. D8 | D163: 1 | E163: 50 | F163: 500 | G163: ='-'!G163 -> 157.29 | J163: - | K163: =G163*I163 -> 0 | L163: 4673732411107 | N163: 4673732411114
B164: 433-010-10 | C164: Сверло по стеклу ш/х 4х резц. D10 | D164: 1 | E164: 50 | F164: 500 | G164: ='-'!G164 -> 217.51 | J164: - | K164: =G164*I164 -> 0 | L164: 4673759127906 | N164: 4673759127913
B165: 433-010-12 | C165: Сверло по стеклу ш/х 4х резц. D12 | D165: 1 | E165: 50 | F165: 500 | G165: ='-'!G165 -> 230.05 | J165: - | K165: =G165*I165 -> 0 | L165: 4673759127920 | N165: 4673759127937
B166: Сверло по металлу HSS
B167: 435-010-0025 | C167: Сверло по металлу HSS D2,5 | D167: 10 | E167: 10 | F167: 600 | G167: ='-'!G167 -> 58.8 | J167: - | K167: =G167*I167 -> 0 | L167: 4673732411169 | N167: 4673732411176
B168: 435-010-003 | C168: Сверло по металлу HSS D3 | D168: 10 | E168: 10 | F168: 600 | G168: ='-'!G168 -> 65.91 | J168: - | K168: =G168*I168 -> 0 | L168: 4673732411183 | N168: 4673732411190
B169: 435-010-0032 | C169: Сверло по металлу HSS D3,2 | D169: 10 | E169: 10 | F169: 400 | G169: ='-'!G169 -> 67.6 | J169: - | K169: =G169*I169 -> 0 | L169: 4673732411206 | N169: 4673732411213
B170: 435-010-0035 | C170: Сверло по металлу HSS D3,5 | D170: 10 | E170: 10 | F170: 400 | G170: ='-'!G170 -> 82.83 | J170: - | K170: =G170*I170 -> 0 | L170: 4673732411220 | N170: 4673732411237
B171: 435-010-0038 | C171: Сверло по металлу HSS D3,8 | D171: 10 | E171: 10 | F171: 400 | G171: ='-'!G171 -> 83.14 | J171: - | K171: =G171*I171 -> 0 | L171: 4673732411244 | N171: 4673732411251
B172: 435-010-004 | C172: Сверло по металлу HSS D4 | D172: 10 | E172: 10 | F172: 400 | G172: ='-'!G172 -> 100.96 | J172: - | K172: =G172*I172 -> 0 | L172: 4673732411268 | N172: 4673732411275
B173: 435-010-0042 | C173: Сверло по металлу HSS D4,2 | D173: 10 | E173: 10 | F173: 200 | G173: ='-'!G173 -> 101.48 | J173: - | K173: =G173*I173 -> 0 | L173: 4673732411282 | N173: 4673732411299
B174: 435-010-0045 | C174: Сверло по металлу HSS D4,5 | D174: 10 | E174: 10 | F174: 200 | G174: ='-'!G174 -> 101.9 | J174: - | K174: =G174*I174 -> 0 | L174: 4673732411305 | N174: 4673732411312
B175: 435-010-0048 | C175: Сверло по металлу HSS D4,8 | D175: 10 | E175: 10 | F175: 200 | G175: ='-'!G175 -> 133.94 | J175: - | K175: =G175*I175 -> 0 | L175: 4673732411329 | N175: 4673732411336
B176: 435-010-005 | C176: Сверло по металлу HSS D5 | D176: 10 | E176: 10 | F176: 200 | G176: ='-'!G176 -> 131.33 | J176: - | K176: =G176*I176 -> 0 | L176: 4673732411343 | N176: 4673732411350
B177: 435-010-0052 | C177: Сверло по металлу HSS D5,2 РАСПРОДАЖА! | D177: 10 | E177: 10 | F177: 200 | G177: ='-'!G177 -> 93.75 | J177: - | K177: =G177*I177 -> 0 | L177: 4673732411367 | N177: 4673732411374
B178: 435-010-0055 | C178: Сверло по металлу HSS D5,5 | D178: 10 | E178: 5 | F178: 100 | G178: ='-'!G178 -> 163.98 | J178: - | K178: =G178*I178 -> 0 | L178: 4673732411381 | N178: 4673732411398
... B201: 435-010-0185 | C201: Сверло по металлу HSS D18,5 РАСПРОДАЖА! | D201: 1 | E201: 12 | F201: 60 | G201: ='-'!G201 -> 248.75 | J201: - | K201: =G201*I201 -> 0 | L201: 4673732411909 | N201: 4673732411916
B202: Сверло по металлу HSS (длинное, 300мм)
B203: 435-777-03300 | C203: Сверло по металлу HSS длинное L300 D3 | D203: 1 | E203: 50 | F203: 500 | G203: ='-'!G203 -> 110.19 | J203: - | K203: =G203*I203 -> 0 | L203: 4673743520829 | N203: 4673743520836
B204: 435-777-04300 | C204: Сверло по металлу HSS длинное L300 D4 | D204: 1 | E204: 50 | F204: 500 | G204: ='-'!G204 -> 101.19 | J204: - | K204: =G204*I204 -> 0 | L204: 4673743520980 | N204: 4673743520997
B205: 435-777-05300 | C205: Сверло по металлу HSS длинное L300 D5 | D205: 1 | E205: 50 | F205: 500 | G205: ='-'!G205 -> 146.78 | J205: - | K205: =G205*I205 -> 0 | L205: 4673743521000 | N205: 4673743521017
B206: 435-777-06300 | C206: Сверло по металлу HSS длинное L300 D6 | D206: 1 | E206: 50 | F206: 500 | G206: ='-'!G206 -> 176.19 | J206: - | K206: =G206*I206 -> 0 | L206: 4673743521024 | N206: 4673743521031
B207: 435-777-07300 | C207: Сверло по металлу HSS длинное L300 D7 | D207: 1 | E207: 50 | F207: 300 | G207: ='-'!G207 -> 193.24 | J207: - | K207: =G207*I207 -> 0 | L207: 4673743521048 | N207: 4673743521055
B208: 435-777-08300 | C208: Сверло по металлу HSS длинное L300 D8 | D208: 1 | E208: 50 | F208: 250 | G208: ='-'!G208 -> 233.5 | J208: - | K208: =G208*I208 -> 0 | L208: 4673743521062 | N208: 4673743521079
B209: 435-777-09300 | C209: Сверло по металлу HSS длинное L300 D9 | D209: 1 | E209: 50 | F209: 200 | G209: ='-'!G209 -> 275.76 | J209: - | K209: =G209*I209 -> 0 | L209: 4673743521086 | N209: 4673743521093
B210: 435-777-10300 | C210: Сверло по металлу HSS длинное L300 D10 | D210: 1 | E210: 15 | F210: 150 | G210: ='-'!G210 -> 337.81 | J210: - | K210: =G210*I210 -> 0 | L210: 4673743521109 | N210: 4673743521116
B211: 435-777-11300 | C211: Сверло по металлу HSS длинное L300 D11 | D211: 1 | E211: 20 | F211: 120 | G211: ='-'!G211 -> 398.26 | J211: - | K211: =G211*I211 -> 0 | L211: 4673743521123 | N211: 4673743521130
B212: 435-777-12300 | C212: Сверло по металлу HSS длинное L300 D12 | D212: 1 | E212: 20 | F212: 120 | G212: ='-'!G212 -> 365.04 | J212: - | K212: =G212*I212 -> 0 | L212: 4673743521147 | N212: 4673743521154
B213: 435-777-13300 | C213: Сверло по металлу HSS длинное L300 D13 | D213: 1 | E213: 20 | F213: 100 | G213: ='-'!G213 -> 452.09 | J213: - | K213: =G213*I213 -> 0 | L213: 4673743521161 | N213: 4673743521178
B214: 435-777-14300 | C214: Сверло по металлу HSS длинное L300 D14 | D214: 1 | E214: 20 | F214: 100 | G214: ='-'!G214 -> 531.25 | J214: - | K214: =G214*I214 -> 0 | L214: 4673743521185 | N214: 4673743521192
...

Sheet -
O1: Корректировка 03 Сентябрь
V3: FALSE | W3: Заграничный клиент, минус НДС
V4: FALSE | W4: Включить стоимость доставки в цену
V5: FALSE | W5: Оплата за наличные
A7: Сентябрь 2026 | J7: =G806 -> 0 | O7: Стоимость доставки по РФ за кг. | P7: 16 | V7: расчёт | AB7: Вес
A8: Изображение | B8: Артикул | C8: Наименование | D8: Единиц в комплекте | E8: Штук/ комплектов во внутр. коробке | F8: Штук/ комплектов в коробке | G8: Цена за штуку/комплект в руб. с НДС) | H8: Ваш заказ, штук/комплектов | I8: Комплекты в штуках | J8: Сумма заказа | K8: Штрих-код (штука) | L8: Штрих-код (комплект) | M8: Штрих-код (коробка) | O8: Скидка | P8: 0 | Q8: индивидуальная скидка | T8: min для ручного ввода | V8: коэфф max | W8: цена без скидки | X8: коэфф % | Y8: без округления | Z8: с округлением | AB8: Брутто за шт. | AC8: Итого, кг. | AD8: Стоимость доставки | AE8: Стоимость доставки за шт. | AF8: округление до 2х знаков | AH8: Округление до 2 знаков | AJ8: Если включить в стоимость доставку | AL8: Если оплата за наличку (-10%) | AN8: Если заграничный клиент (-НДС)
B9: Бур по бетону SDS+ | O9: Бур по бетону SDS+
B10: 402-010-6110 | C10: Бур по бетону SDS+ (6x110) | D10: 1 | E10: 50 | F10: 500 | G10: =AH10 -> 47.18 | I10: - | J10: =G10*H10 -> 0 | K10: 4673732410025 | M10: 4673732410032 | P10: =$P$8 -> 0 | R10: =IF(Q10>0,Q10,P10) -> 0 | S10: =IF(P10>18,"ПЕРЕБОР","-") -> - | T10: 37.74375 | V10: 1.25 | W10: =T10*V10 -> 47.179688 | X10: =R10*0.01 -> 0 | Y10: =W10-(W10*X10) -> 47.179688 | Z10: =ROUND(Y10,2) -> 47.18 | AB10: 0.042 | AC10: =H10*AB10 -> 0 | AD10: =AC10*$P$7 -> 0 | AE10: =AB10*$P$7 -> 0.672 | AF10: =ROUND(AE10,2) -> 0.67 | AH10: =ROUNDUP(AN10,2) -> 47.18 | AJ10: =IF($V$4,AL10+AF10,AL10) -> 47.18 | AL10: =IF($V$5,Z10-Z10*10%,Z10) -> 47.18 | AN10: =IF($V$3,AJ10-((AJ10*1.18031)-AJ10),AJ10) -> 47.18
B11: 402-010-6160 | C11: Бур по бетону SDS+ (6x160) | D11: 1 | E11: 50 | F11: 500 | G11: =AH11 -> 50.05 | I11: - | J11: =G11*H11 -> 0 | K11: 4673732410049 | M11: 4673732410056 | P11: =$P$8 -> 0 | R11: =IF(Q11>0,Q11,P11) -> 0 | S11: =IF(P11>18,"ПЕРЕБОР","-") -> - | T11: 40.03875 | V11: 1.25 | W11: =T11*V11 -> 50.048438 | X11: =R11*0.01 -> 0 | Y11: =W11-(W11*X11) -> 50.048438 | Z11: =ROUND(Y11,2) -> 50.05 | AB11: 0.05 | AC11: =H11*AB11 -> 0 | AD11: =AC11*$P$7 -> 0 | AE11: =AB11*$P$7 -> 0.8 | AF11: =ROUND(AE11,2) -> 0.8 | AH11: =ROUNDUP(AN11,2) -> 50.05 | AJ11: =IF($V$4,AL11+AF11,AL11) -> 50.05 | AL11: =IF($V$5,Z11-Z11*10%,Z11) -> 50.05 | AN11: =IF($V$3,AJ11-((AJ11*1.18031)-AJ11),AJ11) -> 50.05
B12: 402-010-6210 | C12: Бур по бетону SDS+ (6x210) | D12: 1 | E12: 50 | F12: 300 | G12: =AH12 -> 61.88 | I12: - | J12: =G12*H12 -> 0 | K12: 4673732410063 | M12: 4673732410070 | P12: =$P$8 -> 0 | R12: =IF(Q12>0,Q12,P12) -> 0 | S12: =IF(P12>18,"ПЕРЕБОР","-") -> - | T12: 49.5 | V12: 1.25 | W12: =T12*V12 -> 61.875 | X12: =R12*0.01 -> 0 | Y12: =W12-(W12*X12) -> 61.875 | Z12: =ROUND(Y12,2) -> 61.88 | AB12: 0.056666667 | AC12: =H12*AB12 -> 0 | AD12: =AC12*$P$7 -> 0 | AE12: =AB12*$P$7 -> 0.90666667 | AF12: =ROUND(AE12,2) -> 0.91 | AH12: =ROUNDUP(AN12,2) -> 61.88 | AJ12: =IF($V$4,AL12+AF12,AL12) -> 61.88 | AL12: =IF($V$5,Z12-Z12*10%,Z12) -> 61.88 | AN12: =IF($V$3,AJ12-((AJ12*1.18031)-AJ12),AJ12) -> 61.88
B13: 402-010-6260 | C13: Бур по бетону SDS+ (6x260) | D13: 1 | E13: 50 | F13: 250 | G13: =AH13 -> 76.86 | I13: - | J13: =G13*H13 -> 0 | K13: 4673732410087 | M13: 4673732410094 | P13: =$P$8 -> 0 | R13: =IF(Q13>0,Q13,P13) -> 0 | S13: =IF(P13>18,"ПЕРЕБОР","-") -> - | T13: 61.49 | V13: 1.25 | W13: =T13*V13 -> 76.8625 | X13: =R13*0.01 -> 0 | Y13: =W13-(W13*X13) -> 76.8625 | Z13: =ROUND(Y13,2) -> 76.86 | AB13: 0.072 | AC13: =H13*AB13 -> 0 | AD13: =AC13*$P$7 -> 0 | AE13: =AB13*$P$7 -> 1.152 | AF13: =ROUND(AE13,2) -> 1.15 | AH13: =ROUNDUP(AN13,2) -> 76.86 | AJ13: =IF($V$4,AL13+AF13,AL13) -> 76.86 | AL13: =IF($V$5,Z13-Z13*10%,Z13) -> 76.86 | AN13: =IF($V$3,AJ13-((AJ13*1.18031)-AJ13),AJ13) -> 76.86
B14: 402-010-6310 | C14: Бур по бетону SDS+ (6x310) | D14: 1 | E14: 50 | F14: 200 | G14: =AH14 -> 83.19 | I14: - | J14: =G14*H14 -> 0 | K14: 4673732410100 | M14: 4673732410117 | P14: =$P$8 -> 0 | R14: =IF(Q14>0,Q14,P14) -> 0 | S14: =IF(P14>18,"ПЕРЕБОР","-") -> - | T14: 66.55 | V14: 1.25 | W14: =T14*V14 -> 83.1875 | X14: =R14*0.01 -> 0 | Y14: =W14-(W14*X14) -> 83.1875 | Z14: =ROUND(Y14,2) -> 83.19 | AB14: 0.08 | AC14: =H14*AB14 -> 0 | AD14: =AC14*$P$7 -> 0 | AE14: =AB14*$P$7 -> 1.28 | AF14: =ROUND(AE14,2) -> 1.28 | AH14: =ROUNDUP(AN14,2) -> 83.19 | AJ14: =IF($V$4,AL14+AF14,AL14) -> 83.19 | AL14: =IF($V$5,Z14-Z14*10%,Z14) -> 83.19 | AN14: =IF($V$3,AJ14-((AJ14*1.18031)-AJ14),AJ14) -> 83.19
B15: 402-010-6350 | C15: Бур по бетону SDS+ (6x350) | D15: 1 | E15: 50 | F15: 200 | G15: =AH15 -> 96.51 | I15: - | J15: =G15*H15 -> 0 | K15: 4673732410124 | M15: 4673732410131 | P15: =$P$8 -> 0 | R15: =IF(Q15>0,Q15,P15) -> 0 | S15: =IF(P15>18,"ПЕРЕБОР","-") -> - | T15: 77.21 | V15: 1.25 | W15: =T15*V15 -> 96.5125 | X15: =R15*0.01 -> 0 | Y15: =W15-(W15*X15) -> 96.5125 | Z15: =ROUND(Y15,2) -> 96.51 | AB15: 0.1 | AC15: =H15*AB15 -> 0 | AD15: =AC15*$P$7 -> 0 | AE15: =AB15*$P$7 -> 1.6 | AF15: =ROUND(AE15,2) -> 1.6 | AH15: =ROUNDUP(AN15,2) -> 96.51 | AJ15: =IF($V$4,AL15+AF15,AL15) -> 96.51 | AL15: =IF($V$5,Z15-Z15*10%,Z15) -> 96.51 | AN15: =IF($V$3,AJ15-((AJ15*1.18031)-AJ15),AJ15) -> 96.51
B16: 402-010-6410 | C16: Бур по бетону SDS+ (6x410) РАСПРОДАЖА! | D16: 1 | E16: 50 | F16: 200 | G16: =AH16 -> 102.69 | I16: - | J16: =G16*H16 -> 0 | K16: 4673732410148 | M16: 4673732410155 | P16: =$P$8 -> 0 | R16: =IF(Q16>0,Q16,P16) -> 0 | S16: =IF(P16>18,"ПЕРЕБОР","-") -> - | T16: 82.15 | V16: 1.25 | W16: =T16*V16 -> 102.6875 | X16: =R16*0.01 -> 0 | Y16: =W16-(W16*X16) -> 102.6875 | Z16: =ROUND(Y16,2) -> 102.69 | AB16: 0.1 | AC16: =H16*AB16 -> 0 | AD16: =AC16*$P$7 -> 0 | AE16: =AB16*$P$7 -> 1.6 | AF16: =ROUND(AE16,2) -> 1.6 | AH16: =ROUNDUP(AN16,2) -> 102.69 | AJ16: =IF($V$4,AL16+AF16,AL16) -> 102.69 | AL16: =IF($V$5,Z16-Z16*10%,Z16) -> 102.69 | AN16: =IF($V$3,AJ16-((AJ16*1.18031)-AJ16),AJ16) -> 102.69
B17: 402-010-8110 | C17: Бур по бетону SDS+ (8x110) | D17: 1 | E17: 50 | F17: 500 | G17: =AH17 -> 47.5 | I17: - | J17: =G17*H17 -> 0 | K17: 4673732410162 | M17: 4673732410179 | P17: =$P$8 -> 0 | R17: =IF(Q17>0,Q17,P17) -> 0 | S17: =IF(P17>18,"ПЕРЕБОР","-") -> - | T17: 38 | V17: 1.25 | W17: =T17*V17 -> 47.5 | X17: =R17*0.01 -> 0 | Y17: =W17-(W17*X17) -> 47.5 | Z17: =ROUND(Y17,2) -> 47.5 | AB17: 0.046 | AC17: =H17*AB17 -> 0 | AD17: =AC17*$P$7 -> 0 | AE17: =AB17*$P$7 -> 0.736 | AF17: =ROUND(AE17,2) -> 0.74 | AH17: =ROUNDUP(AN17,2) -> 47.5 | AJ17: =IF($V$4,AL17+AF17,AL17) -> 47.5 | AL17: =IF($V$5,Z17-Z17*10%,Z17) -> 47.5 | AN17: =IF($V$3,AJ17-((AJ17*1.18031)-AJ17),AJ17) -> 47.5
B18: 402-010-8160 | C18: Бур по бетону SDS+ (8x160) | D18: 1 | E18: 50 | F18: 500 | G18: =AH18 -> 61.88 | I18: - | J18: =G18*H18 -> 0 | K18: 4673732410186 | M18: 4673732410193 | P18: =$P$8 -> 0 | R18: =IF(Q18>0,Q18,P18) -> 0 | S18: =IF(P18>18,"ПЕРЕБОР","-") -> - | T18: 49.5 | V18: 1.25 | W18: =T18*V18 -> 61.875 | X18: =R18*0.01 -> 0 | Y18: =W18-(W18*X18) -> 61.875 | Z18: =ROUND(Y18,2) -> 61.88 | AB18: 0.058 | AC18: =H18*AB18 -> 0 | AD18: =AC18*$P$7 -> 0 | AE18: =AB18*$P$7 -> 0.928 | AF18: =ROUND(AE18,2) -> 0.93 | AH18: =ROUNDUP(AN18,2) -> 61.88 | AJ18: =IF($V$4,AL18+AF18,AL18) -> 61.88 | AL18: =IF($V$5,Z18-Z18*10%,Z18) -> 61.88 | AN18: =IF($V$3,AJ18-((AJ18*1.18031)-AJ18),AJ18) -> 61.88
B19: 402-010-8210 | C19: Бур по бетону SDS+ (8x210) | D19: 1 | E19: 50 | F19: 250 | G19: =AH19 -> 75.13 | I19: - | J19: =G19*H19 -> 0 | K19: 4673732410209 | M19: 4673732410216 | P19: =$P$8 -> 0 | R19: =IF(Q19>0,Q19,P19) -> 0 | S19: =IF(P19>18,"ПЕРЕБОР","-") -> - | T19: 60.104 | V19: 1.25 | W19: =T19*V19 -> 75.13 | X19: =R19*0.01 -> 0 | Y19: =W19-(W19*X19) -> 75.13 | Z19: =ROUND(Y19,2) -> 75.13 | AB19: 0.076 | AC19: =H19*AB19 -> 0 | AD19: =AC19*$P$7 -> 0 | AE19: =AB19*$P$7 -> 1.216 | AF19: =ROUND(AE19,2) -> 1.22 | AH19: =ROUNDUP(AN19,2) -> 75.13 | AJ19: =IF($V$4,AL19+AF19,AL19) -> 75.13 | AL19: =IF($V$5,Z19-Z19*10%,Z19) -> 75.13 | AN19: =IF($V$3,AJ19-((AJ19*1.18031)-AJ19),AJ19) -> 75.13
B20: 402-010-8260 | C20: Бур по бетону SDS+ (8x260) | D20: 1 | E20: 50 | F20: 200 | G20: =AH20 -> 78.75 | I20: - | J20: =G20*H20 -> 0 | K20: 4673732410223 | M20: 4673732410230 | P20: =$P$8 -> 0 | R20: =IF(Q20>0,Q20,P20) -> 0 | S20: =IF(P20>18,"ПЕРЕБОР","-") -> - | T20: 63 | V20: 1.25 | W20: =T20*V20 -> 78.75 | X20: =R20*0.01 -> 0 | Y20: =W20-(W20*X20) -> 78.75 | Z20: =ROUND(Y20,2) -> 78.75 | AB20: 0.105 | AC20: =H20*AB20 -> 0 | AD20: =AC20*$P$7 -> 0 | AE20: =AB20*$P$7 -> 1.68 | AF20: =ROUND(AE20,2) -> 1.68 | AH20: =ROUNDUP(AN20,2) -> 78.75 | AJ20: =IF($V$4,AL20+AF20,AL20) -> 78.75 | AL20: =IF($V$5,Z20-Z20*10%,Z20) -> 78.75 | AN20: =IF($V$3,AJ20-((AJ20*1.18031)-AJ20),AJ20) -> 78.75
B21: 402-010-8310 | C21: Бур по бетону SDS+ (8x310) | D21: 1 | E21: 50 | F21: 100 | G21: =AH21 -> 86.25 | I21: - | J21: =G21*H21 -> 0 | K21: 4673732410247 | M21: 4673732410254 | P21: =$P$8 -> 0 | R21: =IF(Q21>0,Q21,P21) -> 0 | S21: =IF(P21>18,"ПЕРЕБОР","-") -> - | T21: 69 | V21: 1.25 | W21: =T21*V21 -> 86.25 | X21: =R21*0.01 -> 0 | Y21: =W21-(W21*X21) -> 86.25 | Z21: =ROUND(Y21,2) -> 86.25 | AB21: 0.12 | AC21: =H21*AB21 -> 0 | AD21: =AC21*$P$7 -> 0 | AE21: =AB21*$P$7 -> 1.92 | AF21: =ROUND(AE21,2) -> 1.92 | AH21: =ROUNDUP(AN21,2) -> 86.25 | AJ21: =IF($V$4,AL21+AF21,AL21) -> 86.25 | AL21: =IF($V$5,Z21-Z21*10%,Z21) -> 86.25 | AN21: =IF($V$3,AJ21-((AJ21*1.18031)-AJ21),AJ21) -> 86.25
... B92: 402-010-22460 | C92: Бур по бетону SDS+ (22х460) | D92: 1 | E92: 25 | F92: 25 | G92: =AH92 -> 372.64 | I92: - | J92: =G92*H92 -> 0 | K92: 4673759127746 | M92: 4673759127753 | P92: =$P$8 -> 0 | R92: =IF(Q92>0,Q92,P92) -> 0 | S92: =IF(P92>18,"ПЕРЕБОР","-") -> - | T92: 298.11 | V92: 1.25 | W92: =T92*V92 -> 372.6375 | X92: =R92*0.01 -> 0 | Y92: =W92-(W92*X92) -> 372.6375 | Z92: =ROUND(Y92,2) -> 372.64 | AB92: 0.56 | AC92: =H92*AB92 -> 0 | AD92: =AC92*$P$7 -> 0 | AE92: =AB92*$P$7 -> 8.96 | AF92: =ROUND(AE92,2) -> 8.96 | AH92: =ROUNDUP(AN92,2) -> 372.64 | AJ92: =IF($V$4,AL92+AF92,AL92) -> 372.64 | AL92: =IF($V$5,Z92-Z92*10%,Z92) -> 372.64 | AN92: =IF($V$3,AJ92-((AJ92*1.18031)-AJ92),AJ92) -> 372.64
B93: Зубило SDS+ | O93: Зубило SDS+
B94: 411-010-1425020 | C94: Зубило SDS+ (14x250x20) | D94: 1 | E94: 10 | F94: 100 | G94: =AH94 -> 126.39 | I94: - | J94: =G94*H94 -> 0 | K94: 4673732410780 | M94: 4673732410797 | P94: =$P$8 -> 0 | R94: =IF(Q94>0,Q94,P94) -> 0 | S94: =IF(P94>18,"ПЕРЕБОР","-") -> - | T94: 101.112 | V94: 1.25 | W94: =T94*V94 -> 126.39 | X94: =R94*0.01 -> 0 | Y94: =W94-(W94*X94) -> 126.39 | Z94: =ROUND(Y94,2) -> 126.39 | AB94: 0.25 | AC94: =H94*AB94 -> 0 | AD94: =AC94*$P$7 -> 0 | AE94: =AB94*$P$7 -> 4 | AF94: =ROUND(AE94,2) -> 4 | AH94: =ROUNDUP(AN94,2) -> 126.39 | AJ94: =IF($V$4,AL94+AF94,AL94) -> 126.39 | AL94: =IF($V$5,Z94-Z94*10%,Z94) -> 126.39 | AN94: =IF($V$3,AJ94-((AJ94*1.18031)-AJ94),AJ94) -> 126.39
B95: 411-010-1425050 | C95: Зубило SDS+ (14x250x50) | D95: 1 | E95: 10 | F95: 100 | G95: =AH95 -> 183.48 | I95: - | J95: =G95*H95 -> 0 | K95: 4673732410803 | M95: 4673732410810 | P95: =$P$8 -> 0 | R95: =IF(Q95>0,Q95,P95) -> 0 | S95: =IF(P95>18,"ПЕРЕБОР","-") -> - | T95: 146.784 | V95: 1.25 | W95: =T95*V95 -> 183.48 | X95: =R95*0.01 -> 0 | Y95: =W95-(W95*X95) -> 183.48 | Z95: =ROUND(Y95,2) -> 183.48 | AB95: 0.29 | AC95: =H95*AB95 -> 0 | AD95: =AC95*$P$7 -> 0 | AE95: =AB95*$P$7 -> 4.64 | AF95: =ROUND(AE95,2) -> 4.64 | AH95: =ROUNDUP(AN95,2) -> 183.48 | AJ95: =IF($V$4,AL95+AF95,AL95) -> 183.48 | AL95: =IF($V$5,Z95-Z95*10%,Z95) -> 183.48 | AN95: =IF($V$3,AJ95-((AJ95*1.18031)-AJ95),AJ95) -> 183.48
B96: 411-010-1440020 | C96: Зубило SDS+ (14x400x20) | D96: 1 | E96: 10 | F96: 50 | G96: =AH96 -> 216.25 | I96: - | J96: =G96*H96 -> 0 | K96: 4673768180541 | M96: 4673768180558 | P96: =$P$8 -> 0 | R96: =IF(Q96>0,Q96,P96) -> 0 | S96: =IF(P96>18,"ПЕРЕБОР","-") -> - | T96: 173 | V96: 1.25 | W96: =T96*V96 -> 216.25 | X96: =R96*0.01 -> 0 | Y96: =W96-(W96*X96) -> 216.25 | Z96: =ROUND(Y96,2) -> 216.25 | AB96: 0.44 | AC96: =H96*AB96 -> 0 | AD96: =AC96*$P$7 -> 0 | AE96: =AB96*$P$7 -> 7.04 | AF96: =ROUND(AE96,2) -> 7.04 | AH96: =ROUNDUP(AN96,2) -> 216.25 | AJ96: =IF($V$4,AL96+AF96,AL96) -> 216.25 | AL96: =IF($V$5,Z96-Z96*10%,Z96) -> 216.25 | AN96: =IF($V$3,AJ96-((AJ96*1.18031)-AJ96),AJ96) -> 216.25
B97: 411-010-1440050 | C97: Зубило SDS+ (14x400x50) | D97: 1 | E97: 10 | F97: 50 | G97: =AH97 -> 287.56 | I97: - | J97: =G97*H97 -> 0 | K97: 4673768180565 | M97: 4673768180572 | P97: =$P$8 -> 0 | R97: =IF(Q97>0,Q97,P97) -> 0 | S97: =IF(P97>18,"ПЕРЕБОР","-") -> - | T97: 230.05 | V97: 1.25 | W97: =T97*V97 -> 287.5625 | X97: =R97*0.01 -> 0 | Y97: =W97-(W97*X97) -> 287.5625 | Z97: =ROUND(Y97,2) -> 287.56 | AB97: 0.5 | AC97: =H97*AB97 -> 0 | AD97: =AC97*$P$7 -> 0 | AE97: =AB97*$P$7 -> 8 | AF97: =ROUND(AE97,2) -> 8 | AH97: =ROUNDUP(AN97,2) -> 287.56 | AJ97: =IF($V$4,AL97+AF97,AL97) -> 287.56 | AL97: =IF($V$5,Z97-Z97*10%,Z97) -> 287.56 | AN97: =IF($V$3,AJ97-((AJ97*1.18031)-AJ97),AJ97) -> 287.56
B98: 411-010-1460020 | C98: Зубило SDS+ (14x600x20) | D98: 1 | E98: 5 | F98: 25 | G98: =AH98 -> 310.56 | I98: - | J98: =G98*H98 -> 0 | K98: 4673768180589 | M98: 4673768180596 | P98: =$P$8 -> 0 | R98: =IF(Q98>0,Q98,P98) -> 0 | S98: =IF(P98>18,"ПЕРЕБОР","-") -> - | T98: 248.45 | V98: 1.25 | W98: =T98*V98 -> 310.5625 | X98: =R98*0.01 -> 0 | Y98: =W98-(W98*X98) -> 310.5625 | Z98: =ROUND(Y98,2) -> 310.56 | AB98: 0.72 | AC98: =H98*AB98 -> 0 | AD98: =AC98*$P$7 -> 0 | AE98: =AB98*$P$7 -> 11.52 | AF98: =ROUND(AE98,2) -> 11.52 | AH98: =ROUNDUP(AN98,2) -> 310.56 | AJ98: =IF($V$4,AL98+AF98,AL98) -> 310.56 | AL98: =IF($V$5,Z98-Z98*10%,Z98) -> 310.56 | AN98: =IF($V$3,AJ98-((AJ98*1.18031)-AJ98),AJ98) -> 310.56
B99: 411-010-1460050 | C99: Зубило SDS+ (14x600x50) | D99: 1 | E99: 5 | F99: 25 | G99: =AH99 -> 411.9 | I99: - | J99: =G99*H99 -> 0 | K99: 4673768180602 | M99: 4673768180619 | P99: =$P$8 -> 0 | R99: =IF(Q99>0,Q99,P99) -> 0 | S99: =IF(P99>18,"ПЕРЕБОР","-") -> - | T99: 329.5215 | V99: 1.25 | W99: =T99*V99 -> 411.90188 | X99: =R99*0.01 -> 0 | Y99: =W99-(W99*X99) -> 411.90188 | Z99: =ROUND(Y99,2) -> 411.9 | AB99: 0.8 | AC99: =H99*AB99 -> 0 | AD99: =AC99*$P$7 -> 0 | AE99: =AB99*$P$7 -> 12.8 | AF99: =ROUND(AE99,2) -> 12.8 | AH99: =ROUNDUP(AN99,2) -> 411.9 | AJ99: =IF($V$4,AL99+AF99,AL99) -> 411.9 | AL99: =IF($V$5,Z99-Z99*10%,Z99) -> 411.9 | AN99: =IF($V$3,AJ99-((AJ99*1.18031)-AJ99),AJ99) -> 411.9
B100: Коронка по бетону SDS+ | O100: Коронка по бетону SDS+
B101: 422-010-30 | C101: Коронка по бетону SDS+ D30 | D101: 1 | E101: / | F101: 50 | G101: =AH101 -> 351.13 | I101: - | J101: =G101*H101 -> 0 | K101: 4673759127760 | M101: 4673759127777 | P101: =$P$8 -> 0 | R101: =IF(Q101>0,Q101,P101) -> 0 | S101: =IF(P101>18,"ПЕРЕБОР","-") -> - | T101: 280.9 | V101: 1.25 | W101: =T101*V101 -> 351.125 | X101: =R101*0.01 -> 0 | Y101: =W101-(W101*X101) -> 351.125 | Z101: =ROUND(Y101,2) -> 351.13 | AB101: 0.4 | AC101: =H101*AB101 -> 0 | AD101: =AC101*$P$7 -> 0 | AE101: =AB101*$P$7 -> 6.4 | AF101: =ROUND(AE101,2) -> 6.4 | AH101: =ROUNDUP(AN101,2) -> 351.13 | AJ101: =IF($V$4,AL101+AF101,AL101) -> 351.13 | AL101: =IF($V$5,Z101-Z101*10%,Z101) -> 351.13 | AN101: =IF($V$3,AJ101-((AJ101*1.18031)-AJ101),AJ101) -> 351.13
B102: 422-010-35 | C102: Коронка по бетону SDS+ D35 | D102: 1 | E102: / | F102: 50 | G102: =AH102 -> 364.48 | I102: - | J102: =G102*H102 -> 0 | K102: 4673759127784 | M102: 4673759127791 | P102: =$P$8 -> 0 | R102: =IF(Q102>0,Q102,P102) -> 0 | S102: =IF(P102>18,"ПЕРЕБОР","-") -> - | T102: 291.58 | V102: 1.25 | W102: =T102*V102 -> 364.475 | X102: =R102*0.01 -> 0 | Y102: =W102-(W102*X102) -> 364.475 | Z102: =ROUND(Y102,2) -> 364.48 | AB102: 0.42 | AC102: =H102*AB102 -> 0 | AD102: =AC102*$P$7 -> 0 | AE102: =AB102*$P$7 -> 6.72 | AF102: =ROUND(AE102,2) -> 6.72 | AH102: =ROUNDUP(AN102,2) -> 364.48 | AJ102: =IF($V$4,AL102+AF102,AL102) -> 364.48 | AL102: =IF($V$5,Z102-Z102*10%,Z102) -> 364.48 | AN102: =IF($V$3,AJ102-((AJ102*1.18031)-AJ102),AJ102) -> 364.48
B103: 422-010-40 | C103: Коронка по бетону SDS+ D40 | D103: 1 | E103: / | F103: 50 | G103: =AH103 -> 438.6 | I103: - | J103: =G103*H103 -> 0 | K103: 4673759127807 | M103: 4673759127814 | P103: =$P$8 -> 0 | R103: =IF(Q103>0,Q103,P103) -> 0 | S103: =IF(P103>18,"ПЕРЕБОР","-") -> - | T103: 350.88 | V103: 1.25 | W103: =T103*V103 -> 438.6 | X103: =R103*0.01 -> 0 | Y103: =W103-(W103*X103) -> 438.6 | Z103: =ROUND(Y103,2) -> 438.6 | AB103: 0.44 | AC103: =H103*AB103 -> 0 | AD103: =AC103*$P$7 -> 0 | AE103: =AB103*$P$7 -> 7.04 | AF103: =ROUND(AE103,2) -> 7.04 | AH103: =ROUNDUP(AN103,2) -> 438.6 | AJ103: =IF($V$4,AL103+AF103,AL103) -> 438.6 | AL103: =IF($V$5,Z103-Z103*10%,Z103) -> 438.6 | AN103: =IF($V$3,AJ103-((AJ103*1.18031)-AJ103),AJ103) -> 438.6
B104: 422-010-45 | C104: Коронка по бетону SDS+ D45 | D104: 1 | E104: / | F104: 50 | G104: =AH104 -> 547 | I104: - | J104: =G104*H104 -> 0 | K104: 4673732414535 | M104: 4673732414542 | P104: =$P$8 -> 0 | R104: =IF(Q104>0,Q104,P104) -> 0 | S104: =IF(P104>18,"ПЕРЕБОР","-") -> - | T104: 437.602 | V104: 1.25 | W104: =T104*V104 -> 547.0025 | X104: =R104*0.01 -> 0 | Y104: =W104-(W104*X104) -> 547.0025 | Z104: =ROUND(Y104,2) -> 547 | AB104: 0.49 | AC104: =H104*AB104 -> 0 | AD104: =AC104*$P$7 -> 0 | AE104: =AB104*$P$7 -> 7.84 | AF104: =ROUND(AE104,2) -> 7.84 | AH104: =ROUNDUP(AN104,2) -> 547 | AJ104: =IF($V$4,AL104+AF104,AL104) -> 547 | AL104: =IF($V$5,Z104-Z104*10%,Z104) -> 547 | AN104: =IF($V$3,AJ104-((AJ104*1.18031)-AJ104),AJ104) -> 547
B105: 422-010-50 | C105: Коронка по бетону SDS+ D50 | D105: 1 | E105: / | F105: 50 | G105: =AH105 -> 586.84 | I105: - | J105: =G105*H105 -> 0 | K105: 4673732414566 | M105: 4673732414559 | P105: =$P$8 -> 0 | R105: =IF(Q105>0,Q105,P105) -> 0 | S105: =IF(P105>18,"ПЕРЕБОР","-") -> - | T105: 469.475 | V105: 1.25 | W105: =T105*V105 -> 586.84375 | X105: =R105*0.01 -> 0 | Y105: =W105-(W105*X105) -> 586.84375 | Z105: =ROUND(Y105,2) -> 586.84 | AB105: 0.56 | AC105: =H105*AB105 -> 0 | AD105: =AC105*$P$7 -> 0 | AE105: =AB105*$P$7 -> 8.96 | AF105: =ROUND(AE105,2) -> 8.96 | AH105: =ROUNDUP(AN105,2) -> 586.84 | AJ105: =IF($V$4,AL105+AF105,AL105) -> 586.84 | AL105: =IF($V$5,Z105-Z105*10%,Z105) -> 586.84 | AN105: =IF($V$3,AJ105-((AJ105*1.18031)-AJ105),AJ105) -> 586.84
B106: 422-010-55 | C106: Коронка по бетону SDS+ D55 | D106: 1 | E106: / | F106: 20 | G106: =AH106 -> 481.84 | I106: - | J106: =G106*H106 -> 0 | K106: 4673732414597 | M106: 4673732414603 | P106: =$P$8 -> 0 | R106: =IF(Q106>0,Q106,P106) -> 0 | S106: =IF(P106>18,"ПЕРЕБОР","-") -> - | T106: 385.47 | V106: 1.25 | W106: =T106*V106 -> 481.8375 | X106: =R106*0.01 -> 0 | Y106: =W106-(W106*X106) -> 481.8375 | Z106: =ROUND(Y106,2) -> 481.84 | AB106: 0.6 | AC106: =H106*AB106 -> 0 | AD106: =AC106*$P$7 -> 0 | AE106: =AB106*$P$7 -> 9.6 | AF106: =ROUND(AE106,2) -> 9.6 | AH106: =ROUNDUP(AN106,2) -> 481.84 | AJ106: =IF($V$4,AL106+AF106,AL106) -> 481.84 | AL106: =IF($V$5,Z106-Z106*10%,Z106) -> 481.84 | AN106: =IF($V$3,AJ106-((AJ106*1.18031)-AJ106),AJ106) -> 481.84
B107: 422-010-60 | C107: Коронка по бетону SDS+ D60 | D107: 1 | E107: / | F107: 20 | G107: =AH107 -> 506.55 | I107: - | J107: =G107*H107 -> 0 | K107: 4673732414610 | M107: 4673732414627 | P107: =$P$8 -> 0 | R107: =IF(Q107>0,Q107,P107) -> 0 | S107: =IF(P107>18,"ПЕРЕБОР","-") -> - | T107: 405.24 | V107: 1.25 | W107: =T107*V107 -> 506.55 | X107: =R107*0.01 -> 0 | Y107: =W107-(W107*X107) -> 506.55 | Z107: =ROUND(Y107,2) -> 506.55 | AB107: 0.65 | AC107: =H107*AB107 -> 0 | AD107: =AC107*$P$7 -> 0 | AE107: =AB107*$P$7 -> 10.4 | AF107: =ROUND(AE107,2) -> 10.4 | AH107: =ROUNDUP(AN107,2) -> 506.55 | AJ107: =IF($V$4,AL107+AF107,AL107) -> 506.55 | AL107: =IF($V$5,Z107-Z107*10%,Z107) -> 506.55 | AN107: =IF($V$3,AJ107-((AJ107*1.18031)-AJ107),AJ107) -> 506.55
B108: 422-010-65 | C108: Коронка по бетону SDS+ D65 | D108: 1 | E108: / | F108: 20 | G108: =AH108 -> 647.19 | I108: - | J108: =G108*H108 -> 0 | K108: 4673732410827 | M108: 4673732410834 | P108: =$P$8 -> 0 | R108: =IF(Q108>0,Q108,P108) -> 0 | S108: =IF(P108>18,"ПЕРЕБОР","-") -> - | T108: 517.753 | V108: 1.25 | W108: =T108*V108 -> 647.19125 | X108: =R108*0.01 -> 0 | Y108: =W108-(W108*X108) -> 647.19125 | Z108: =ROUND(Y108,2) -> 647.19 | AB108: 0.8 | AC108: =H108*AB108 -> 0 | AD108: =AC108*$P$7 -> 0 | AE108: =AB108*$P$7 -> 12.8 | AF108: =ROUND(AE108,2) -> 12.8 | AH108: =ROUNDUP(AN108,2) -> 647.19 | AJ108: =IF($V$4,AL108+AF108,AL108) -> 647.19 | AL108: =IF($V$5,Z108-Z108*10%,Z108) -> 647.19 | AN108: =IF($V$3,AJ108-((AJ108*1.18031)-AJ108),AJ108) -> 647.19
B109: 422-010-68 | C109: Коронка по бетону SDS+ D68 | D109: 1 | E109: / | F109: 20 | G109: =AH109 -> 700.16 | I109: - | J109: =G109*H109 -> 0 | K109: 4673732410841 | M109: 4673732410858 | P109: =$P$8 -> 0 | R109: =IF(Q109>0,Q109,P109) -> 0 | S109: =IF(P109>18,"ПЕРЕБОР","-") -> - | T109: 560.1305 | V109: 1.25 | W109: =T109*V109 -> 700.16313 | X109: =R109*0.01 -> 0 | Y109: =W109-(W109*X109) -> 700.16313 | Z109: =ROUND(Y109,2) -> 700.16 | AB109: 0.85 | AC109: =H109*AB109 -> 0 | AD109: =AC109*$P$7 -> 0 | AE109: =AB109*$P$7 -> 13.6 | AF109: =ROUND(AE109,2) -> 13.6 | AH109: =ROUNDUP(AN109,2) -> 700.16 | AJ109: =IF($V$4,AL109+AF109,AL109) -> 700.16 | AL109: =IF($V$5,Z109-Z109*10%,Z109) -> 700.16 | AN109: =IF($V$3,AJ109-((AJ109*1.18031)-AJ109),AJ109) -> 700.16
B110: 422-010-70 | C110: Коронка по бетону SDS+ D70 | D110: 1 | E110: / | F110: 20 | G110: =AH110 -> 734.95 | I110: - | J110: =G110*H110 -> 0 | K110: 4673732410865 | M110: 4673732410872 | P110: =$P$8 -> 0 | R110: =IF(Q110>0,Q110,P110) -> 0 | S110: =IF(P110>18,"ПЕРЕБОР","-") -> - | T110: 587.961 | V110: 1.25 | W110: =T110*V110 -> 734.95125 | X110: =R110*0.01 -> 0 | Y110: =W110-(W110*X110) -> 734.95125 | Z110: =ROUND(Y110,2) -> 734.95 | AB110: 0.875 | AC110: =H110*AB110 -> 0 | AD110: =AC110*$P$7 -> 0 | AE110: =AB110*$P$7 -> 14 | AF110: =ROUND(AE110,2) -> 14 | AH110: =ROUNDUP(AN110,2) -> 734.95 | AJ110: =IF($V$4,AL110+AF110,AL110) -> 734.95 | AL110: =IF($V$5,Z110-Z110*10%,Z110) -> 734.95 | AN110: =IF($V$3,AJ110-((AJ110*1.18031)-AJ110),AJ110) -> 734.95
B111: 422-010-75 | C111: Коронка по бетону SDS+ D75 | D111: 1 | E111: / | F111: 20 | G111: =AH111 -> 630.09 | I111: - | J111: =G111*H111 -> 0 | K111: 4673732410889 | M111: 4673732410896 | P111: =$P$8 -> 0 | R111: =IF(Q111>0,Q111,P111) -> 0 | S111: =IF(P111>18,"ПЕРЕБОР","-") -> - | T111: 504.07 | V111: 1.25 | W111: =T111*V111 -> 630.0875 | X111: =R111*0.01 -> 0 | Y111: =W111-(W111*X111) -> 630.0875 | Z111: =ROUND(Y111,2) -> 630.09 | AB111: 0.925 | AC111: =H111*AB111 -> 0 | AD111: =AC111*$P$7 -> 0 | AE111: =AB111*$P$7 -> 14.8 | AF111: =ROUND(AE111,2) -> 14.8 | AH111: =ROUNDUP(AN111,2) -> 630.09 | AJ111: =IF($V$4,AL111+AF111,AL111) -> 630.09 | AL111: =IF($V$5,Z111-Z111*10%,Z111) -> 630.09 | AN111: =IF($V$3,AJ111-((AJ111*1.18031)-AJ111),AJ111) -> 630.09
B112: 422-010-100 | C112: Коронка по бетону SDS+ D100 | D112: 1 | E112: / | F112: 10 | G112: =AH112 -> 1114.4 | I112: - | J112: =G112*H112 -> 0 | K112: 4673732410902 | M112: 4673732410919 | P112: =$P$8 -> 0 | R112: =IF(Q112>0,Q112,P112) -> 0 | S112: =IF(P112>18,"ПЕРЕБОР","-") -> - | T112: 891.517 | V112: 1.25 | W112: =T112*V112 -> 1114.3963 | X112: =R112*0.01 -> 0 | Y112: =W112-(W112*X112) -> 1114.3963 | Z112: =ROUND(Y112,2) -> 1114.4 | AB112: 1.2 | AC112: =H112*AB112 -> 0 | AD112: =AC112*$P$7 -> 0 | AE112: =AB112*$P$7 -> 19.2 | AF112: =ROUND(AE112,2) -> 19.2 | AH112: =ROUNDUP(AN112,2) -> 1114.4 | AJ112: =IF($V$4,AL112+AF112,AL112) -> 1114.4 | AL112: =IF($V$5,Z112-Z112*10%,Z112) -> 1114.4 | AN112: =IF($V$3,AJ112-((AJ112*1.18031)-AJ112),AJ112) -> 1114.4
... B116: 422-010-150 | C116: Коронка по бетону SDS+ D150 | D116: 1 | E116: / | F116: 10 | G116: =AH116 -> 1985.66 | I116: - | J116: =G116*H116 -> 0 | K116: 4673759127845 | M116: 4673759127852 | P116: =$P$8 -> 0 | R116: =IF(Q116>0,Q116,P116) -> 0 | S116: =IF(P116>18,"ПЕРЕБОР","-") -> - | T116: 1588.53 | V116: 1.25 | W116: =T116*V116 -> 1985.6625 | X116: =R116*0.01 -> 0 | Y116: =W116-(W116*X116) -> 1985.6625 | Z116: =ROUND(Y116,2) -> 1985.66 | AB116: 2.5 | AC116: =H116*AB116 -> 0 | AD116: =AC116*$P$7 -> 0 | AE116: =AB116*$P$7 -> 40 | AF116: =ROUND(AE116,2) -> 40 | AH116: =ROUNDUP(AN116,2) -> 1985.66 | AJ116: =IF($V$4,AL116+AF116,AL116) -> 1985.66 | AL116: =IF($V$5,Z116-Z116*10%,Z116) -> 1985.66 | AN116: =IF($V$3,AJ116-((AJ116*1.18031)-AJ116),AJ116) -> 1985.66
B117: Коронка алмазная по бетону (безударные) | O117: Коронка алмазная по бетону
B118: 634-708-068 | C118: Коронка алмазная по бетону 68мм (безударная) | D118: 1 | E118: / | F118: 30 | G118: =AH118 -> 1876.56 | I118: - | J118: =G118*H118 -> 0 | K118: 4673768180626 | M118: 4673768180633 | P118: =$P$8 -> 0 | R118: =IF(Q118>0,Q118,P118) -> 0 | S118: =IF(P118>18,"ПЕРЕБОР","-") -> - | T118: 1501.247 | V118: 1.25 | W118: =T118*V118 -> 1876.5587 | X118: =R118*0.01 -> 0 | Y118: =W118-(W118*X118) -> 1876.5587 | Z118: =ROUND(Y118,2) -> 1876.56 | AB118: 0.68333333 | AC118: =H118*AB118 -> 0 | AD118: =AC118*$P$7 -> 0 | AE118: =AB118*$P$7 -> 10.933333 | AF118: =ROUND(AE118,2) -> 10.93 | AH118: =ROUNDUP(AN118,2) -> 1876.56 | AJ118: =IF($V$4,AL118+AF118,AL118) -> 1876.56 | AL118: =IF($V$5,Z118-Z118*10%,Z118) -> 1876.56 | AN118: =IF($V$3,AJ118-((AJ118*1.18031)-AJ118),AJ118) -> 1876.56
B119: 634-708-072 | C119: Коронка алмазная по бетону 72мм (безударная) | D119: 1 | E119: / | F119: 30 | G119: =AH119 -> 2024.4 | I119: - | J119: =G119*H119 -> 0 | K119: 4673768180640 | M119: 4673768180657 | P119: =$P$8 -> 0 | R119: =IF(Q119>0,Q119,P119) -> 0 | S119: =IF(P119>18,"ПЕРЕБОР","-") -> - | T119: 1619.519 | V119: 1.25 | W119: =T119*V119 -> 2024.3988 | X119: =R119*0.01 -> 0 | Y119: =W119-(W119*X119) -> 2024.3988 | Z119: =ROUND(Y119,2) -> 2024.4 | AB119: 0.71666667 | AC119: =H119*AB119 -> 0 | AD119: =AC119*$P$7 -> 0 | AE119: =AB119*$P$7 -> 11.466667 | AF119: =ROUND(AE119,2) -> 11.47 | AH119: =ROUNDUP(AN119,2) -> 2024.4 | AJ119: =IF($V$4,AL119+AF119,AL119) -> 2024.4 | AL119: =IF($V$5,Z119-Z119*10%,Z119) -> 2024.4 | AN119: =IF($V$3,AJ119-((AJ119*1.18031)-AJ119),AJ119) -> 2024.4
B120: 634-708-082 | C120: Коронка алмазная по бетону 82мм (безударная) | D120: 1 | E120: / | F120: 30 | G120: =AH120 -> 1840.36 | I120: - | J120: =G120*H120 -> 0 | K120: 4673768180664 | M120: 4673768180671 | P120: =$P$8 -> 0 | R120: =IF(Q120>0,Q120,P120) -> 0 | S120: =IF(P120>18,"ПЕРЕБОР","-") -> - | T120: 1472.29 | V120: 1.25 | W120: =T120*V120 -> 1840.3625 | X120: =R120*0.01 -> 0 | Y120: =W120-(W120*X120) -> 1840.3625 | Z120: =ROUND(Y120,2) -> 1840.36 | AB120: 0.78333333 | AC120: =H120*AB120 -> 0 | AD120: =AC120*$P$7 -> 0 | AE120: =AB120*$P$7 -> 12.533333 | AF120: =ROUND(AE120,2) -> 12.53 | AH120: =ROUNDUP(AN120,2) -> 1840.36 | AJ120: =IF($V$4,AL120+AF120,AL120) -> 1840.36 | AL120: =IF($V$5,Z120-Z120*10%,Z120) -> 1840.36 | AN120: =IF($V$3,AJ120-((AJ120*1.18031)-AJ120),AJ120) -> 1840.36
B121: Коронки по керамической плитке | O121: Коронки по керамической плитке
B122: 695-704-337 | C122: Набор коронок по керамической плитке (4 предм.: 33,53,67,73) | D122: 1 | E122: 5 | F122: 20 | G122: =AH122 -> 1410.94 | I122: - | J122: =G122*H122 -> 0 | K122: 4673743524988 | M122: 4673743524995 | P122: =$P$8 -> 0 | R122: =IF(Q122>0,Q122,P122) -> 0 | S122: =IF(P122>18,"ПЕРЕБОР","-") -> - | T122: 1128.75 | V122: 1.25 | W122: =T122*V122 -> 1410.9375 | X122: =R122*0.01 -> 0 | Y122: =W122-(W122*X122) -> 1410.9375 | Z122: =ROUND(Y122,2) -> 1410.94 | AB122: 0.75 | AC122: =H122*AB122 -> 0 | AD122: =AC122*$P$7 -> 0 | AE122: =AB122*$P$7 -> 12 | AF122: =ROUND(AE122,2) -> 12 | AH122: =ROUNDUP(AN122,2) -> 1410.94 | AJ122: =IF($V$4,AL122+AF122,AL122) -> 1410.94 | AL122: =IF($V$5,Z122-Z122*10%,Z122) -> 1410.94 | AN122: =IF($V$3,AJ122-((AJ122*1.18031)-AJ122),AJ122) -> 1410.94
B123: Коронка по стеклу с центрирующим сверлом | O123: Коронка по стеклу с центр. сверлом
B124: 822-808-02055 | C124: Коронка по стеклу с центрирующим сверлом D 20 Х H 55 | D124: 1 | E124: 16 | F124: 400 | G124: =AH124 -> 152.58 | I124: - | J124: =G124*H124 -> 0 | K124: 4673743520874 | M124: 4673743520843 | P124: =$P$8 -> 0 | R124: =IF(Q124>0,Q124,P124) -> 0 | S124: =IF(P124>18,"ПЕРЕБОР","-") -> - | T124: 122.06 | V124: 1.25 | W124: =T124*V124 -> 152.575 | X124: =R124*0.01 -> 0 | Y124: =W124-(W124*X124) -> 152.575 | Z124: =ROUND(Y124,2) -> 152.58 | AB124: 0.039 | AC124: =H124*AB124 -> 0 | AD124: =AC124*$P$7 -> 0 | AE124: =AB124*$P$7 -> 0.624 | AF124: =ROUND(AE124,2) -> 0.62 | AH124: =ROUNDUP(AN124,2) -> 152.58 | AJ124: =IF($V$4,AL124+AF124,AL124) -> 152.58 | AL124: =IF($V$5,Z124-Z124*10%,Z124) -> 152.58 | AN124: =IF($V$3,AJ124-((AJ124*1.18031)-AJ124),AJ124) -> 152.58
B125: 822-808-02255 | C125: Коронка по стеклу с центрирующим сверлом D 22 Х H 55 РАСПРОДАЖА! | D125: 1 | E125: 16 | F125: 400 | G125: =AH125 -> 118.75 | I125: - | J125: =G125*H125 -> 0 | K125: 4673743520881 | M125: 4673743520898 | P125: =$P$8 -> 0 | R125: =IF(Q125>0,Q125,P125) -> 0 | S125: =IF(P125>18,"ПЕРЕБОР","-") -> - | T125: 95 | V125: 1.25 | W125: =T125*V125 -> 118.75 | X125: =R125*0.01 -> 0 | Y125: =W125-(W125*X125) -> 118.75 | Z125: =ROUND(Y125,2) -> 118.75 | AB125: 0.041 | AC125: =H125*AB125 -> 0 | AD125: =AC125*$P$7 -> 0 | AE125: =AB125*$P$7 -> 0.656 | AF125: =ROUND(AE125,2) -> 0.66 | AH125: =ROUNDUP(AN125,2) -> 118.75 | AJ125: =IF($V$4,AL125+AF125,AL125) -> 118.75 | AL125: =IF($V$5,Z125-Z125*10%,Z125) -> 118.75 | AN125: =IF($V$3,AJ125-((AJ125*1.18031)-AJ125),AJ125) -> 118.75
B126: 822-808-02555 | C126: Коронка по стеклу с центрирующим сверлом D 25 Х H 55 | D126: 1 | E126: 16 | F126: 288 | G126: =AH126 -> 197.18 | I126: - | J126: =G126*H126 -> 0 | K126: 4673743521208 | M126: 4673743521215 | P126: =$P$8 -> 0 | R126: =IF(Q126>0,Q126,P126) -> 0 | S126: =IF(P126>18,"ПЕРЕБОР","-") -> - | T126: 157.74 | V126: 1.25 | W126: =T126*V126 -> 197.175 | X126: =R126*0.01 -> 0 | Y126: =W126-(W126*X126) -> 197.175 | Z126: =ROUND(Y126,2) -> 197.18 | AB126: 0.0514 | AC126: =H126*AB126 -> 0 | AD126: =AC126*$P$7 -> 0 | AE126: =AB126*$P$7 -> 0.8224 | AF126: =ROUND(AE126,2) -> 0.82 | AH126: =ROUNDUP(AN126,2) -> 197.18 | AJ126: =IF($V$4,AL126+AF126,AL126) -> 197.18 | AL126: =IF($V$5,Z126-Z126*10%,Z126) -> 197.18 | AN126: =IF($V$3,AJ126-((AJ126*1.18031)-AJ126),AJ126) -> 197.18
B127: 822-808-02855 | C127: Коронка по стеклу с центрирующим сверлом D 28 Х H 55 | D127: 1 | E127: 16 | F127: 192 | G127: =AH127 -> 217.69 | I127: - | J127: =G127*H127 -> 0 | K127: 4673743521222 | M127: 4673743521239 | P127: =$P$8 -> 0 | R127: =IF(Q127>0,Q127,P127) -> 0 | S127: =IF(P127>18,"ПЕРЕБОР","-") -> - | T127: 174.153 | V127: 1.25 | W127: =T127*V127 -> 217.69125 | X127: =R127*0.01 -> 0 | Y127: =W127-(W127*X127) -> 217.69125 | Z127: =ROUND(Y127,2) -> 217.69 | AB127: 0.0615 | AC127: =H127*AB127 -> 0 | AD127: =AC127*$P$7 -> 0 | AE127: =AB127*$P$7 -> 0.984 | AF127: =ROUND(AE127,2) -> 0.98 | AH127: =ROUNDUP(AN127,2) -> 217.69 | AJ127: =IF($V$4,AL127+AF127,AL127) -> 217.69 | AL127: =IF($V$5,Z127-Z127*10%,Z127) -> 217.69 | AN127: =IF($V$3,AJ127-((AJ127*1.18031)-AJ127),AJ127) -> 217.69
B128: 822-808-03055 | C128: Коронка по стеклу с центрирующим сверлом D 30 Х H 55 | D128: 1 | E128: 16 | F128: 192 | G128: =AH128 -> 234.74 | I128: - | J128: =G128*H128 -> 0 | K128: 4673743521246 | M128: 4673743521253 | P128: =$P$8 -> 0 | R128: =IF(Q128>0,Q128,P128) -> 0 | S128: =IF(P128>18,"ПЕРЕБОР","-") -> - | T128: 187.79 | V128: 1.25 | W128: =T128*V128 -> 234.7375 | X128: =R128*0.01 -> 0 | Y128: =W128-(W128*X128) -> 234.7375 | Z128: =ROUND(Y128,2) -> 234.74 | AB128: 0.0641 | AC128: =H128*AB128 -> 0 | AD128: =AC128*$P$7 -> 0 | AE128: =AB128*$P$7 -> 1.0256 | AF128: =ROUND(AE128,2) -> 1.03 | AH128: =ROUNDUP(AN128,2) -> 234.74 | AJ128: =IF($V$4,AL128+AF128,AL128) -> 234.74 | AL128: =IF($V$5,Z128-Z128*10%,Z128) -> 234.74 | AN128: =IF($V$3,AJ128-((AJ128*1.18031)-AJ128),AJ128) -> 234.74
B129: 822-808-03255 | C129: Коронка по стеклу с центрирующим сверлом D 32 Х H 55 | D129: 1 | E129: 10 | F129: 160 | G129: =AH129 -> 257.57 | I129: - | J129: =G129*H129 -> 0 | K129: 4673743521260 | M129: 4673743521277 | P129: =$P$8 -> 0 | R129: =IF(Q129>0,Q129,P129) -> 0 | S129: =IF(P129>18,"ПЕРЕБОР","-") -> - | T129: 206.052 | V129: 1.25 | W129: =T129*V129 -> 257.565 | X129: =R129*0.01 -> 0 | Y129: =W129-(W129*X129) -> 257.565 | Z129: =ROUND(Y129,2) -> 257.57 | AB129: 0.0756 | AC129: =H129*AB129 -> 0 | AD129: =AC129*$P$7 -> 0 | AE129: =AB129*$P$7 -> 1.2096 | AF129: =ROUND(AE129,2) -> 1.21 | AH129: =ROUNDUP(AN129,2) -> 257.57 | AJ129: =IF($V$4,AL129+AF129,AL129) -> 257.57 | AL129: =IF($V$5,Z129-Z129*10%,Z129) -> 257.57 | AN129: =IF($V$3,AJ129-((AJ129*1.18031)-AJ129),AJ129) -> 257.57
B130: 822-808-03555 | C130: Коронка по стеклу с центрирующим сверлом D 35 Х H 55 | D130: 1 | E130: 10 | F130: 160 | G130: =AH130 -> 275.83 | I130: - | J130: =G130*H130 -> 0 | K130: 4673743521284 | M130: 4673743521291 | P130: =$P$8 -> 0 | R130: =IF(Q130>0,Q130,P130) -> 0 | S130: =IF(P130>18,"ПЕРЕБОР","-") -> - | T130: 220.66 | V130: 1.25 | W130: =T130*V130 -> 275.825 | X130: =R130*0.01 -> 0 | Y130: =W130-(W130*X130) -> 275.825 | Z130: =ROUND(Y130,2) -> 275.83 | AB130: 0.0769 | AC130: =H130*AB130 -> 0 | AD130: =AC130*$P$7 -> 0 | AE130: =AB130*$P$7 -> 1.2304 | AF130: =ROUND(AE130,2) -> 1.23 | AH130: =ROUNDUP(AN130,2) -> 275.83 | AJ130: =IF($V$4,AL130+AF130,AL130) -> 275.83 | AL130: =IF($V$5,Z130-Z130*10%,Z130) -> 275.83 | AN130: =IF($V$3,AJ130-((AJ130*1.18031)-AJ130),AJ130) -> 275.83
B131: 822-808-04055 | C131: Коронка по стеклу с центрирующим сверлом D 40 Х H 55 | D131: 1 | E131: 8 | F131: 128 | G131: =AH131 -> 324.82 | I131: - | J131: =G131*H131 -> 0 | K131: 4673743521307 | M131: 4673743521314 | P131: =$P$8 -> 0 | R131: =IF(Q131>0,Q131,P131) -> 0 | S131: =IF(P131>18,"ПЕРЕБОР","-") -> - | T131: 259.858 | V131: 1.25 | W131: =T131*V131 -> 324.8225 | X131: =R131*0.01 -> 0 | Y131: =W131-(W131*X131) -> 324.8225 | Z131: =ROUND(Y131,2) -> 324.82 | AB131: 0.0883 | AC131: =H131*AB131 -> 0 | AD131: =AC131*$P$7 -> 0 | AE131: =AB131*$P$7 -> 1.4128 | AF131: =ROUND(AE131,2) -> 1.41 | AH131: =ROUNDUP(AN131,2) -> 324.82 | AJ131: =IF($V$4,AL131+AF131,AL131) -> 324.82 | AL131: =IF($V$5,Z131-Z131*10%,Z131) -> 324.82 | AN131: =IF($V$3,AJ131-((AJ131*1.18031)-AJ131),AJ131) -> 324.82
B132: 822-808-04255 | C132: Коронка по стеклу с центрирующим сверлом D 42 Х H 55 | D132: 1 | E132: 16 | F132: 128 | G132: =AH132 -> 334.68 | I132: - | J132: =G132*H132 -> 0 | K132: 4673743521321 | M132: 4673743521338 | P132: =$P$8 -> 0 | R132: =IF(Q132>0,Q132,P132) -> 0 | S132: =IF(P132>18,"ПЕРЕБОР","-") -> - | T132: 267.74415 | V132: 1.25 | W132: =T132*V132 -> 334.68019 | X132: =R132*0.01 -> 0 | Y132: =W132-(W132*X132) -> 334.68019 | Z132: =ROUND(Y132,2) -> 334.68 | AB132: 0.1 | AC132: =H132*AB132 -> 0 | AD132: =AC132*$P$7 -> 0 | AE132: =AB132*$P$7 -> 1.6 | AF132: =ROUND(AE132,2) -> 1.6 | AH132: =ROUNDUP(AN132,2) -> 334.68 | AJ132: =IF($V$4,AL132+AF132,AL132) -> 334.68 | AL132: =IF($V$5,Z132-Z132*10%,Z132) -> 334.68 | AN132: =IF($V$3,AJ132-((AJ132*1.18031)-AJ132),AJ132) -> 334.68
B133: 822-808-04555 | C133: Коронка по стеклу с центрирующим сверлом D 45 Х H 55 | D133: 1 | E133: 16 | F133: 128 | G133: =AH133 -> 369.72 | I133: - | J133: =G133*H133 -> 0 | K133: 4673743521345 | M133: 4673743521352 | P133: =$P$8 -> 0 | R133: =IF(Q133>0,Q133,P133) -> 0 | S133: =IF(P133>18,"ПЕРЕБОР","-") -> - | T133: 295.7745 | V133: 1.25 | W133: =T133*V133 -> 369.71812 | X133: =R133*0.01 -> 0 | Y133: =W133-(W133*X133) -> 369.71812 | Z133: =ROUND(Y133,2) -> 369.72 | AB133: 0.1078 | AC133: =H133*AB133 -> 0 | AD133: =AC133*$P$7 -> 0 | AE133: =AB133*$P$7 -> 1.7248 | AF133: =ROUND(AE133,2) -> 1.72 | AH133: =ROUNDUP(AN133,2) -> 369.72 | AJ133: =IF($V$4,AL133+AF133,AL133) -> 369.72 | AL133: =IF($V$5,Z133-Z133*10%,Z133) -> 369.72 | AN133: =IF($V$3,AJ133-((AJ133*1.18031)-AJ133),AJ133) -> 369.72
B134: 822-808-05055 | C134: Коронка по стеклу с центрирующим сверлом D 50 Х H 55 | D134: 1 | E134: 6 | F134: 96 | G134: =AH134 -> 379.11 | I134: - | J134: =G134*H134 -> 0 | K134: 4673743521369 | M134: 4673743521376 | P134: =$P$8 -> 0 | R134: =IF(Q134>0,Q134,P134) -> 0 | S134: =IF(P134>18,"ПЕРЕБОР","-") -> - | T134: 303.29 | V134: 1.25 | W134: =T134*V134 -> 379.1125 | X134: =R134*0.01 -> 0 | Y134: =W134-(W134*X134) -> 379.1125 | Z134: =ROUND(Y134,2) -> 379.11 | AB134: 0.1292 | AC134: =H134*AB134 -> 0 | AD134: =AC134*$P$7 -> 0 | AE134: =AB134*$P$7 -> 2.0672 | AF134: =ROUND(AE134,2) -> 2.07 | AH134: =ROUNDUP(AN134,2) -> 379.11 | AJ134: =IF($V$4,AL134+AF134,AL134) -> 379.11 | AL134: =IF($V$5,Z134-Z134*10%,Z134) -> 379.11 | AN134: =IF($V$3,AJ134-((AJ134*1.18031)-AJ134),AJ134) -> 379.11
B135: 822-808-05555 | C135: Коронка по стеклу с центрирующим сверлом D 55 Х H 55 | D135: 1 | E135: 10 | F135: 100 | G135: =AH135 -> 455.49 | I135: - | J135: =G135*H135 -> 0 | K135: 4673743521383 | M135: 4673743521390 | P135: =$P$8 -> 0 | R135: =IF(Q135>0,Q135,P135) -> 0 | S135: =IF(P135>18,"ПЕРЕБОР","-") -> - | T135: 364.39275 | V135: 1.25 | W135: =T135*V135 -> 455.49094 | X135: =R135*0.01 -> 0 | Y135: =W135-(W135*X135) -> 455.49094 | Z135: =ROUND(Y135,2) -> 455.49 | AB135: 0.115 | AC135: =H135*AB135 -> 0 | AD135: =AC135*$P$7 -> 0 | AE135: =AB135*$P$7 -> 1.84 | AF135: =ROUND(AE135,2) -> 1.84 | AH135: =ROUNDUP(AN135,2) -> 455.49 | AJ135: =IF($V$4,AL135+AF135,AL135) -> 455.49 | AL135: =IF($V$5,Z135-Z135*10%,Z135) -> 455.49 | AN135: =IF($V$3,AJ135-((AJ135*1.18031)-AJ135),AJ135) -> 455.49
... B149: 822-808-12055 | C149: Коронка по стеклу с центрирующим сверлом D 120 Х H 55 | D149: 1 | E149: 10 | F149: 50 | G149: =AH149 -> 1024.65 | I149: - | J149: =G149*H149 -> 0 | K149: 4673743521666 | M149: 4673743521673 | P149: =$P$8 -> 0 | R149: =IF(Q149>0,Q149,P149) -> 0 | S149: =IF(P149>18,"ПЕРЕБОР","-") -> - | T149: 819.72 | V149: 1.25 | W149: =T149*V149 -> 1024.65 | X149: =R149*0.01 -> 0 | Y149: =W149-(W149*X149) -> 1024.65 | Z149: =ROUND(Y149,2) -> 1024.65 | AB149: 0.34 | AC149: =H149*AB149 -> 0 | AD149: =AC149*$P$7 -> 0 | AE149: =AB149*$P$7 -> 5.44 | AF149: =ROUND(AE149,2) -> 5.44 | AH149: =ROUNDUP(AN149,2) -> 1024.65 | AJ149: =IF($V$4,AL149+AF149,AL149) -> 1024.65 | AL149: =IF($V$5,Z149-Z149*10%,Z149) -> 1024.65 | AN149: =IF($V$3,AJ149-((AJ149*1.18031)-AJ149),AJ149) -> 1024.65
B150: Пика SDS+ | O150: Пика SDS+
B151: 427-010-14250 | C151: Пика SDS+ (14X250) | D151: 1 | E151: 10 | F151: 100 | G151: =AH151 -> 120.85 | I151: - | J151: =G151*H151 -> 0 | K151: 4673732411008 | M151: 4673732411015 | P151: =$P$8 -> 0 | R151: =IF(Q151>0,Q151,P151) -> 0 | S151: =IF(P151>18,"ПЕРЕБОР","-") -> - | T151: 96.679 | V151: 1.25 | W151: =T151*V151 -> 120.84875 | X151: =R151*0.01 -> 0 | Y151: =W151-(W151*X151) -> 120.84875 | Z151: =ROUND(Y151,2) -> 120.85 | AB151: 0.24 | AC151: =H151*AB151 -> 0 | AD151: =AC151*$P$7 -> 0 | AE151: =AB151*$P$7 -> 3.84 | AF151: =ROUND(AE151,2) -> 3.84 | AH151: =ROUNDUP(AN151,2) -> 120.85 | AJ151: =IF($V$4,AL151+AF151,AL151) -> 120.85 | AL151: =IF($V$5,Z151-Z151*10%,Z151) -> 120.85 | AN151: =IF($V$3,AJ151-((AJ151*1.18031)-AJ151),AJ151) -> 120.85
B152: 427-010-14400 | C152: Пика SDS+ (14X400) | D152: 1 | E152: 10 | F152: 50 | G152: =AH152 -> 199.53 | I152: - | J152: =G152*H152 -> 0 | K152: 4673732411022 | M152: 4673732411039 | P152: =$P$8 -> 0 | R152: =IF(Q152>0,Q152,P152) -> 0 | S152: =IF(P152>18,"ПЕРЕБОР","-") -> - | T152: 159.62 | V152: 1.25 | W152: =T152*V152 -> 199.525 | X152: =R152*0.01 -> 0 | Y152: =W152-(W152*X152) -> 199.525 | Z152: =ROUND(Y152,2) -> 199.53 | AB152: 0.38 | AC152: =H152*AB152 -> 0 | AD152: =AC152*$P$7 -> 0 | AE152: =AB152*$P$7 -> 6.08 | AF152: =ROUND(AE152,2) -> 6.08 | AH152: =ROUNDUP(AN152,2) -> 199.53 | AJ152: =IF($V$4,AL152+AF152,AL152) -> 199.53 | AL152: =IF($V$5,Z152-Z152*10%,Z152) -> 199.53 | AN152: =IF($V$3,AJ152-((AJ152*1.18031)-AJ152),AJ152) -> 199.53
B153: Пика SDS MAX | O153: Пика SDS MAX
B154: 425-010-18280 | C154: Пика SDS MAX (18X280) | D154: 1 | E154: 10 | F154: 50 | G154: =AH154 -> 261.04 | I154: - | J154: =G154*H154 -> 0 | K154: 4673732410964 | M154: 4673732410971 | P154: =$P$8 -> 0 | R154: =IF(Q154>0,Q154,P154) -> 0 | S154: =IF(P154>18,"ПЕРЕБОР","-") -> - | T154: 208.835 | V154: 1.25 | W154: =T154*V154 -> 261.04375 | X154: =R154*0.01 -> 0 | Y154: =W154-(W154*X154) -> 261.04375 | Z154: =ROUND(Y154,2) -> 261.04 | AB154: 0.48 | AC154: =H154*AB154 -> 0 | AD154: =AC154*$P$7 -> 0 | AE154: =AB154*$P$7 -> 7.68 | AF154: =ROUND(AE154,2) -> 7.68 | AH154: =ROUNDUP(AN154,2) -> 261.04 | AJ154: =IF($V$4,AL154+AF154,AL154) -> 261.04 | AL154: =IF($V$5,Z154-Z154*10%,Z154) -> 261.04 | AN154: =IF($V$3,AJ154-((AJ154*1.18031)-AJ154),AJ154) -> 261.04
B155: 425-010-18400 | C155: Пика SDS MAX (18X400) | D155: 1 | E155: 5 | F155: 25 | G155: =AH155 -> 326.91 | I155: - | J155: =G155*H155 -> 0 | K155: 4673732410988 | M155: 4673732410995 | P155: =$P$8 -> 0 | R155: =IF(Q155>0,Q155,P155) -> 0 | S155: =IF(P155>18,"ПЕРЕБОР","-") -> - | T155: 261.53 | V155: 1.25 | W155: =T155*V155 -> 326.9125 | X155: =R155*0.01 -> 0 | Y155: =W155-(W155*X155) -> 326.9125 | Z155: =ROUND(Y155,2) -> 326.91 | AB155: 0.7 | AC155: =H155*AB155 -> 0 | AD155: =AC155*$P$7 -> 0 | AE155: =AB155*$P$7 -> 11.2 | AF155: =ROUND(AE155,2) -> 11.2 | AH155: =ROUNDUP(AN155,2) -> 326.91 | AJ155: =IF($V$4,AL155+AF155,AL155) -> 326.91 | AL155: =IF($V$5,Z155-Z155*10%,Z155) -> 326.91 | AN155: =IF($V$3,AJ155-((AJ155*1.18031)-AJ155),AJ155) -> 326.91
B156: Сверло по стеклу цилиндрический хвостовик | O156: Сверло по стеклу цил. хвостовик
B157: 432-010-06 | C157: Сверло по стеклу ц/х D6 | D157: 1 | E157: 50 | F157: 500 | G157: =AH157 -> 81.72 | I157: - | J157: =G157*H157 -> 0 | K157: 4673732411046 | M157: 4673732411053 | P157: =$P$8 -> 0 | R157: =IF(Q157>0,Q157,P157) -> 0 | S157: =IF(P157>18,"ПЕРЕБОР","-") -> - | T157: 65.37375 | V157: 1.25 | W157: =T157*V157 -> 81.717187 | X157: =R157*0.01 -> 0 | Y157: =W157-(W157*X157) -> 81.717187 | Z157: =ROUND(Y157,2) -> 81.72 | AB157: 0.0184 | AC157: =H157*AB157 -> 0 | AD157: =AC157*$P$7 -> 0 | AE157: =AB157*$P$7 -> 0.2944 | AF157: =ROUND(AE157,2) -> 0.29 | AH157: =ROUNDUP(AN157,2) -> 81.72 | AJ157: =IF($V$4,AL157+AF157,AL157) -> 81.72 | AL157: =IF($V$5,Z157-Z157*10%,Z157) -> 81.72 | AN157: =IF($V$3,AJ157-((AJ157*1.18031)-AJ157),AJ157) -> 81.72
B158: 432-010-08 | C158: Сверло по стеклу ц/х D8 | D158: 1 | E158: 50 | F158: 500 | G158: =AH158 -> 103.81 | I158: - | J158: =G158*H158 -> 0 | K158: 4673732411060 | M158: 4673732411077 | P158: =$P$8 -> 0 | R158: =IF(Q158>0,Q158,P158) -> 0 | S158: =IF(P158>18,"ПЕРЕБОР","-") -> - | T158: 83.05 | V158: 1.25 | W158: =T158*V158 -> 103.8125 | X158: =R158*0.01 -> 0 | Y158: =W158-(W158*X158) -> 103.8125 | Z158: =ROUND(Y158,2) -> 103.81 | AB158: 0.022 | AC158: =H158*AB158 -> 0 | AD158: =AC158*$P$7 -> 0 | AE158: =AB158*$P$7 -> 0.352 | AF158: =ROUND(AE158,2) -> 0.35 | AH158: =ROUNDUP(AN158,2) -> 103.81 | AJ158: =IF($V$4,AL158+AF158,AL158) -> 103.81 | AL158: =IF($V$5,Z158-Z158*10%,Z158) -> 103.81 | AN158: =IF($V$3,AJ158-((AJ158*1.18031)-AJ158),AJ158) -> 103.81
B159: 432-010-10 | C159: Сверло по стеклу ц/х D10 | D159: 1 | E159: 50 | F159: 500 | G159: =AH159 -> 137.2 | I159: - | J159: =G159*H159 -> 0 | K159: 4673759127869 | M159: 4673759127876 | P159: =$P$8 -> 0 | R159: =IF(Q159>0,Q159,P159) -> 0 | S159: =IF(P159>18,"ПЕРЕБОР","-") -> - | T159: 109.758 | V159: 1.25 | W159: =T159*V159 -> 137.1975 | X159: =R159*0.01 -> 0 | Y159: =W159-(W159*X159) -> 137.1975 | Z159: =ROUND(Y159,2) -> 137.2 | AB159: 0.024 | AC159: =H159*AB159 -> 0 | AD159: =AC159*$P$7 -> 0 | AE159: =AB159*$P$7 -> 0.384 | AF159: =ROUND(AE159,2) -> 0.38 | AH159: =ROUNDUP(AN159,2) -> 137.2 | AJ159: =IF($V$4,AL159+AF159,AL159) -> 137.2 | AL159: =IF($V$5,Z159-Z159*10%,Z159) -> 137.2 | AN159: =IF($V$3,AJ159-((AJ159*1.18031)-AJ159),AJ159) -> 137.2
B160: 432-010-12 | C160: Сверло по стеклу ц/х D12 | D160: 1 | E160: 50 | F160: 500 | G160: =AH160 -> 146.43 | I160: - | J160: =G160*H160 -> 0 | K160: 4673759127883 | M160: 4673759127890 | P160: =$P$8 -> 0 | R160: =IF(Q160>0,Q160,P160) -> 0 | S160: =IF(P160>18,"ПЕРЕБОР","-") -> - | T160: 117.14625 | V160: 1.25 | W160: =T160*V160 -> 146.43281 | X160: =R160*0.01 -> 0 | Y160: =W160-(W160*X160) -> 146.43281 | Z160: =ROUND(Y160,2) -> 146.43 | AB160: 0.027 | AC160: =H160*AB160 -> 0 | AD160: =AC160*$P$7 -> 0 | AE160: =AB160*$P$7 -> 0.432 | AF160: =ROUND(AE160,2) -> 0.43 | AH160: =ROUNDUP(AN160,2) -> 146.43 | AJ160: =IF($V$4,AL160+AF160,AL160) -> 146.43 | AL160: =IF($V$5,Z160-Z160*10%,Z160) -> 146.43 | AN160: =IF($V$3,AJ160-((AJ160*1.18031)-AJ160),AJ160) -> 146.43
B161: Сверло по стеклу шестигранный хвостовик (4х резцовое) | O161: Сверло по стеклу шест. хвостовик
B162: 433-010-06 | C162: Сверло по стеклу ш/х 4х резц. D6 | D162: 1 | E162: 50 | F162: 500 | G162: =AH162 -> 143.03 | I162: - | J162: =G162*H162 -> 0 | K162: 4673732411084 | M162: 4673732411091 | P162: =$P$8 -> 0 | R162: =IF(Q162>0,Q162,P162) -> 0 | S162: =IF(P162>18,"ПЕРЕБОР","-") -> - | T162: 114.42375 | V162: 1.25 | W162: =T162*V162 -> 143.02969 | X162: =R162*0.01 -> 0 | Y162: =W162-(W162*X162) -> 143.02969 | Z162: =ROUND(Y162,2) -> 143.03 | AB162: 0.0264 | AC162: =H162*AB162 -> 0 | AD162: =AC162*$P$7 -> 0 | AE162: =AB162*$P$7 -> 0.4224 | AF162: =ROUND(AE162,2) -> 0.42 | AH162: =ROUNDUP(AN162,2) -> 143.03 | AJ162: =IF($V$4,AL162+AF162,AL162) -> 143.03 | AL162: =IF($V$5,Z162-Z162*10%,Z162) -> 143.03 | AN162: =IF($V$3,AJ162-((AJ162*1.18031)-AJ162),AJ162) -> 143.03
B163: 433-010-08 | C163: Сверло по стеклу ш/х 4х резц. D8 | D163: 1 | E163: 50 | F163: 500 | G163: =AH163 -> 157.29 | I163: - | J163: =G163*H163 -> 0 | K163: 4673732411107 | M163: 4673732411114 | P163: =$P$8 -> 0 | R163: =IF(Q163>0,Q163,P163) -> 0 | S163: =IF(P163>18,"ПЕРЕБОР","-") -> - | T163: 125.83 | V163: 1.25 | W163: =T163*V163 -> 157.2875 | X163: =R163*0.01 -> 0 | Y163: =W163-(W163*X163) -> 157.2875 | Z163: =ROUND(Y163,2) -> 157.29 | AB163: 0.03 | AC163: =H163*AB163 -> 0 | AD163: =AC163*$P$7 -> 0 | AE163: =AB163*$P$7 -> 0.48 | AF163: =ROUND(AE163,2) -> 0.48 | AH163: =ROUNDUP(AN163,2) -> 157.29 | AJ163: =IF($V$4,AL163+AF163,AL163) -> 157.29 | AL163: =IF($V$5,Z163-Z163*10%,Z163) -> 157.29 | AN163: =IF($V$3,AJ163-((AJ163*1.18031)-AJ163),AJ163) -> 157.29
B164: 433-010-10 | C164: Сверло по стеклу ш/х 4х резц. D10 | D164: 1 | E164: 50 | F164: 500 | G164: =AH164 -> 217.51 | I164: - | J164: =G164*H164 -> 0 | K164: 4673759127906 | M164: 4673759127913 | P164: =$P$8 -> 0 | R164: =IF(Q164>0,Q164,P164) -> 0 | S164: =IF(P164>18,"ПЕРЕБОР","-") -> - | T164: 174.009 | V164: 1.25 | W164: =T164*V164 -> 217.51125 | X164: =R164*0.01 -> 0 | Y164: =W164-(W164*X164) -> 217.51125 | Z164: =ROUND(Y164,2) -> 217.51 | AB164: 0.032 | AC164: =H164*AB164 -> 0 | AD164: =AC164*$P$7 -> 0 | AE164: =AB164*$P$7 -> 0.512 | AF164: =ROUND(AE164,2) -> 0.51 | AH164: =ROUNDUP(AN164,2) -> 217.51 | AJ164: =IF($V$4,AL164+AF164,AL164) -> 217.51 | AL164: =IF($V$5,Z164-Z164*10%,Z164) -> 217.51 | AN164: =IF($V$3,AJ164-((AJ164*1.18031)-AJ164),AJ164) -> 217.51
B165: 433-010-12 | C165: Сверло по стеклу ш/х 4х резц. D12 | D165: 1 | E165: 50 | F165: 500 | G165: =AH165 -> 230.05 | I165: - | J165: =G165*H165 -> 0 | K165: 4673759127920 | M165: 4673759127937 | P165: =$P$8 -> 0 | R165: =IF(Q165>0,Q165,P165) -> 0 | S165: =IF(P165>18,"ПЕРЕБОР","-") -> - | T165: 184.04 | V165: 1.25 | W165: =T165*V165 -> 230.05 | X165: =R165*0.01 -> 0 | Y165: =W165-(W165*X165) -> 230.05 | Z165: =ROUND(Y165,2) -> 230.05 | AB165: 0.035 | AC165: =H165*AB165 -> 0 | AD165: =AC165*$P$7 -> 0 | AE165: =AB165*$P$7 -> 0.56 | AF165: =ROUND(AE165,2) -> 0.56 | AH165: =ROUNDUP(AN165,2) -> 230.05 | AJ165: =IF($V$4,AL165+AF165,AL165) -> 230.05 | AL165: =IF($V$5,Z165-Z165*10%,Z165) -> 230.05 | AN165: =IF($V$3,AJ165-((AJ165*1.18031)-AJ165),AJ165) -> 230.05
B166: Сверло по металлу HSS | O166: Сверло по металлу HSS
B167: 435-010-0025 | C167: Сверло по металлу HSS D2,5 | D167: 10 | E167: 10 | F167: 600 | G167: =AH167 -> 58.8 | I167: - | J167: =G167*H167 -> 0 | K167: 4673732411169 | M167: 4673732411176 | P167: =$P$8 -> 0 | R167: =IF(Q167>0,Q167,P167) -> 0 | S167: =IF(P167>18,"ПЕРЕБОР","-") -> - | T167: 47.04 | V167: 1.25 | W167: =T167*V167 -> 58.8 | X167: =R167*0.01 -> 0 | Y167: =W167-(W167*X167) -> 58.8 | Z167: =ROUND(Y167,2) -> 58.8 | AB167: 0.023 | AC167: =H167*AB167 -> 0 | AD167: =AC167*$P$7 -> 0 | AE167: =AB167*$P$7 -> 0.368 | AF167: =ROUND(AE167,2) -> 0.37 | AH167: =ROUNDUP(AN167,2) -> 58.8 | AJ167: =IF($V$4,AL167+AF167,AL167) -> 58.8 | AL167: =IF($V$5,Z167-Z167*10%,Z167) -> 58.8 | AN167: =IF($V$3,AJ167-((AJ167*1.18031)-AJ167),AJ167) -> 58.8
B168: 435-010-003 | C168: Сверло по металлу HSS D3 | D168: 10 | E168: 10 | F168: 600 | G168: =AH168 -> 65.91 | I168: - | J168: =G168*H168 -> 0 | K168: 4673732411183 | M168: 4673732411190 | P168: =$P$8 -> 0 | R168: =IF(Q168>0,Q168,P168) -> 0 | S168: =IF(P168>18,"ПЕРЕБОР","-") -> - | T168: 52.73 | V168: 1.25 | W168: =T168*V168 -> 65.9125 | X168: =R168*0.01 -> 0 | Y168: =W168-(W168*X168) -> 65.9125 | Z168: =ROUND(Y168,2) -> 65.91 | AB168: 0.030166667 | AC168: =H168*AB168 -> 0 | AD168: =AC168*$P$7 -> 0 | AE168: =AB168*$P$7 -> 0.48266667 | AF168: =ROUND(AE168,2) -> 0.48 | AH168: =ROUNDUP(AN168,2) -> 65.91 | AJ168: =IF($V$4,AL168+AF168,AL168) -> 65.91 | AL168: =IF($V$5,Z168-Z168*10%,Z168) -> 65.91 | AN168: =IF($V$3,AJ168-((AJ168*1.18031)-AJ168),AJ168) -> 65.91
B169: 435-010-0032 | C169: Сверло по металлу HSS D3,2 | D169: 10 | E169: 10 | F169: 400 | G169: =AH169 -> 67.6 | I169: - | J169: =G169*H169 -> 0 | K169: 4673732411206 | M169: 4673732411213 | P169: =$P$8 -> 0 | R169: =IF(Q169>0,Q169,P169) -> 0 | S169: =IF(P169>18,"ПЕРЕБОР","-") -> - | T169: 54.08 | V169: 1.25 | W169: =T169*V169 -> 67.6 | X169: =R169*0.01 -> 0 | Y169: =W169-(W169*X169) -> 67.6 | Z169: =ROUND(Y169,2) -> 67.6 | AB169: 0.03525 | AC169: =H169*AB169 -> 0 | AD169: =AC169*$P$7 -> 0 | AE169: =AB169*$P$7 -> 0.564 | AF169: =ROUND(AE169,2) -> 0.56 | AH169: =ROUNDUP(AN169,2) -> 67.6 | AJ169: =IF($V$4,AL169+AF169,AL169) -> 67.6 | AL169: =IF($V$5,Z169-Z169*10%,Z169) -> 67.6 | AN169: =IF($V$3,AJ169-((AJ169*1.18031)-AJ169),AJ169) -> 67.6
B170: 435-010-0035 | C170: Сверло по металлу HSS D3,5 | D170: 10 | E170: 10 | F170: 400 | G170: =AH170 -> 82.83 | I170: - | J170: =G170*H170 -> 0 | K170: 4673732411220 | M170: 4673732411237 | P170: =$P$8 -> 0 | R170: =IF(Q170>0,Q170,P170) -> 0 | S170: =IF(P170>18,"ПЕРЕБОР","-") -> - | T170: 66.2655 | V170: 1.25 | W170: =T170*V170 -> 82.831875 | X170: =R170*0.01 -> 0 | Y170: =W170-(W170*X170) -> 82.831875 | Z170: =ROUND(Y170,2) -> 82.83 | AB170: 0.043 | AC170: =H170*AB170 -> 0 | AD170: =AC170*$P$7 -> 0 | AE170: =AB170*$P$7 -> 0.688 | AF170: =ROUND(AE170,2) -> 0.69 | AH170: =ROUNDUP(AN170,2) -> 82.83 | AJ170: =IF($V$4,AL170+AF170,AL170) -> 82.83 | AL170: =IF($V$5,Z170-Z170*10%,Z170) -> 82.83 | AN170: =IF($V$3,AJ170-((AJ170*1.18031)-AJ170),AJ170) -> 82.83
B171: 435-010-0038 | C171: Сверло по металлу HSS D3,8 | D171: 10 | E171: 10 | F171: 400 | G171: =AH171 -> 83.14 | I171: - | J171: =G171*H171 -> 0 | K171: 4673732411244 | M171: 4673732411251 | P171: =$P$8 -> 0 | R171: =IF(Q171>0,Q171,P171) -> 0 | S171: =IF(P171>18,"ПЕРЕБОР","-") -> - | T171: 66.51 | V171: 1.25 | W171: =T171*V171 -> 83.1375 | X171: =R171*0.01 -> 0 | Y171: =W171-(W171*X171) -> 83.1375 | Z171: =ROUND(Y171,2) -> 83.14 | AB171: 0.0495 | AC171: =H171*AB171 -> 0 | AD171: =AC171*$P$7 -> 0 | AE171: =AB171*$P$7 -> 0.792 | AF171: =ROUND(AE171,2) -> 0.79 | AH171: =ROUNDUP(AN171,2) -> 83.14 | AJ171: =IF($V$4,AL171+AF171,AL171) -> 83.14 | AL171: =IF($V$5,Z171-Z171*10%,Z171) -> 83.14 | AN171: =IF($V$3,AJ171-((AJ171*1.18031)-AJ171),AJ171) -> 83.14
B172: 435-010-004 | C172: Сверло по металлу HSS D4 | D172: 10 | E172: 10 | F172: 400 | G172: =AH172 -> 100.96 | I172: - | J172: =G172*H172 -> 0 | K172: 4673732411268 | M172: 4673732411275 | P172: =$P$8 -> 0 | R172: =IF(Q172>0,Q172,P172) -> 0 | S172: =IF(P172>18,"ПЕРЕБОР","-") -> - | T172: 80.766 | V172: 1.25 | W172: =T172*V172 -> 100.9575 | X172: =R172*0.01 -> 0 | Y172: =W172-(W172*X172) -> 100.9575 | Z172: =ROUND(Y172,2) -> 100.96 | AB172: 0.0565 | AC172: =H172*AB172 -> 0 | AD172: =AC172*$P$7 -> 0 | AE172: =AB172*$P$7 -> 0.904 | AF172: =ROUND(AE172,2) -> 0.9 | AH172: =ROUNDUP(AN172,2) -> 100.96 | AJ172: =IF($V$4,AL172+AF172,AL172) -> 100.96 | AL172: =IF($V$5,Z172-Z172*10%,Z172) -> 100.96 | AN172: =IF($V$3,AJ172-((AJ172*1.18031)-AJ172),AJ172) -> 100.96
B173: 435-010-0042 | C173: Сверло по металлу HSS D4,2 | D173: 10 | E173: 10 | F173: 200 | G173: =AH173 -> 101.48 | I173: - | J173: =G173*H173 -> 0 | K173: 4673732411282 | M173: 4673732411299 | P173: =$P$8 -> 0 | R173: =IF(Q173>0,Q173,P173) -> 0 | S173: =IF(P173>18,"ПЕРЕБОР","-") -> - | T173: 81.18 | V173: 1.25 | W173: =T173*V173 -> 101.475 | X173: =R173*0.01 -> 0 | Y173: =W173-(W173*X173) -> 101.475 | Z173: =ROUND(Y173,2) -> 101.48 | AB173: 0.059 | AC173: =H173*AB173 -> 0 | AD173: =AC173*$P$7 -> 0 | AE173: =AB173*$P$7 -> 0.944 | AF173: =ROUND(AE173,2) -> 0.94 | AH173: =ROUNDUP(AN173,2) -> 101.48 | AJ173: =IF($V$4,AL173+AF173,AL173) -> 101.48 | AL173: =IF($V$5,Z173-Z173*10%,Z173) -> 101.48 | AN173: =IF($V$3,AJ173-((AJ173*1.18031)-AJ173),AJ173) -> 101.48
B174: 435-010-0045 | C174: Сверло по металлу HSS D4,5 | D174: 10 | E174: 10 | F174: 200 | G174: =AH174 -> 101.9 | I174: - | J174: =G174*H174 -> 0 | K174: 4673732411305 | M174: 4673732411312 | P174: =$P$8 -> 0 | R174: =IF(Q174>0,Q174,P174) -> 0 | S174: =IF(P174>18,"ПЕРЕБОР","-") -> - | T174: 81.52 | V174: 1.25 | W174: =T174*V174 -> 101.9 | X174: =R174*0.01 -> 0 | Y174: =W174-(W174*X174) -> 101.9 | Z174: =ROUND(Y174,2) -> 101.9 | AB174: 0.0715 | AC174: =H174*AB174 -> 0 | AD174: =AC174*$P$7 -> 0 | AE174: =AB174*$P$7 -> 1.144 | AF174: =ROUND(AE174,2) -> 1.14 | AH174: =ROUNDUP(AN174,2) -> 101.9 | AJ174: =IF($V$4,AL174+AF174,AL174) -> 101.9 | AL174: =IF($V$5,Z174-Z174*10%,Z174) -> 101.9 | AN174: =IF($V$3,AJ174-((AJ174*1.18031)-AJ174),AJ174) -> 101.9
B175: 435-010-0048 | C175: Сверло по металлу HSS D4,8 | D175: 10 | E175: 10 | F175: 200 | G175: =AH175 -> 133.94 | I175: - | J175: =G175*H175 -> 0 | K175: 4673732411329 | M175: 4673732411336 | P175: =$P$8 -> 0 | R175: =IF(Q175>0,Q175,P175) -> 0 | S175: =IF(P175>18,"ПЕРЕБОР","-") -> - | T175: 107.15 | V175: 1.25 | W175: =T175*V175 -> 133.9375 | X175: =R175*0.01 -> 0 | Y175: =W175-(W175*X175) -> 133.9375 | Z175: =ROUND(Y175,2) -> 133.94 | AB175: 0.079 | AC175: =H175*AB175 -> 0 | AD175: =AC175*$P$7 -> 0 | AE175: =AB175*$P$7 -> 1.264 | AF175: =ROUND(AE175,2) -> 1.26 | AH175: =ROUNDUP(AN175,2) -> 133.94 | AJ175: =IF($V$4,AL175+AF175,AL175) -> 133.94 | AL175: =IF($V$5,Z175-Z175*10%,Z175) -> 133.94 | AN175: =IF($V$3,AJ175-((AJ175*1.18031)-AJ175),AJ175) -> 133.94
B176: 435-010-005 | C176: Сверло по металлу HSS D5 | D176: 10 | E176: 10 | F176: 200 | G176: =AH176 -> 131.33 | I176: - | J176: =G176*H176 -> 0 | K176: 4673732411343 | M176: 4673732411350 | P176: =$P$8 -> 0 | R176: =IF(Q176>0,Q176,P176) -> 0 | S176: =IF(P176>18,"ПЕРЕБОР","-") -> - | T176: 105.063 | V176: 1.25 | W176: =T176*V176 -> 131.32875 | X176: =R176*0.01 -> 0 | Y176: =W176-(W176*X176) -> 131.32875 | Z176: =ROUND(Y176,2) -> 131.33 | AB176: 0.0895 | AC176: =H176*AB176 -> 0 | AD176: =AC176*$P$7 -> 0 | AE176: =AB176*$P$7 -> 1.432 | AF176: =ROUND(AE176,2) -> 1.43 | AH176: =ROUNDUP(AN176,2) -> 131.33 | AJ176: =IF($V$4,AL176+AF176,AL176) -> 131.33 | AL176: =IF($V$5,Z176-Z176*10%,Z176) -> 131.33 | AN176: =IF($V$3,AJ176-((AJ176*1.18031)-AJ176),AJ176) -> 131.33
B177: 435-010-0052 | C177: Сверло по металлу HSS D5,2 РАСПРОДАЖА! | D177: 10 | E177: 10 | F177: 200 | G177: =AH177 -> 93.75 | I177: - | J177: =G177*H177 -> 0 | K177: 4673732411367 | M177: 4673732411374 | P177: =$P$8 -> 0 | R177: =IF(Q177>0,Q177,P177) -> 0 | S177: =IF(P177>18,"ПЕРЕБОР","-") -> - | T177: 75 | V177: 1.25 | W177: =T177*V177 -> 93.75 | X177: =R177*0.01 -> 0 | Y177: =W177-(W177*X177) -> 93.75 | Z177: =ROUND(Y177,2) -> 93.75 | AB177: 0.1055 | AC177: =H177*AB177 -> 0 | AD177: =AC177*$P$7 -> 0 | AE177: =AB177*$P$7 -> 1.688 | AF177: =ROUND(AE177,2) -> 1.69 | AH177: =ROUNDUP(AN177,2) -> 93.75 | AJ177: =IF($V$4,AL177+AF177,AL177) -> 93.75 | AL177: =IF($V$5,Z177-Z177*10%,Z177) -> 93.75 | AN177: =IF($V$3,AJ177-((AJ177*1.18031)-AJ177),AJ177) -> 93.75
B178: 435-010-0055 | C178: Сверло по металлу HSS D5,5 | D178: 10 | E178: 5 | F178: 100 | G178: =AH178 -> 163.98 | I178: - | J178: =G178*H178 -> 0 | K178: 4673732411381 | M178: 4673732411398 | P178: =$P$8 -> 0 | R178: =IF(Q178>0,Q178,P178) -> 0 | S178: =IF(P178>18,"ПЕРЕБОР","-") -> - | T178: 131.18 | V178: 1.25 | W178: =T178*V178 -> 163.975 | X178: =R178*0.01 -> 0 | Y178: =W178-(W178*X178) -> 163.975 | Z178: =ROUND(Y178,2) -> 163.98 | AB178: 0.119 | AC178: =H178*AB178 -> 0 | AD178: =AC178*$P$7 -> 0 | AE178: =AB178*$P$7 -> 1.904 | AF178: =ROUND(AE178,2) -> 1.9 | AH178: =ROUNDUP(AN178,2) -> 163.98 | AJ178: =IF($V$4,AL178+AF178,AL178) -> 163.98 | AL178: =IF($V$5,Z178-Z178*10%,Z178) -> 163.98 | AN178: =IF($V$3,AJ178-((AJ178*1.18031)-AJ178),AJ178) -> 163.98
... B201: 435-010-0185 | C201: Сверло по металлу HSS D18,5 РАСПРОДАЖА! | D201: 1 | E201: 12 | F201: 60 | G201: =AH201 -> 248.75 | I201: - | J201: =G201*H201 -> 0 | K201: 4673732411909 | M201: 4673732411916 | P201: =$P$8 -> 0 | R201: =IF(Q201>0,Q201,P201) -> 0 | S201: =IF(P201>18,"ПЕРЕБОР","-") -> - | T201: 199 | V201: 1.25 | W201: =T201*V201 -> 248.75 | X201: =R201*0.01 -> 0 | Y201: =W201-(W201*X201) -> 248.75 | Z201: =ROUND(Y201,2) -> 248.75 | AB201: 0.2917 | AC201: =H201*AB201 -> 0 | AD201: =AC201*$P$7 -> 0 | AE201: =AB201*$P$7 -> 4.6672 | AF201: =ROUND(AE201,2) -> 4.67 | AH201: =ROUNDUP(AN201,2) -> 248.75 | AJ201: =IF($V$4,AL201+AF201,AL201) -> 248.75 | AL201: =IF($V$5,Z201-Z201*10%,Z201) -> 248.75 | AN201: =IF($V$3,AJ201-((AJ201*1.18031)-AJ201),AJ201) -> 248.75
B202: Сверло по металлу HSS (длинное, 300мм) | O202: Сверло по металлу HSS длинное
B203: 435-777-03300 | C203: Сверло по металлу HSS длинное L300 D3 | D203: 1 | E203: 50 | F203: 500 | G203: =AH203 -> 110.19 | I203: - | J203: =G203*H203 -> 0 | K203: 4673743520829 | M203: 4673743520836 | P203: =$P$8 -> 0 | R203: =IF(Q203>0,Q203,P203) -> 0 | S203: =IF(P203>18,"ПЕРЕБОР","-") -> - | T203: 88.15 | V203: 1.25 | W203: =T203*V203 -> 110.1875 | X203: =R203*0.01 -> 0 | Y203: =W203-(W203*X203) -> 110.1875 | Z203: =ROUND(Y203,2) -> 110.19 | AB203: 0.032 | AC203: =H203*AB203 -> 0 | AD203: =AC203*$P$7 -> 0 | AE203: =AB203*$P$7 -> 0.512 | AF203: =ROUND(AE203,2) -> 0.51 | AH203: =ROUNDUP(AN203,2) -> 110.19 | AJ203: =IF($V$4,AL203+AF203,AL203) -> 110.19 | AL203: =IF($V$5,Z203-Z203*10%,Z203) -> 110.19 | AN203: =IF($V$3,AJ203-((AJ203*1.18031)-AJ203),AJ203) -> 110.19
B204: 435-777-04300 | C204: Сверло по металлу HSS длинное L300 D4 | D204: 1 | E204: 50 | F204: 500 | G204: =AH204 -> 101.19 | I204: - | J204: =G204*H204 -> 0 | K204: 4673743520980 | M204: 4673743520997 | P204: =$P$8 -> 0 | R204: =IF(Q204>0,Q204,P204) -> 0 | S204: =IF(P204>18,"ПЕРЕБОР","-") -> - | T204: 80.95 | V204: 1.25 | W204: =T204*V204 -> 101.1875 | X204: =R204*0.01 -> 0 | Y204: =W204-(W204*X204) -> 101.1875 | Z204: =ROUND(Y204,2) -> 101.19 | AB204: 0.04 | AC204: =H204*AB204 -> 0 | AD204: =AC204*$P$7 -> 0 | AE204: =AB204*$P$7 -> 0.64 | AF204: =ROUND(AE204,2) -> 0.64 | AH204: =ROUNDUP(AN204,2) -> 101.19 | AJ204: =IF($V$4,AL204+AF204,AL204) -> 101.19 | AL204: =IF($V$5,Z204-Z204*10%,Z204) -> 101.19 | AN204: =IF($V$3,AJ204-((AJ204*1.18031)-AJ204),AJ204) -> 101.19
B205: 435-777-05300 | C205: Сверло по металлу HSS длинное L300 D5 | D205: 1 | E205: 50 | F205: 500 | G205: =AH205 -> 146.78 | I205: - | J205: =G205*H205 -> 0 | K205: 4673743521000 | M205: 4673743521017 | P205: =$P$8 -> 0 | R205: =IF(Q205>0,Q205,P205) -> 0 | S205: =IF(P205>18,"ПЕРЕБОР","-") -> - | T205: 117.425 | V205: 1.25 | W205: =T205*V205 -> 146.78125 | X205: =R205*0.01 -> 0 | Y205: =W205-(W205*X205) -> 146.78125 | Z205: =ROUND(Y205,2) -> 146.78 | AB205: 0.05 | AC205: =H205*AB205 -> 0 | AD205: =AC205*$P$7 -> 0 | AE205: =AB205*$P$7 -> 0.8 | AF205: =ROUND(AE205,2) -> 0.8 | AH205: =ROUNDUP(AN205,2) -> 146.78 | AJ205: =IF($V$4,AL205+AF205,AL205) -> 146.78 | AL205: =IF($V$5,Z205-Z205*10%,Z205) -> 146.78 | AN205: =IF($V$3,AJ205-((AJ205*1.18031)-AJ205),AJ205) -> 146.78
B206: 435-777-06300 | C206: Сверло по металлу HSS длинное L300 D6 | D206: 1 | E206: 50 | F206: 500 | G206: =AH206 -> 176.19 | I206: - | J206: =G206*H206 -> 0 | K206: 4673743521024 | M206: 4673743521031 | P206: =$P$8 -> 0 | R206: =IF(Q206>0,Q206,P206) -> 0 | S206: =IF(P206>18,"ПЕРЕБОР","-") -> - | T206: 140.954 | V206: 1.25 | W206: =T206*V206 -> 176.1925 | X206: =R206*0.01 -> 0 | Y206: =W206-(W206*X206) -> 176.1925 | Z206: =ROUND(Y206,2) -> 176.19 | AB206: 0.066 | AC206: =H206*AB206 -> 0 | AD206: =AC206*$P$7 -> 0 | AE206: =AB206*$P$7 -> 1.056 | AF206: =ROUND(AE206,2) -> 1.06 | AH206: =ROUNDUP(AN206,2) -> 176.19 | AJ206: =IF($V$4,AL206+AF206,AL206) -> 176.19 | AL206: =IF($V$5,Z206-Z206*10%,Z206) -> 176.19 | AN206: =IF($V$3,AJ206-((AJ206*1.18031)-AJ206),AJ206) -> 176.19
B207: 435-777-07300 | C207: Сверло по металлу HSS длинное L300 D7 | D207: 1 | E207: 50 | F207: 300 | G207: =AH207 -> 193.24 | I207: - | J207: =G207*H207 -> 0 | K207: 4673743521048 | M207: 4673743521055 | P207: =$P$8 -> 0 | R207: =IF(Q207>0,Q207,P207) -> 0 | S207: =IF(P207>18,"ПЕРЕБОР","-") -> - | T207: 154.59 | V207: 1.25 | W207: =T207*V207 -> 193.2375 | X207: =R207*0.01 -> 0 | Y207: =W207-(W207*X207) -> 193.2375 | Z207: =ROUND(Y207,2) -> 193.24 | AB207: 0.0833 | AC207: =H207*AB207 -> 0 | AD207: =AC207*$P$7 -> 0 | AE207: =AB207*$P$7 -> 1.3328 | AF207: =ROUND(AE207,2) -> 1.33 | AH207: =ROUNDUP(AN207,2) -> 193.24 | AJ207: =IF($V$4,AL207+AF207,AL207) -> 193.24 | AL207: =IF($V$5,Z207-Z207*10%,Z207) -> 193.24 | AN207: =IF($V$3,AJ207-((AJ207*1.18031)-AJ207),AJ207) -> 193.24
B208: 435-777-08300 | C208: Сверло по металлу HSS длинное L300 D8 | D208: 1 | E208: 50 | F208: 250 | G208: =AH208 -> 233.5 | I208: - | J208: =G208*H208 -> 0 | K208: 4673743521062 | M208: 4673743521079 | P208: =$P$8 -> 0 | R208: =IF(Q208>0,Q208,P208) -> 0 | S208: =IF(P208>18,"ПЕРЕБОР","-") -> - | T208: 186.8 | V208: 1.25 | W208: =T208*V208 -> 233.5 | X208: =R208*0.01 -> 0 | Y208: =W208-(W208*X208) -> 233.5 | Z208: =ROUND(Y208,2) -> 233.5 | AB208: 0.1 | AC208: =H208*AB208 -> 0 | AD208: =AC208*$P$7 -> 0 | AE208: =AB208*$P$7 -> 1.6 | AF208: =ROUND(AE208,2) -> 1.6 | AH208: =ROUNDUP(AN208,2) -> 233.5 | AJ208: =IF($V$4,AL208+AF208,AL208) -> 233.5 | AL208: =IF($V$5,Z208-Z208*10%,Z208) -> 233.5 | AN208: =IF($V$3,AJ208-((AJ208*1.18031)-AJ208),AJ208) -> 233.5
B209: 435-777-09300 | C209: Сверло по металлу HSS длинное L300 D9 | D209: 1 | E209: 50 | F209: 200 | G209: =AH209 -> 275.76 | I209: - | J209: =G209*H209 -> 0 | K209: 4673743521086 | M209: 4673743521093 | P209: =$P$8 -> 0 | R209: =IF(Q209>0,Q209,P209) -> 0 | S209: =IF(P209>18,"ПЕРЕБОР","-") -> - | T209: 220.61 | V209: 1.25 | W209: =T209*V209 -> 275.7625 | X209: =R209*0.01 -> 0 | Y209: =W209-(W209*X209) -> 275.7625 | Z209: =ROUND(Y209,2) -> 275.76 | AB209: 0.125 | AC209: =H209*AB209 -> 0 | AD209: =AC209*$P$7 -> 0 | AE209: =AB209*$P$7 -> 2 | AF209: =ROUND(AE209,2) -> 2 | AH209: =ROUNDUP(AN209,2) -> 275.76 | AJ209: =IF($V$4,AL209+AF209,AL209) -> 275.76 | AL209: =IF($V$5,Z209-Z209*10%,Z209) -> 275.76 | AN209: =IF($V$3,AJ209-((AJ209*1.18031)-AJ209),AJ209) -> 275.76
B210: 435-777-10300 | C210: Сверло по металлу HSS длинное L300 D10 | D210: 1 | E210: 15 | F210: 150 | G210: =AH210 -> 337.81 | I210: - | J210: =G210*H210 -> 0 | K210: 4673743521109 | M210: 4673743521116 | P210: =$P$8 -> 0 | R210: =IF(Q210>0,Q210,P210) -> 0 | S210: =IF(P210>18,"ПЕРЕБОР","-") -> - | T210: 270.25 | V210: 1.25 | W210: =T210*V210 -> 337.8125 | X210: =R210*0.01 -> 0 | Y210: =W210-(W210*X210) -> 337.8125 | Z210: =ROUND(Y210,2) -> 337.81 | AB210: 0.1467 | AC210: =H210*AB210 -> 0 | AD210: =AC210*$P$7 -> 0 | AE210: =AB210*$P$7 -> 2.3472 | AF210: =ROUND(AE210,2) -> 2.35 | AH210: =ROUNDUP(AN210,2) -> 337.81 | AJ210: =IF($V$4,AL210+AF210,AL210) -> 337.81 | AL210: =IF($V$5,Z210-Z210*10%,Z210) -> 337.81 | AN210: =IF($V$3,AJ210-((AJ210*1.18031)-AJ210),AJ210) -> 337.81
...

Sheet KRONbuild
D2: +7 (926) 489-69-85 (Москва) 8 (423) 200-02-26 (Владивосток) www.kronbuild.ru | G2: +7 (926) 489-69-85 (Москва) 8 (423) 200-02-26 (Владивосток) www.headrock.ru
A8: Сентябрь 2026 | J8: =I195 -> 0
A9: артикул | B9: изображение | C9: наименование | D9: вес (грамм) | E9: выход (литров) | F9: количество в коробке | G9: Цена в руб. (с НДС 22%): | H9: Ваш заказ (коробок) | I9: Ваш заказ (штук/комплектов) | J9: Сумма заказа в руб. (с НДС 20%) | L9: Штрихкод штуки | M9: Штрихкод коробки
C10: Профессиональная монтажная пена KRONbuild (пистолетная)
A11: FWPM80 | C11: Зима Masters 80 | D11: 1000 | E11: 80 | F11: 12 | G11: ='+'!AI11 -> 446.25 | I11: =H11*F11 -> 0 | J11: =G11*I11 -> 0 | L11: 4660447836226 | M11: 4673759127258
A12: FSPM80 | C12: Лето Masters 80 АКЦИЯ! | D12: 1000 | E12: 80 | F12: 12 | G12: ='+'!AI12 -> 383.75 | I12: =H12*F12 -> 0 | J12: =G12*I12 -> 0 | L12: 4660447836233 | M12: 4673759127272
A13: FSP70 | C13: Лето PRO 70 АКЦИЯ! | D13: 950 | E13: 70 | F13: 12 | G13: ='+'!AI13 -> 335 | I13: =H13*F13 -> 0 | J13: =G13*I13 -> 0 | L13: 4660447836295 | M13: 4627168565842
A14: FSU65 | C14: Лето Ultra 65 АКЦИЯ! | D14: 850 | E14: 65 | F14: 12 | G14: ='+'!AI14 -> 315 | I14: =H14*F14 -> 0 | J14: =G14*I14 -> 0 | L14: 4660447836301 | M14: 4627168562827
A15: FAS70 | C15: Всесезонная PRO 70 | D15: 950 | E15: 70 | F15: 12 | G15: ='+'!AI15 -> 396.25 | I15: =H15*F15 -> 0 | J15: =G15*I15 -> 0 | L15: 4660447836257 | M15: 4627198693171
A16: FAS65U | C16: Всесезонная Ultra 65 | D16: 850 | E16: 65 | F16: 12 | G16: ='+'!AI16 -> 353.75 | I16: =H16*F16 -> 0 | J16: =G16*I16 -> 0 | L16: 4660447836264 | M16: 4627168566122
A17: FWP70 | C17: Зима PRO 70 | D17: 950 | E17: 70 | F17: 12 | G17: ='+'!AI17 -> 392.5 | I17: =H17*F17 -> 0 | J17: =G17*I17 -> 0 | L17: 4660447836271 | M17: 14627147350046
A18: FWU65 | C18: Зима Ultra 65 | D18: 850 | E18: 65 | F18: 12 | G18: ='+'!AI18 -> 375 | I18: =H18*F18 -> 0 | J18: =G18*I18 -> 0 | L18: 4660447836288 | M18: 4627168562803
C19: Профессиональная общестроительная монтажная пена KRONbuild (пистолетная)
A20: FSS65 | C20: Лето Standart 65 АКЦИЯ! | D20: 800 | E20: 65 | F20: 12 | G20: ='+'!AI20 -> 292.5 | I20: =H20*F20 -> 0 | J20: =G20*I20 -> 0 | L20: 4660447836356 | M20: 4627168565866
A21: FASST | C21: Всесезонная Standart 65 | D21: 800 | E21: 65 | F21: 12 | G21: ='+'!AI21 -> 337.5 | I21: =H21*F21 -> 0 | J21: =G21*I21 -> 0 | L21: 4660447836332 | M21: 4673732414528
A22: FASGUN65 | C22: Всесезонная HANDGUN 65 | D22: 800 | E22: 65 | F22: 12 | G22: ='+'!AI22 -> 351.25 | I22: =H22*F22 -> 0 | J22: =G22*I22 -> 0 | L22: 4660447836240 | M22: 4673759127234
A23: FAO65 | C23: Всесезонная ONE 65 | D23: 770 | E23: 65 | F23: 12 | G23: ='+'!AI23 -> 293.75 | I23: =H23*F23 -> 0 | J23: =G23*I23 -> 0 | L23: 4660447836325 | M23: 4627198692020
A24: FAS650 | C24: Всесезонная 65 | D24: 650 | E24: 65 | F24: 12 | G24: ='+'!AI24 -> 270 | I24: =H24*F24 -> 0 | J24: =G24*I24 -> 0 | L24: 4660447836318 | M24: 4627198691986
A25: FWS65 | C25: Зима Standart 65 | D25: 800 | E25: 65 | F25: 12 | G25: ='+'!AI25 -> 352.5 | I25: =H25*F25 -> 0 | J25: =G25*I25 -> 0 | L25: 4660447836349 | M25: 14627147350039
C26: Профессиональная специальная монтажная пена KRONbuild (пистолетная)
A27: FPFB1 | C27: Огнестойкая B1 | D27: 850 | E27: 65 | F27: 12 | G27: ='+'!AI27 -> 475 | I27: =H27*F27 -> 0 | J27: =G27*I27 -> 0 | L27: 4660447836387 | M27: 4673732414252
A28: FC850 | C28: Цемент-пена | D28: 900 | E28: - | F28: 12 | G28: ='+'!AI28 -> 515 | I28: =H28*F28 -> 0 | J28: =G28*I28 -> 0 | L28: 4660447836394 | M28: 4673743522878
A29: PUI90 | C29: Напыляемый утеплитель + насадка-распылитель | D29: 900 | E29: - | F29: 12 | G29: ='+'!AI29 -> 555 | I29: =H29*F29 -> 0 | J29: =G29*I29 -> 0 | L29: 4660447836370 | M29: 4673732414917
A30: GF800 | C30: Клей-пена | D30: 800 | E30: 65 | F30: 12 | G30: ='+'!AI30 -> 398.75 | I30: =H30*F30 -> 0 | J30: =G30*I30 -> 0 | L30: 4660447836363 | M30: 4627198692006
C31: Бытовая монтажная пена KRONbuild
A32: FH200 | C32: Всесезонная 20+ | D32: 380 | E32: 20+ | F32: 12 | G32: ='+'!AI32 -> 176.25 | I32: =H32*F32 -> 0 | J32: =G32*I32 -> 0 | L32: 4660447836189 | M32: 14627155466425
A33: FH400 | C33: Всесезонная 40+ | D33: 500 | E33: 40+ | F33: 12 | G33: ='+'!AI33 -> 220 | I33: =H33*F33 -> 0 | J33: =G33*I33 -> 0 | L33: 4660447836196 | M33: 4627168566771
A34: FHO65 | C34: Всесезонная ONE 65 | D34: 770 | E34: 65 | F34: 12 | G34: ='+'!AI34 -> 293.75 | I34: =H34*F34 -> 0 | J34: =G34*I34 -> 0 | L34: 4660447836202 | M34: 4627181320091
C35: Очиститель монтажной пены KRONbuild
A36: CF351 | C36: Очиститель монтажной пены | D36: 350 | E36: - | F36: 12 | G36: ='+'!AI36 -> 140 | I36: =H36*F36 -> 0 | J36: =G36*I36 -> 0 | L36: 4627147350025 | M36: 14627147350022
C37: Герметики KRONbuild
A38: SUT80 | C38: Герметик универсальный (бесцветный) 80 мл | D38: 80 | E38: - | F38: 12 | G38: ='+'!AI38 -> 120 | I38: =H38*F38 -> 0 | J38: =G38*I38 -> 0 | L38: 4660447835984 | M38: 4673743524407
A39: SUW80 | C39: Герметик универсальный (белый) 80 мл | D39: 80 | E39: - | F39: 12 | G39: ='+'!AI39 -> 120 | I39: =H39*F39 -> 0 | J39: =G39*I39 -> 0 | L39: 4660447835960 | M39: 4673743524414
A40: SST80 | C40: Герметик санитарный (бесцветный) 80 мл | D40: 80 | E40: - | F40: 12 | G40: ='+'!AI40 -> 122.5 | I40: =H40*F40 -> 0 | J40: =G40*I40 -> 0 | L40: 4660447835946 | M40: 4673743524421
A41: SSW80 | C41: Герметик санитарный (белый) 80 мл | D41: 80 | E41: - | F41: 12 | G41: ='+'!AI41 -> 122.5 | I41: =H41*F41 -> 0 | J41: =G41*I41 -> 0 | L41: 4660447835922 | M41: 4673743524438
A42: SNT60 | C42: Герметик силиконовый нейтральный (бесцветный) 600 мл. | D42: 550 | E42: - | F42: 20 | G42: ='+'!AI42 -> 298.75 | I42: =H42*F42 -> 0 | J42: =G42*I42 -> 0 | L42: 4660447835908 | M42: 4673743522335
A43: SNW28 | C43: Герметик нейтральный (белый) 280 мл. | D43: 430 | E43: - | F43: 24 | G43: ='+'!AI43 -> 147.5 | I43: =H43*F43 -> 0 | J43: =G43*I43 -> 0 | L43: 4660447835885 | M43: 14627147356161
A44: SNT28 | C44: Герметик нейтральный (бесцветный) 280 мл. | D44: 300 | E44: - | F44: 24 | G44: ='+'!AI44 -> 150 | I44: =H44*F44 -> 0 | J44: =G44*I44 -> 0 | L44: 4660447835892 | M44: 4627168563428
A45: SSW28 | C45: Герметик санитарный (белый) 280 мл. | D45: 300 | E45: - | F45: 24 | G45: ='+'!AI45 -> 131.25 | I45: =H45*F45 -> 0 | J45: =G45*I45 -> 0 | L45: 4660447835915 | M45: 14627155469785
A46: SST28 | C46: Герметик санитарный (бесцветный) 280 мл. | D46: 300 | E46: - | F46: 24 | G46: ='+'!AI46 -> 131.25 | I46: =H46*F46 -> 0 | J46: =G46*I46 -> 0 | L46: 4660447835939 | M46: 4627168563442
A47: SUW28 | C47: Герметик универсальный (белый) 280 мл. | D47: 300 | E47: - | F47: 24 | G47: ='+'!AI47 -> 128.75 | I47: =H47*F47 -> 0 | J47: =G47*I47 -> 0 | L47: 4660447835953 | M47: 14627147354778
A48: SUT28 | C48: Герметик универсальный (бесцветный) 280 мл. | D48: 300 | E48: - | F48: 24 | G48: ='+'!AI48 -> 128.75 | I48: =H48*F48 -> 0 | J48: =G48*I48 -> 0 | L48: 4660447835977 | M48: 4627168563466
A49: SUB28 | C49: Герметик универсальный (чёрный) 280 мл. | D49: 300 | E49: - | F49: 24 | G49: ='+'!AI49 -> 128.75 | I49: =H49*F49 -> 0 | J49: =G49*I49 -> 0 | L49: 4660447835991 | M49: 4673743520423
... A51: ASA28 | C51: Герметик акриловый (белый) 280 мл. | D51: 420 | E51: - | F51: 24 | G51: ='+'!AI51 -> 136.25 | I51: =H51*F51 -> 0 | J51: =G51*I51 -> 0 | L51: 4660447835861 | M51: 14627155469792
C52: Специализированные герметики KRONbuild
A53: PSG78 | C53: Герметик полиуретановый PU-40 (серый) 600 мл. | D53: 870 | E53: - | F53: 20 | G53: ='+'!AI53 -> 315 | I53: =H53*F53 -> 0 | J53: =G53*I53 -> 0 | L53: 4660447836110 | M53: 14627181321927
A54: PSB78 | C54: Герметик полиуретановый PU-40 (черный) 600 мл. | D54: 870 | E54: - | F54: 20 | G54: ='+'!AI54 -> 315 | I54: =H54*F54 -> 0 | J54: =G54*I54 -> 0 | L54: 4660447836127 | M54: 14627181322351
A55: PSW78 | C55: Герметик полиуретановый PU-40 (белый) 600 мл. | D55: 870 | E55: - | F55: 20 | G55: ='+'!AI55 -> 315 | I55: =H55*F55 -> 0 | J55: =G55*I55 -> 0 | L55: 4660447836103 | M55: 14627181322375
A56: WS650 | C56: Герметик атмосферостойкий силиконовый (черный) | D56: 870 | E56: - | F56: 20 | G56: ='+'!AI56 -> 341.25 | I56: =H56*F56 -> 0 | J56: =G56*I56 -> 0 | L56: 4660447836011 | M56: 4673732414207
A57: SHR30 | C57: Герметик высокотемпературный 300°C (красный) 300 мл. | D57: 370 | E57: - | F57: 24 | G57: ='+'!AI57 -> 298.75 | I57: =H57*F57 -> 0 | J57: =G57*I57 -> 0 | L57: 4660447836134 | M57: 4673743522175
A58: SAT30 | C58: Герметик аквариумный (бесцветный) 280 мл. | D58: 300 | E58: - | F58: 24 | G58: ='+'!AI58 -> 206.25 | I58: =H58*F58 -> 0 | J58: =G58*I58 -> 0 | L58: 4660447836141 | M58: 4673732414573
A59: SAB30 | C59: Герметик аквариумный (чёрный) 280 мл. | D59: 300 | E59: - | F59: 24 | G59: ='+'!AI59 -> 206.25 | I59: =H59*F59 -> 0 | J59: =G59*I59 -> 0 | L59: 4660447836158 | M59: 4673732414887
C60: Жидкие гвозди KRONbuild
A61: LNB39 | C61: Клей монтажный "Жидкие гвозди" (бежевый) | D61: 390 | E61: - | F61: 24 | G61: ='+'!AI61 -> 185 | I61: =H61*F61 -> 0 | J61: =G61*I61 -> 0 | L61: 4627181328561 | M61: 4627181328578
A62: LNW39 | C62: Клей монтажный "Жидкие гвозди" (белый) | D62: 450 | E62: - | F62: 24 | G62: ='+'!AI62 -> 185 | I62: =H62*F62 -> 0 | J62: =G62*I62 -> 0 | L62: 4673743522847 | M62: 4673743522854
A63: MSC36 | C63: Клей-герметик на основе гибридных полимеров Crystal (прозрачный) | D63: 360 | E63: - | F63: 24 | G63: ='+'!AI63 -> 356.25 | I63: =H63*F63 -> 0 | J63: =G63*I63 -> 0 | L63: 4660447836004 | M63: 4627181328554
C64: Герметик акриловый пароизоляционный KRONBuild
A65: ASIW7KG | C65: Герметик акриловый пароизоляционный KRONBuild белый 7кг | D65: 7000 | E65: - | F65: 1 | G65: ='+'!AI65 -> 1265 | I65: =H65*F65 -> 0 | J65: =G65*I65 -> 0 | L65: 4660447836035 | M65: -
A66: ASIG7KG | C66: Герметик акриловый пароизоляционный KRONBuild серый 7кг | D66: 7000 | E66: - | F66: 1 | G66: ='+'!AI66 -> 1265 | I66: =H66*F66 -> 0 | J66: =G66*I66 -> 0 | L66: 4660447836059 | M66: -
A67: ASIW930 | C67: Герметик акриловый пароизоляционный KRONBuild белый 600мл | D67: 930 | E67: - | F67: 20 | G67: ='+'!AI67 -> 206.25 | I67: =H67*F67 -> 0 | J67: =G67*I67 -> 0 | L67: 4660447836028 | M67: 4673768182651
A68: ASIG930 | C68: Герметик акриловый пароизоляционный KRONBuild серый 600мл | D68: 930 | E68: - | F68: 20 | G68: ='+'!AI68 -> 206.25 | I68: =H68*F68 -> 0 | J68: =G68*I68 -> 0 | L68: 4660447836042 | M68: 4673768182675
C69: Герметик акриловый паропроницаемый KRONBuild
A70: ASW7KG | C70: Герметик акриловый паропроницаемый KRONBuild белый 7кг | D70: 7000 | E70: - | F70: 1 | G70: ='+'!AI70 -> 1280 | I70: =H70*F70 -> 0 | J70: =G70*I70 -> 0 | L70: 4660447836073 | M70: -
A71: ASG7KG | C71: Герметик акриловый паропроницаемый KRONBuild серый 7кг | D71: 7000 | E71: - | F71: 1 | G71: ='+'!AI71 -> 1280 | I71: =H71*F71 -> 0 | J71: =G71*I71 -> 0 | L71: 4660447836097 | M71: -
A72: ASW930 | C72: Герметик акриловый паропроницаемый KRONBuild белый 600мл | D72: 930 | E72: - | F72: 20 | G72: ='+'!AI72 -> 206.25 | I72: =H72*F72 -> 0 | J72: =G72*I72 -> 0 | L72: 4660447836066 | M72: 4673768182613
A73: ASG930 | C73: Герметик акриловый паропроницаемый KRONBuild серый 600мл | D73: 930 | E73: - | F73: 20 | G73: ='+'!AI73 -> 206.25 | I73: =H73*F73 -> 0 | J73: =G73*I73 -> 0 | L73: 4660447836080 | M73: 4673768182637
C74: Эмали, грунт KRONbuild
A75: SP1018G | C75: Эмаль акриловая RAL 1018 желтая глянец 520 мл. | D75: 310 | E75: - | F75: 12 | G75: ='+'!AI75 -> 172.5 | I75: =H75*F75 -> 0 | J75: =G75*I75 -> 0 | L75: 4673759126800 | M75: 4673759126817
A76: SP3020G | C76: Эмаль акриловая RAL 3020 красная глянец 520 мл. | D76: 310 | E76: - | F76: 12 | G76: ='+'!AI76 -> 172.5 | I76: =H76*F76 -> 0 | J76: =G76*I76 -> 0 | L76: 4673759126749 | M76: 4673759126756
A77: SP5005G | C77: Эмаль акриловая RAL 5005 синяя глянец 520 мл. | D77: 310 | E77: - | F77: 12 | G77: ='+'!AI77 -> 172.5 | I77: =H77*F77 -> 0 | J77: =G77*I77 -> 0 | L77: 4673759126763 | M77: 4673759126770
A78: SP6018G | C78: Эмаль акриловая RAL 6018 светло-зеленая глянец 520 мл. | D78: 310 | E78: - | F78: 12 | G78: ='+'!AI78 -> 172.5 | I78: =H78*F78 -> 0 | J78: =G78*I78 -> 0 | L78: 4673759126886 | M78: 4673759126893
A79: SP7046G | C79: Эмаль акриловая RAL 7046 темно-серая глянец 520 мл. | D79: 310 | E79: - | F79: 12 | G79: ='+'!AI79 -> 172.5 | I79: =H79*F79 -> 0 | J79: =G79*I79 -> 0 | L79: 4673759126862 | M79: 4673759126879
A80: SP8012G | C80: Эмаль акриловая RAL 8012 коричневая глянец 520 мл. | D80: 310 | E80: - | F80: 12 | G80: ='+'!AI80 -> 172.5 | I80: =H80*F80 -> 0 | J80: =G80*I80 -> 0 | L80: 4673759126909 | M80: 4673759126916
A81: SP9003G | C81: Эмаль акриловая RAL 9003 белая глянец 520 мл. | D81: 310 | E81: - | F81: 12 | G81: ='+'!AI81 -> 172.5 | I81: =H81*F81 -> 0 | J81: =G81*I81 -> 0 | L81: 4673759126701 | M81: 4673759126718
A82: SP9003M | C82: Эмаль акриловая RAL 9003 белая матовая 520 мл. | D82: 310 | E82: - | F82: 12 | G82: ='+'!AI82 -> 172.5 | I82: =H82*F82 -> 0 | J82: =G82*I82 -> 0 | L82: 4673759126725 | M82: 4673759126732
A83: SP9005G | C83: Эмаль акриловая RAL 9005 черная глянец 520 мл. | D83: 310 | E83: - | F83: 12 | G83: ='+'!AI83 -> 172.5 | I83: =H83*F83 -> 0 | J83: =G83*I83 -> 0 | L83: 4673759126664 | M83: 4673759126671
A84: SP9005M | C84: Эмаль акриловая RAL 9005 черная матовая 520 мл. | D84: 310 | E84: - | F84: 12 | G84: ='+'!AI84 -> 172.5 | I84: =H84*F84 -> 0 | J84: =G84*I84 -> 0 | L84: 4673759126688 | M84: 4673759126695
A85: SP3011G | C85: Эмаль акриловая RAL 3011 коричнево-красный глянец 520 мл. | D85: 310 | E85: - | F85: 12 | G85: ='+'!AI85 -> 172.5 | I85: =H85*F85 -> 0 | J85: =G85*I85 -> 0 | L85: 4673759127340 | M85: 4673759127357
A86: SP6005G | C86: Эмаль акриловая RAL 6005 зеленый мох глянец 520 мл. | D86: 310 | E86: - | F86: 12 | G86: ='+'!AI86 -> 172.5 | I86: =H86*F86 -> 0 | J86: =G86*I86 -> 0 | L86: 4673759127326 | M86: 4673759127333
... A113: SPSREM | C113: Удалитель наклеек 520 мл. | D113: 377 | E113: - | F113: 12 | G113: ='+'!AI113 -> 192.5 | I113: =H113*F113 -> 0 | J113: =G113*I113 -> 0 | L113: 4673743522304 | M113: 4673743522311
C114: Эпоксидные клея KRONbuild
A115: EXP06 | C115: Эпоксидный клей (смола+отвердитель) в шприце 6мл. | D115: 27 | E115: - | F115: 12 | G115: ='+'!AI115 -> 68.75 | I115: =H115*F115 -> 0 | J115: =G115*I115 -> 0 | L115: 4673759125902 | M115: 4673759127203
A116: EXP25 | C116: Эпоксидный клей (смола+отвердитель) в шприце 25мл. | D116: 59 | E116: - | F116: 12 | G116: ='+'!AI116 -> 120 | I116: =H116*F116 -> 0 | J116: =G116*I116 -> 0 | L116: 4673759125926 | M116: 4673759127210
C117: Супер клея KRONbuild
A118: CBR20 | C118: Супер-клей KRONbuild цианоакрилатный | D118: 20 | E118: - | F118: 20 | G118: ='+'!AI118 -> 108.75 | I118: =H118*F118 -> 0 | J118: =G118*I118 -> 0 | L118: 4673743520386 | M118: 4673743523301
A119: GSX03 | C119: Супер-клей гель KRONbuild цианоакрилатный | D119: 3 | E119: - | F119: 24 | G119: ='+'!AI119 -> 35 | I119: =H119*F119 -> 0 | J119: =G119*I119 -> 0 | L119: 4673743520409 | M119: 4673743523318
C120: Уплотнители самоклеящиеся KRONbuild
A121: SD1412B | C121: Уплотнитель самокл. KRONbuild D 14*12 мм, длина 40м, черный | D121: 1833 | E121: - | F121: 6 | G121: ='+'!AI121 -> 1237.5 | I121: =H121*F121 -> 0 | J121: =G121*I121 -> 0 | L121: 4673759129467 | M121: 4673759129474
A122: SD98W | C122: Уплотнитель самокл. KRONbuild D 9*8 мм, длина 100м, белый | D122: 1866 | E122: - | F122: 6 | G122: ='+'!AI122 -> 1228.31 | I122: =H122*F122 -> 0 | J122: =G122*I122 -> 0 | L122: 4673759129504 | M122: 4673759129511
A123: SD98B | C123: Уплотнитель самокл. KRONbuild D 9*8 мм, длина 100м, черный | D123: 1866 | E123: - | F123: 6 | G123: ='+'!AI123 -> 1228.31 | I123: =H123*F123 -> 0 | J123: =G123*I123 -> 0 | L123: 4673759129528 | M123: 4673759129535
A124: SD98BR | C124: Уплотнитель самокл. KRONbuild D 9*8 мм, длина 100м, коричневый | D124: 1866 | E124: - | F124: 6 | G124: ='+'!AI124 -> 1228.31 | I124: =H124*F124 -> 0 | J124: =G124*I124 -> 0 | L124: 4673759129542 | M124: 4673759129559
A125: SP955W | C125: Уплотнитель самокл. KRONbuild P 9*5,5 мм, длина 100м, белый | D125: 1566 | E125: - | F125: 6 | G125: ='+'!AI125 -> 1200 | I125: =H125*F125 -> 0 | J125: =G125*I125 -> 0 | L125: 4673759129382 | M125: 4673759129399
A126: SP955B | C126: Уплотнитель самокл. KRONbuild P 9*5,5 мм, длина 100м, черный | D126: 1566 | E126: - | F126: 6 | G126: ='+'!AI126 -> 1200 | I126: =H126*F126 -> 0 | J126: =G126*I126 -> 0 | L126: 4673759129405 | M126: 4673759129412
A127: SP955BR | C127: Уплотнитель самокл. KRONbuild P 9*5,5 мм, длина 100м, коричневый | D127: 1566 | E127: - | F127: 6 | G127: ='+'!AI127 -> 1200 | I127: =H127*F127 -> 0 | J127: =G127*I127 -> 0 | L127: 4673759129429 | M127: 4673759129436
A128: SE94W | C128: Уплотнитель самокл. KRONbuild E 9*4 мм, длина 150м, белый | D128: 1966 | E128: - | F128: 6 | G128: ='+'!AI128 -> 1498.75 | I128: =H128*F128 -> 0 | J128: =G128*I128 -> 0 | L128: 4673759129320 | M128: 4673759129337
A129: SE94B | C129: Уплотнитель самокл. KRONbuild E 9*4 мм, длина 150м, черный | D129: 1966 | E129: - | F129: 6 | G129: ='+'!AI129 -> 1498.75 | I129: =H129*F129 -> 0 | J129: =G129*I129 -> 0 | L129: 4673759129344 | M129: 4673759129351
A130: SE94BR | C130: Уплотнитель самокл. KRONbuild E 9*4 мм, длина 150м, коричневый | D130: 1966 | E130: - | F130: 6 | G130: ='+'!AI130 -> 1498.75 | I130: =H130*F130 -> 0 | J130: =G130*I130 -> 0 | L130: 4673759129368 | M130: 4673759129375
C131: Дюбели рамные KRONbuild
A132: 071-010-092 | C132: Дюбель рамный М10 - 92 мм (компл. 100 шт.) РАСПРОДАЖА! | D132: 30 | E132: - | F132: 1 | G132: ='+'!AI132 -> 714.69 | I132: =H132*F132 -> 0 | J132: =G132*I132 -> 0 | L132: 4673768182378 | M132: 4673768182248
A133: 071-010-112 | C133: Дюбель рамный М10 - 112 мм (компл. 100 шт.) РАСПРОДАЖА! | D133: 35 | E133: - | F133: 1 | G133: ='+'!AI133 -> 815.41 | I133: =H133*F133 -> 0 | J133: =G133*I133 -> 0 | L133: 4673768182385 | M133: 4673768182255
...

Sheet +
O3: Корректировка 03 Сентябрь | AD3: FALSE | AE3: Включить стоимость доставки в цену
AD4: FALSE | AE4: Оплата за наличные
AD5: FALSE | AE5: Заграничный клиент, минус НДС
O6: КУБ УПЛОТН | P6: 5500
O7: ПО РФ | P7: 23 | AM7: 5
A8: Сентябрь 2026 | J8: =I195 -> 0 | T8: расчёт | AA8: Вес | AM8: %
A9: артикул | B9: изображение | C9: наименование | D9: вес (грамм) | E9: выход (литров) | F9: количество в коробке | G9: Цена в руб. (с НДС 20%): | H9: Ваш заказ (коробок) | I9: Ваш заказ (штук/комплектов) | J9: Сумма заказа в руб. (с НДС 20%) | L9: Штрихкод штуки | M9: Штрихкод коробки | O9: Скидка | P9: 0 | R9: min для ручного ввода | T9: коэфф max | U9: цена без скидки | V9: коэфф % | W9: без округления | X9: с округлением | AA9: Брутто коробки | AB9: Итого, кг. | AC9: Стоимость доставки | AD9: Вес штуки | AE9: округление до 3х знаков | AF9: Стоимость доставки за шт. руб. | AG9: округление до 2х знаков | AI9: Округление до 2х знаков | AK9: Если включить доставку в стоимость | AM9: Если оплата за наличку | AO9: Если заграничный клиент (-НДС) | AQ9: Рекомендованная цена Мин Кайрос
C10: Профессиональная монтажная пена KRONbuild (пистолетная) | O10: Проф.пена | Q10: =IF(P10>18,"ПЕРЕБОР","-") -> -
A11: FWPM80 | C11: Зима Masters 80 | D11: 1000 | E11: 80 | F11: 12 | G11: =AI11 -> 446.25 | I11: =H11*F11 -> 0 | J11: =G11*I11 -> 0 | L11: 4660447836226 | M11: 4673759127258 | P11: =$P$9 -> 0 | Q11: =IF(P11>18,"ПЕРЕБОР","-") -> - | R11: 357 | T11: 1.25 | U11: =R11*T11 -> 446.25 | V11: =P11*0.01 -> 0 | W11: =U11-(U11*V11) -> 446.25 | X11: =ROUND(W11,2) -> 446.25 | AA11: 12.3 | AB11: =H11*AA11 -> 0 | AC11: =AB11*$P$7 -> 0 | AD11: =AA11/F11 -> 1.025 | AE11: =ROUND(AD11,3) -> 1.025 | AF11: =AE11*$P$7 -> 23.575 | AG11: =ROUND(AF11,2) -> 23.58 | AI11: =ROUND(AO11,2) -> 446.25 | AK11: =IF($AD$3,AM11+AG11,AM11) -> 446.25 | AM11: =IF($AD$4,X11-($AM$7/100*X11),X11) -> 446.25 | AO11: =IF($AD$5,AK11-((AK11*1.18031)-AK11),AK11) -> 446.25
A12: FSPM80 | C12: Лето Masters 80 АКЦИЯ! | D12: 1000 | E12: 80 | F12: 12 | G12: =AI12 -> 383.75 | I12: =H12*F12 -> 0 | J12: =G12*I12 -> 0 | L12: 4660447836233 | M12: 4673759127272 | P12: =$P$9 -> 0 | Q12: =IF(P12>18,"ПЕРЕБОР","-") -> - | R12: 307 | T12: 1.25 | U12: =R12*T12 -> 383.75 | V12: =P12*0.01 -> 0 | W12: =U12-(U12*V12) -> 383.75 | X12: =ROUND(W12,2) -> 383.75 | AA12: 12.3 | AB12: =H12*AA12 -> 0 | AC12: =AB12*$P$7 -> 0 | AD12: =AA12/F12 -> 1.025 | AE12: =ROUND(AD12,3) -> 1.025 | AF12: =AE12*$P$7 -> 23.575 | AG12: =ROUND(AF12,2) -> 23.58 | AI12: =ROUND(AO12,2) -> 383.75 | AK12: =IF($AD$3,AM12+AG12,AM12) -> 383.75 | AM12: =IF($AD$4,X12-($AM$7/100*X12),X12) -> 383.75 | AO12: =IF($AD$5,AK12-((AK12*1.18031)-AK12),AK12) -> 383.75
A13: FSP70 | C13: Лето PRO 70 АКЦИЯ! | D13: 950 | E13: 70 | F13: 12 | G13: =AI13 -> 335 | I13: =H13*F13 -> 0 | J13: =G13*I13 -> 0 | L13: 4660447836295 | M13: 4627168565842 | P13: =$P$9 -> 0 | Q13: =IF(P13>18,"ПЕРЕБОР","-") -> - | R13: 268 | T13: 1.25 | U13: =R13*T13 -> 335 | V13: =P13*0.01 -> 0 | W13: =U13-(U13*V13) -> 335 | X13: =ROUND(W13,2) -> 335 | AA13: 11.8 | AB13: =H13*AA13 -> 0 | AC13: =AB13*$P$7 -> 0 | AD13: =AA13/F13 -> 0.98333333 | AE13: =ROUND(AD13,3) -> 0.983 | AF13: =AE13*$P$7 -> 22.609 | AG13: =ROUND(AF13,2) -> 22.61 | AI13: =ROUND(AO13,2) -> 335 | AK13: =IF($AD$3,AM13+AG13,AM13) -> 335 | AM13: =IF($AD$4,X13-($AM$7/100*X13),X13) -> 335 | AO13: =IF($AD$5,AK13-((AK13*1.18031)-AK13),AK13) -> 335
A14: FSU65 | C14: Лето Ultra 65 АКЦИЯ! | D14: 850 | E14: 65 | F14: 12 | G14: =AI14 -> 315 | I14: =H14*F14 -> 0 | J14: =G14*I14 -> 0 | L14: 4660447836301 | M14: 4627168562827 | P14: =$P$9 -> 0 | Q14: =IF(P14>18,"ПЕРЕБОР","-") -> - | R14: 252 | T14: 1.25 | U14: =R14*T14 -> 315 | V14: =P14*0.01 -> 0 | W14: =U14-(U14*V14) -> 315 | X14: =ROUND(W14,2) -> 315 | AA14: 10.6 | AB14: =H14*AA14 -> 0 | AC14: =AB14*$P$7 -> 0 | AD14: =AA14/F14 -> 0.88333333 | AE14: =ROUND(AD14,3) -> 0.883 | AF14: =AE14*$P$7 -> 20.309 | AG14: =ROUND(AF14,2) -> 20.31 | AI14: =ROUND(AO14,2) -> 315 | AK14: =IF($AD$3,AM14+AG14,AM14) -> 315 | AM14: =IF($AD$4,X14-($AM$7/100*X14),X14) -> 315 | AO14: =IF($AD$5,AK14-((AK14*1.18031)-AK14),AK14) -> 315
A15: FAS70 | C15: Всесезонная PRO 70 | D15: 950 | E15: 70 | F15: 12 | G15: =AI15 -> 396.25 | I15: =H15*F15 -> 0 | J15: =G15*I15 -> 0 | L15: 4660447836257 | M15: 4627198693171 | P15: =$P$9 -> 0 | Q15: =IF(P15>18,"ПЕРЕБОР","-") -> - | R15: 317 | T15: 1.25 | U15: =R15*T15 -> 396.25 | V15: =P15*0.01 -> 0 | W15: =U15-(U15*V15) -> 396.25 | X15: =ROUND(W15,2) -> 396.25 | AA15: 11.8 | AB15: =H15*AA15 -> 0 | AC15: =AB15*$P$7 -> 0 | AD15: =AA15/F15 -> 0.98333333 | AE15: =ROUND(AD15,3) -> 0.983 | AF15: =AE15*$P$7 -> 22.609 | AG15: =ROUND(AF15,2) -> 22.61 | AI15: =ROUND(AO15,2) -> 396.25 | AK15: =IF($AD$3,AM15+AG15,AM15) -> 396.25 | AM15: =IF($AD$4,X15-($AM$7/100*X15),X15) -> 396.25 | AO15: =IF($AD$5,AK15-((AK15*1.18031)-AK15),AK15) -> 396.25
A16: FAS65U | C16: Всесезонная Ultra 65 | D16: 850 | E16: 65 | F16: 12 | G16: =AI16 -> 353.75 | I16: =H16*F16 -> 0 | J16: =G16*I16 -> 0 | L16: 4660447836264 | M16: 4627168566122 | P16: =$P$9 -> 0 | R16: 283 | T16: 1.25 | U16: =R16*T16 -> 353.75 | V16: =P16*0.01 -> 0 | W16: =U16-(U16*V16) -> 353.75 | X16: =ROUND(W16,2) -> 353.75 | AA16: 10.6 | AB16: =H16*AA16 -> 0 | AC16: =AB16*$P$7 -> 0 | AD16: =AA16/F16 -> 0.88333333 | AE16: =ROUND(AD16,3) -> 0.883 | AF16: =AE16*$P$7 -> 20.309 | AG16: =ROUND(AF16,2) -> 20.31 | AI16: =ROUND(AO16,2) -> 353.75 | AK16: =IF($AD$3,AM16+AG16,AM16) -> 353.75 | AM16: =IF($AD$4,X16-($AM$7/100*X16),X16) -> 353.75 | AO16: =IF($AD$5,AK16-((AK16*1.18031)-AK16),AK16) -> 353.75
A17: FWP70 | C17: Зима PRO 70 | D17: 950 | E17: 70 | F17: 12 | G17: =AI17 -> 392.5 | I17: =H17*F17 -> 0 | J17: =G17*I17 -> 0 | L17: 4660447836271 | M17: 14627147350046 | P17: =$P$9 -> 0 | Q17: =IF(P17>18,"ПЕРЕБОР","-") -> - | R17: 314 | T17: 1.25 | U17: =R17*T17 -> 392.5 | V17: =P17*0.01 -> 0 | W17: =U17-(U17*V17) -> 392.5 | X17: =ROUND(W17,2) -> 392.5 | AA17: 11.8 | AB17: =H17*AA17 -> 0 | AC17: =AB17*$P$7 -> 0 | AD17: =AA17/F17 -> 0.98333333 | AE17: =ROUND(AD17,3) -> 0.983 | AF17: =AE17*$P$7 -> 22.609 | AG17: =ROUND(AF17,2) -> 22.61 | AI17: =ROUND(AO17,2) -> 392.5 | AK17: =IF($AD$3,AM17+AG17,AM17) -> 392.5 | AM17: =IF($AD$4,X17-($AM$7/100*X17),X17) -> 392.5 | AO17: =IF($AD$5,AK17-((AK17*1.18031)-AK17),AK17) -> 392.5
A18: FWU65 | C18: Зима Ultra 65 | D18: 850 | E18: 65 | F18: 12 | G18: =AI18 -> 375 | I18: =H18*F18 -> 0 | J18: =G18*I18 -> 0 | L18: 4660447836288 | M18: 4627168562803 | P18: =$P$9 -> 0 | Q18: =IF(P18>18,"ПЕРЕБОР","-") -> - | R18: 300 | T18: 1.25 | U18: =R18*T18 -> 375 | V18: =P18*0.01 -> 0 | W18: =U18-(U18*V18) -> 375 | X18: =ROUND(W18,2) -> 375 | AA18: 10.6 | AB18: =H18*AA18 -> 0 | AC18: =AB18*$P$7 -> 0 | AD18: =AA18/F18 -> 0.88333333 | AE18: =ROUND(AD18,3) -> 0.883 | AF18: =AE18*$P$7 -> 20.309 | AG18: =ROUND(AF18,2) -> 20.31 | AI18: =ROUND(AO18,2) -> 375 | AK18: =IF($AD$3,AM18+AG18,AM18) -> 375 | AM18: =IF($AD$4,X18-($AM$7/100*X18),X18) -> 375 | AO18: =IF($AD$5,AK18-((AK18*1.18031)-AK18),AK18) -> 375
C19: Профессиональная общестроительная монтажная пена KRONbuild (пистолетная) | O19: Общестроительная пена | Q19: =IF(P19>18,"ПЕРЕБОР","-") -> -
A20: FSS65 | C20: Лето Standart 65 АКЦИЯ! | D20: 800 | E20: 65 | F20: 12 | G20: =AI20 -> 292.5 | I20: =H20*F20 -> 0 | J20: =G20*I20 -> 0 | L20: 4660447836356 | M20: 4627168565866 | P20: =$P$9 -> 0 | Q20: =IF(P20>18,"ПЕРЕБОР","-") -> - | R20: 234 | T20: 1.25 | U20: =R20*T20 -> 292.5 | V20: =P20*0.01 -> 0 | W20: =U20-(U20*V20) -> 292.5 | X20: =ROUND(W20,2) -> 292.5 | AA20: 10 | AB20: =H20*AA20 -> 0 | AC20: =AB20*$P$7 -> 0 | AD20: =AA20/F20 -> 0.83333333 | AE20: =ROUND(AD20,3) -> 0.833 | AF20: =AE20*$P$7 -> 19.159 | AG20: =ROUND(AF20,2) -> 19.16 | AI20: =ROUND(AO20,2) -> 292.5 | AK20: =IF($AD$3,AM20+AG20,AM20) -> 292.5 | AM20: =IF($AD$4,X20-($AM$7/100*X20),X20) -> 292.5 | AO20: =IF($AD$5,AK20-((AK20*1.18031)-AK20),AK20) -> 292.5
A21: FASST | C21: Всесезонная Standart 65 | D21: 800 | E21: 65 | F21: 12 | G21: =AI21 -> 337.5 | I21: =H21*F21 -> 0 | J21: =G21*I21 -> 0 | L21: 4660447836332 | M21: 4673732414528 | P21: =$P$9 -> 0 | Q21: =IF(P21>18,"ПЕРЕБОР","-") -> - | R21: 270 | T21: 1.25 | U21: =R21*T21 -> 337.5 | V21: =P21*0.01 -> 0 | W21: =U21-(U21*V21) -> 337.5 | X21: =ROUND(W21,2) -> 337.5 | AA21: 10 | AB21: =H21*AA21 -> 0 | AC21: =AB21*$P$7 -> 0 | AD21: =AA21/F21 -> 0.83333333 | AE21: =ROUND(AD21,3) -> 0.833 | AF21: =AE21*$P$7 -> 19.159 | AG21: =ROUND(AF21,2) -> 19.16 | AI21: =ROUND(AO21,2) -> 337.5 | AK21: =IF($AD$3,AM21+AG21,AM21) -> 337.5 | AM21: =IF($AD$4,X21-($AM$7/100*X21),X21) -> 337.5 | AO21: =IF($AD$5,AK21-((AK21*1.18031)-AK21),AK21) -> 337.5
A22: FASGUN65 | C22: Всесезонная HANDGUN 65 | D22: 800 | E22: 65 | F22: 12 | G22: =AI22 -> 351.25 | I22: =H22*F22 -> 0 | J22: =G22*I22 -> 0 | L22: 4660447836240 | M22: 4673759127234 | P22: =$P$9 -> 0 | R22: 281 | T22: 1.25 | U22: =R22*T22 -> 351.25 | V22: =P22*0.01 -> 0 | W22: =U22-(U22*V22) -> 351.25 | X22: =ROUND(W22,2) -> 351.25 | AA22: 10 | AB22: =H22*AA22 -> 0 | AC22: =AB22*$P$7 -> 0 | AD22: =AA22/F22 -> 0.83333333 | AE22: =ROUND(AD22,3) -> 0.833 | AF22: =AE22*$P$7 -> 19.159 | AG22: =ROUND(AF22,2) -> 19.16 | AI22: =ROUND(AO22,2) -> 351.25 | AK22: =IF($AD$3,AM22+AG22,AM22) -> 351.25 | AM22: =IF($AD$4,X22-($AM$7/100*X22),X22) -> 351.25 | AO22: =IF($AD$5,AK22-((AK22*1.18031)-AK22),AK22) -> 351.25
A23: FAO65 | C23: Всесезонная ONE 65 | D23: 770 | E23: 65 | F23: 12 | G23: =AI23 -> 293.75 | I23: =H23*F23 -> 0 | J23: =G23*I23 -> 0 | L23: 4660447836325 | M23: 4627198692020 | P23: =$P$9 -> 0 | Q23: =IF(P23>18,"ПЕРЕБОР","-") -> - | R23: 235 | T23: 1.25 | U23: =R23*T23 -> 293.75 | V23: =P23*0.01 -> 0 | W23: =U23-(U23*V23) -> 293.75 | X23: =ROUND(W23,2) -> 293.75 | AA23: 9.64 | AB23: =H23*AA23 -> 0 | AC23: =AB23*$P$7 -> 0 | AD23: =AA23/F23 -> 0.80333333 | AE23: =ROUND(AD23,3) -> 0.803 | AF23: =AE23*$P$7 -> 18.469 | AG23: =ROUND(AF23,2) -> 18.47 | AI23: =ROUND(AO23,2) -> 293.75 | AK23: =IF($AD$3,AM23+AG23,AM23) -> 293.75 | AM23: =IF($AD$4,X23-($AM$7/100*X23),X23) -> 293.75 | AO23: =IF($AD$5,AK23-((AK23*1.18031)-AK23),AK23) -> 293.75
A24: FAS650 | C24: Всесезонная 65 | D24: 650 | E24: 65 | F24: 12 | G24: =AI24 -> 270 | I24: =H24*F24 -> 0 | J24: =G24*I24 -> 0 | L24: 4660447836318 | M24: 4627198691986 | P24: =$P$9 -> 0 | R24: 216 | T24: 1.25 | U24: =R24*T24 -> 270 | V24: =P24*0.01 -> 0 | W24: =U24-(U24*V24) -> 270 | X24: =ROUND(W24,2) -> 270 | AA24: 8.2 | AB24: =H24*AA24 -> 0 | AC24: =AB24*$P$7 -> 0 | AD24: =AA24/F24 -> 0.68333333 | AE24: =ROUND(AD24,3) -> 0.683 | AF24: =AE24*$P$7 -> 15.709 | AG24: =ROUND(AF24,2) -> 15.71 | AI24: =ROUND(AO24,2) -> 270 | AK24: =IF($AD$3,AM24+AG24,AM24) -> 270 | AM24: =IF($AD$4,X24-($AM$7/100*X24),X24) -> 270 | AO24: =IF($AD$5,AK24-((AK24*1.18031)-AK24),AK24) -> 270
A25: FWS65 | C25: Зима Standart 65 | D25: 800 | E25: 65 | F25: 12 | G25: =AI25 -> 352.5 | I25: =H25*F25 -> 0 | J25: =G25*I25 -> 0 | L25: 4660447836349 | M25: 14627147350039 | P25: =$P$9 -> 0 | Q25: =IF(P25>18,"ПЕРЕБОР","-") -> - | R25: 282 | T25: 1.25 | U25: =R25*T25 -> 352.5 | V25: =P25*0.01 -> 0 | W25: =U25-(U25*V25) -> 352.5 | X25: =ROUND(W25,2) -> 352.5 | AA25: 10 | AB25: =H25*AA25 -> 0 | AC25: =AB25*$P$7 -> 0 | AD25: =AA25/F25 -> 0.83333333 | AE25: =ROUND(AD25,3) -> 0.833 | AF25: =AE25*$P$7 -> 19.159 | AG25: =ROUND(AF25,2) -> 19.16 | AI25: =ROUND(AO25,2) -> 352.5 | AK25: =IF($AD$3,AM25+AG25,AM25) -> 352.5 | AM25: =IF($AD$4,X25-($AM$7/100*X25),X25) -> 352.5 | AO25: =IF($AD$5,AK25-((AK25*1.18031)-AK25),AK25) -> 352.5
C26: Профессиональная специальная монтажная пена KRONbuild (пистолетная) | O26: Специальная пена | Q26: =IF(P26>18,"ПЕРЕБОР","-") -> -
A27: FPFB1 | C27: Огнестойкая B1 | D27: 850 | E27: 65 | F27: 12 | G27: =AI27 -> 475 | I27: =H27*F27 -> 0 | J27: =G27*I27 -> 0 | L27: 4660447836387 | M27: 4673732414252 | P27: =$P$9 -> 0 | Q27: =IF(P27>18,"ПЕРЕБОР","-") -> - | R27: 380 | T27: 1.25 | U27: =R27*T27 -> 475 | V27: =P27*0.01 -> 0 | W27: =U27-(U27*V27) -> 475 | X27: =ROUND(W27,2) -> 475 | AA27: 10.6 | AB27: =H27*AA27 -> 0 | AC27: =AB27*$P$7 -> 0 | AD27: =AA27/F27 -> 0.88333333 | AE27: =ROUND(AD27,3) -> 0.883 | AF27: =AE27*$P$7 -> 20.309 | AG27: =ROUND(AF27,2) -> 20.31 | AI27: =ROUND(AO27,2) -> 475 | AK27: =IF($AD$3,AM27+AG27,AM27) -> 475 | AM27: =IF($AD$4,X27-($AM$7/100*X27),X27) -> 475 | AO27: =IF($AD$5,AK27-((AK27*1.18031)-AK27),AK27) -> 475
A28: FC850 | C28: Цемент-пена | D28: 900 | E28: - | F28: 12 | G28: =AI28 -> 515 | I28: =H28*F28 -> 0 | J28: =G28*I28 -> 0 | L28: 4660447836394 | M28: 4673743522878 | P28: =$P$9 -> 0 | Q28: =IF(P28>18,"ПЕРЕБОР","-") -> - | R28: 412 | T28: 1.25 | U28: =R28*T28 -> 515 | V28: =P28*0.01 -> 0 | W28: =U28-(U28*V28) -> 515 | X28: =ROUND(W28,2) -> 515 | AA28: 11.2 | AB28: =H28*AA28 -> 0 | AC28: =AB28*$P$7 -> 0 | AD28: =AA28/F28 -> 0.93333333 | AE28: =ROUND(AD28,3) -> 0.933 | AF28: =AE28*$P$7 -> 21.459 | AG28: =ROUND(AF28,2) -> 21.46 | AI28: =ROUND(AO28,2) -> 515 | AK28: =IF($AD$3,AM28+AG28,AM28) -> 515 | AM28: =IF($AD$4,X28-($AM$7/100*X28),X28) -> 515 | AO28: =IF($AD$5,AK28-((AK28*1.18031)-AK28),AK28) -> 515
A29: PUI90 | C29: Напыляемый утеплитель + насадка-распылитель | D29: 900 | E29: - | F29: 12 | G29: =AI29 -> 555 | I29: =H29*F29 -> 0 | J29: =G29*I29 -> 0 | L29: 4660447836370 | M29: 4673732414917 | P29: =$P$9 -> 0 | Q29: =IF(P29>18,"ПЕРЕБОР","-") -> - | R29: 444 | T29: 1.25 | U29: =R29*T29 -> 555 | V29: =P29*0.01 -> 0 | W29: =U29-(U29*V29) -> 555 | X29: =ROUND(W29,2) -> 555 | AA29: 11.2 | AB29: =H29*AA29 -> 0 | AC29: =AB29*$P$7 -> 0 | AD29: =AA29/F29 -> 0.93333333 | AE29: =ROUND(AD29,3) -> 0.933 | AF29: =AE29*$P$7 -> 21.459 | AG29: =ROUND(AF29,2) -> 21.46 | AI29: =ROUND(AO29,2) -> 555 | AK29: =IF($AD$3,AM29+AG29,AM29) -> 555 | AM29: =IF($AD$4,X29-($AM$7/100*X29),X29) -> 555 | AO29: =IF($AD$5,AK29-((AK29*1.18031)-AK29),AK29) -> 555
A30: GF800 | C30: Клей-пена | D30: 800 | E30: 65 | F30: 12 | G30: =AI30 -> 398.75 | I30: =H30*F30 -> 0 | J30: =G30*I30 -> 0 | L30: 4660447836363 | M30: 4627198692006 | P30: =$P$9 -> 0 | Q30: =IF(P30>18,"ПЕРЕБОР","-") -> - | R30: 319 | T30: 1.25 | U30: =R30*T30 -> 398.75 | V30: =P30*0.01 -> 0 | W30: =U30-(U30*V30) -> 398.75 | X30: =ROUND(W30,2) -> 398.75 | AA30: 10 | AB30: =H30*AA30 -> 0 | AC30: =AB30*$P$7 -> 0 | AD30: =AA30/F30 -> 0.83333333 | AE30: =ROUND(AD30,3) -> 0.833 | AF30: =AE30*$P$7 -> 19.159 | AG30: =ROUND(AF30,2) -> 19.16 | AI30: =ROUND(AO30,2) -> 398.75 | AK30: =IF($AD$3,AM30+AG30,AM30) -> 398.75 | AM30: =IF($AD$4,X30-($AM$7/100*X30),X30) -> 398.75 | AO30: =IF($AD$5,AK30-((AK30*1.18031)-AK30),AK30) -> 398.75
C31: Бытовая монтажная пена KRONbuild | O31: Бытовая пена | Q31: =IF(P31>18,"ПЕРЕБОР","-") -> -
A32: FH200 | C32: Всесезонная 20+ | D32: 380 | E32: 20+ | F32: 12 | G32: =AI32 -> 176.25 | I32: =H32*F32 -> 0 | J32: =G32*I32 -> 0 | L32: 4660447836189 | M32: 14627155466425 | P32: =$P$9 -> 0 | Q32: =IF(P32>18,"ПЕРЕБОР","-") -> - | R32: 141 | T32: 1.25 | U32: =R32*T32 -> 176.25 | V32: =P32*0.01 -> 0 | W32: =U32-(U32*V32) -> 176.25 | X32: =ROUND(W32,2) -> 176.25 | AA32: 5.2 | AB32: =H32*AA32 -> 0 | AC32: =AB32*$P$7 -> 0 | AD32: =AA32/F32 -> 0.43333333 | AE32: =ROUND(AD32,3) -> 0.433 | AF32: =AE32*$P$7 -> 9.959 | AG32: =ROUND(AF32,2) -> 9.96 | AI32: =ROUND(AO32,2) -> 176.25 | AK32: =IF($AD$3,AM32+AG32,AM32) -> 176.25 | AM32: =IF($AD$4,X32-($AM$7/100*X32),X32) -> 176.25 | AO32: =IF($AD$5,AK32-((AK32*1.18031)-AK32),AK32) -> 176.25
A33: FH400 | C33: Всесезонная 40+ | D33: 500 | E33: 40+ | F33: 12 | G33: =AI33 -> 220 | I33: =H33*F33 -> 0 | J33: =G33*I33 -> 0 | L33: 4660447836196 | M33: 4627168566771 | P33: =$P$9 -> 0 | Q33: =IF(P33>18,"ПЕРЕБОР","-") -> - | R33: 176 | T33: 1.25 | U33: =R33*T33 -> 220 | V33: =P33*0.01 -> 0 | W33: =U33-(U33*V33) -> 220 | X33: =ROUND(W33,2) -> 220 | AA33: 7.6 | AB33: =H33*AA33 -> 0 | AC33: =AB33*$P$7 -> 0 | AD33: =AA33/F33 -> 0.63333333 | AE33: =ROUND(AD33,3) -> 0.633 | AF33: =AE33*$P$7 -> 14.559 | AG33: =ROUND(AF33,2) -> 14.56 | AI33: =ROUND(AO33,2) -> 220 | AK33: =IF($AD$3,AM33+AG33,AM33) -> 220 | AM33: =IF($AD$4,X33-($AM$7/100*X33),X33) -> 220 | AO33: =IF($AD$5,AK33-((AK33*1.18031)-AK33),AK33) -> 220
A34: FHO65 | C34: Всесезонная ONE 65 | D34: 770 | E34: 65 | F34: 12 | G34: =AI34 -> 293.75 | I34: =H34*F34 -> 0 | J34: =G34*I34 -> 0 | L34: 4660447836202 | M34: 4627181320091 | P34: =$P$9 -> 0 | Q34: =IF(P34>18,"ПЕРЕБОР","-") -> - | R34: 235 | T34: 1.25 | U34: =R34*T34 -> 293.75 | V34: =P34*0.01 -> 0 | W34: =U34-(U34*V34) -> 293.75 | X34: =ROUND(W34,2) -> 293.75 | AA34: 9.64 | AB34: =H34*AA34 -> 0 | AC34: =AB34*$P$7 -> 0 | AD34: =AA34/F34 -> 0.80333333 | AE34: =ROUND(AD34,3) -> 0.803 | AF34: =AE34*$P$7 -> 18.469 | AG34: =ROUND(AF34,2) -> 18.47 | AI34: =ROUND(AO34,2) -> 293.75 | AK34: =IF($AD$3,AM34+AG34,AM34) -> 293.75 | AM34: =IF($AD$4,X34-($AM$7/100*X34),X34) -> 293.75 | AO34: =IF($AD$5,AK34-((AK34*1.18031)-AK34),AK34) -> 293.75
C35: Очиститель монтажной пены KRONbuild | O35: Очиститель м. пены | Q35: =IF(P35>18,"ПЕРЕБОР","-") -> - | AO35: =IF($AD$5,AK35-((AK35*1.18031)-AK35),AK35) -> 0
A36: CF351 | C36: Очиститель монтажной пены | D36: 350 | E36: - | F36: 12 | G36: =AI36 -> 140 | I36: =H36*F36 -> 0 | J36: =G36*I36 -> 0 | L36: 4627147350025 | M36: 14627147350022 | P36: =$P$9 -> 0 | Q36: =IF(P36>18,"ПЕРЕБОР","-") -> - | R36: 112 | T36: 1.25 | U36: =R36*T36 -> 140 | V36: =P36*0.01 -> 0 | W36: =U36-(U36*V36) -> 140 | X36: =ROUND(W36,2) -> 140 | AA36: 4.55 | AB36: =H36*AA36 -> 0 | AC36: =AB36*$P$7 -> 0 | AD36: =AA36/F36 -> 0.37916667 | AE36: =ROUND(AD36,3) -> 0.379 | AF36: =AE36*$P$7 -> 8.717 | AG36: =ROUND(AF36,2) -> 8.72 | AI36: =ROUND(AO36,2) -> 140 | AK36: =IF($AD$3,AM36+AG36,AM36) -> 140 | AM36: =IF($AD$4,X36-($AM$7/100*X36),X36) -> 140 | AO36: =IF($AD$5,AK36-((AK36*1.18031)-AK36),AK36) -> 140
C37: Герметики KRONbuild | O37: Герметики | Q37: =IF(P37>18,"ПЕРЕБОР","-") -> -
A38: SUT80 | C38: Герметик универсальный (бесцветный) 80 мл | D38: 80 | E38: - | F38: 12 | G38: =AI38 -> 120 | I38: =H38*F38 -> 0 | J38: =G38*I38 -> 0 | L38: 4660447835984 | M38: 4673743524407 | P38: =$P$9 -> 0 | Q38: =IF(P38>18,"ПЕРЕБОР","-") -> - | R38: 96 | T38: 1.25 | U38: =R38*T38 -> 120 | V38: =P38*0.01 -> 0 | W38: =U38-(U38*V38) -> 120 | X38: =ROUND(W38,2) -> 120 | AA38: 0.96 | AB38: =H38*AA38 -> 0 | AC38: =AB38*$P$7 -> 0 | AD38: =AA38/F38 -> 0.08 | AE38: =ROUND(AD38,3) -> 0.08 | AF38: =AE38*$P$7 -> 1.84 | AG38: =ROUND(AF38,2) -> 1.84 | AI38: =ROUND(AO38,2) -> 120 | AK38: =IF($AD$3,AM38+AG38,AM38) -> 120 | AM38: =IF($AD$4,X38-($AM$7/100*X38),X38) -> 120 | AO38: =IF($AD$5,AK38-((AK38*1.18031)-AK38),AK38) -> 120
A39: SUW80 | C39: Герметик универсальный (белый) 80 мл | D39: 80 | E39: - | F39: 12 | G39: =AI39 -> 120 | I39: =H39*F39 -> 0 | J39: =G39*I39 -> 0 | L39: 4660447835960 | M39: 4673743524414 | P39: =$P$9 -> 0 | Q39: =IF(P39>18,"ПЕРЕБОР","-") -> - | R39: 96 | T39: 1.25 | U39: =R39*T39 -> 120 | V39: =P39*0.01 -> 0 | W39: =U39-(U39*V39) -> 120 | X39: =ROUND(W39,2) -> 120 | AA39: 0.96 | AB39: =H39*AA39 -> 0 | AC39: =AB39*$P$7 -> 0 | AD39: =AA39/F39 -> 0.08 | AE39: =ROUND(AD39,3) -> 0.08 | AF39: =AE39*$P$7 -> 1.84 | AG39: =ROUND(AF39,2) -> 1.84 | AI39: =ROUND(AO39,2) -> 120 | AK39: =IF($AD$3,AM39+AG39,AM39) -> 120 | AM39: =IF($AD$4,X39-($AM$7/100*X39),X39) -> 120 | AO39: =IF($AD$5,AK39-((AK39*1.18031)-AK39),AK39) -> 120
A40: SST80 | C40: Герметик санитарный (бесцветный) 80 мл | D40: 80 | E40: - | F40: 12 | G40: =AI40 -> 122.5 | I40: =H40*F40 -> 0 | J40: =G40*I40 -> 0 | L40: 4660447835946 | M40: 4673743524421 | P40: =$P$9 -> 0 | Q40: =IF(P40>18,"ПЕРЕБОР","-") -> - | R40: 98 | T40: 1.25 | U40: =R40*T40 -> 122.5 | V40: =P40*0.01 -> 0 | W40: =U40-(U40*V40) -> 122.5 | X40: =ROUND(W40,2) -> 122.5 | AA40: 0.96 | AB40: =H40*AA40 -> 0 | AC40: =AB40*$P$7 -> 0 | AD40: =AA40/F40 -> 0.08 | AE40: =ROUND(AD40,3) -> 0.08 | AF40: =AE40*$P$7 -> 1.84 | AG40: =ROUND(AF40,2) -> 1.84 | AI40: =ROUND(AO40,2) -> 122.5 | AK40: =IF($AD$3,AM40+AG40,AM40) -> 122.5 | AM40: =IF($AD$4,X40-($AM$7/100*X40),X40) -> 122.5 | AO40: =IF($AD$5,AK40-((AK40*1.18031)-AK40),AK40) -> 122.5
A41: SSW80 | C41: Герметик санитарный (белый) 80 мл | D41: 80 | E41: - | F41: 12 | G41: =AI41 -> 122.5 | I41: =H41*F41 -> 0 | J41: =G41*I41 -> 0 | L41: 4660447835922 | M41: 4673743524438 | P41: =$P$9 -> 0 | Q41: =IF(P41>18,"ПЕРЕБОР","-") -> - | R41: 98 | T41: 1.25 | U41: =R41*T41 -> 122.5 | V41: =P41*0.01 -> 0 | W41: =U41-(U41*V41) -> 122.5 | X41: =ROUND(W41,2) -> 122.5 | AA41: 0.96 | AB41: =H41*AA41 -> 0 | AC41: =AB41*$P$7 -> 0 | AD41: =AA41/F41 -> 0.08 | AE41: =ROUND(AD41,3) -> 0.08 | AF41: =AE41*$P$7 -> 1.84 | AG41: =ROUND(AF41,2) -> 1.84 | AI41: =ROUND(AO41,2) -> 122.5 | AK41: =IF($AD$3,AM41+AG41,AM41) -> 122.5 | AM41: =IF($AD$4,X41-($AM$7/100*X41),X41) -> 122.5 | AO41: =IF($AD$5,AK41-((AK41*1.18031)-AK41),AK41) -> 122.5
A42: SNT60 | C42: Герметик силиконовый нейтральный (бесцветный) 600 мл. | D42: 550 | E42: - | F42: 20 | G42: =AI42 -> 298.75 | I42: =H42*F42 -> 0 | J42: =G42*I42 -> 0 | L42: 4660447835908 | M42: 4673743522335 | P42: =$P$9 -> 0 | Q42: =IF(P42>18,"ПЕРЕБОР","-") -> - | R42: 239 | T42: 1.25 | U42: =R42*T42 -> 298.75 | V42: =P42*0.01 -> 0 | W42: =U42-(U42*V42) -> 298.75 | X42: =ROUND(W42,2) -> 298.75 | AA42: 11.4 | AB42: =H42*AA42 -> 0 | AC42: =AB42*$P$7 -> 0 | AD42: =AA42/F42 -> 0.57 | AE42: =ROUND(AD42,3) -> 0.57 | AF42: =AE42*$P$7 -> 13.11 | AG42: =ROUND(AF42,2) -> 13.11 | AI42: =ROUND(AO42,2) -> 298.75 | AK42: =IF($AD$3,AM42+AG42,AM42) -> 298.75 | AM42: =IF($AD$4,X42-($AM$7/100*X42),X42) -> 298.75 | AO42: =IF($AD$5,AK42-((AK42*1.18031)-AK42),AK42) -> 298.75
A43: SNW28 | C43: Герметик нейтральный (белый) 280 мл. | D43: 430 | E43: - | F43: 24 | G43: =AI43 -> 147.5 | I43: =H43*F43 -> 0 | J43: =G43*I43 -> 0 | L43: 4660447835885 | M43: 14627147356161 | P43: =$P$9 -> 0 | Q43: =IF(P43>18,"ПЕРЕБОР","-") -> - | R43: 118 | T43: 1.25 | U43: =R43*T43 -> 147.5 | V43: =P43*0.01 -> 0 | W43: =U43-(U43*V43) -> 147.5 | X43: =ROUND(W43,2) -> 147.5 | AA43: 10.72 | AB43: =H43*AA43 -> 0 | AC43: =AB43*$P$7 -> 0 | AD43: =AA43/F43 -> 0.44666667 | AE43: =ROUND(AD43,3) -> 0.447 | AF43: =AE43*$P$7 -> 10.281 | AG43: =ROUND(AF43,2) -> 10.28 | AI43: =ROUND(AO43,2) -> 147.5 | AK43: =IF($AD$3,AM43+AG43,AM43) -> 147.5 | AM43: =IF($AD$4,X43-($AM$7/100*X43),X43) -> 147.5 | AO43: =IF($AD$5,AK43-((AK43*1.18031)-AK43),AK43) -> 147.5
A44: SNT28 | C44: Герметик нейтральный (бесцветный) 280 мл. | D44: 300 | E44: - | F44: 24 | G44: =AI44 -> 150 | I44: =H44*F44 -> 0 | J44: =G44*I44 -> 0 | L44: 4660447835892 | M44: 4627168563428 | P44: =$P$9 -> 0 | Q44: =IF(P44>18,"ПЕРЕБОР","-") -> - | R44: 120 | T44: 1.25 | U44: =R44*T44 -> 150 | V44: =P44*0.01 -> 0 | W44: =U44-(U44*V44) -> 150 | X44: =ROUND(W44,2) -> 150 | AA44: 7.6 | AB44: =H44*AA44 -> 0 | AC44: =AB44*$P$7 -> 0 | AD44: =AA44/F44 -> 0.31666667 | AE44: =ROUND(AD44,3) -> 0.317 | AF44: =AE44*$P$7 -> 7.291 | AG44: =ROUND(AF44,2) -> 7.29 | AI44: =ROUND(AO44,2) -> 150 | AK44: =IF($AD$3,AM44+AG44,AM44) -> 150 | AM44: =IF($AD$4,X44-($AM$7/100*X44),X44) -> 150 | AO44: =IF($AD$5,AK44-((AK44*1.18031)-AK44),AK44) -> 150
A45: SSW28 | C45: Герметик санитарный (белый) 280 мл. | D45: 300 | E45: - | F45: 24 | G45: =AI45 -> 131.25 | I45: =H45*F45 -> 0 | J45: =G45*I45 -> 0 | L45: 4660447835915 | M45: 14627155469785 | P45: =$P$9 -> 0 | Q45: =IF(P45>18,"ПЕРЕБОР","-") -> - | R45: 105 | T45: 1.25 | U45: =R45*T45 -> 131.25 | V45: =P45*0.01 -> 0 | W45: =U45-(U45*V45) -> 131.25 | X45: =ROUND(W45,2) -> 131.25 | AA45: 7.6 | AB45: =H45*AA45 -> 0 | AC45: =AB45*$P$7 -> 0 | AD45: =AA45/F45 -> 0.31666667 | AE45: =ROUND(AD45,3) -> 0.317 | AF45: =AE45*$P$7 -> 7.291 | AG45: =ROUND(AF45,2) -> 7.29 | AI45: =ROUND(AO45,2) -> 131.25 | AK45: =IF($AD$3,AM45+AG45,AM45) -> 131.25 | AM45: =IF($AD$4,X45-($AM$7/100*X45),X45) -> 131.25 | AO45: =IF($AD$5,AK45-((AK45*1.18031)-AK45),AK45) -> 131.25
A46: SST28 | C46: Герметик санитарный (бесцветный) 280 мл. | D46: 300 | E46: - | F46: 24 | G46: =AI46 -> 131.25 | I46: =H46*F46 -> 0 | J46: =G46*I46 -> 0 | L46: 4660447835939 | M46: 4627168563442 | P46: =$P$9 -> 0 | Q46: =IF(P46>18,"ПЕРЕБОР","-") -> - | R46: 105 | T46: 1.25 | U46: =R46*T46 -> 131.25 | V46: =P46*0.01 -> 0 | W46: =U46-(U46*V46) -> 131.25 | X46: =ROUND(W46,2) -> 131.25 | AA46: 7.6 | AB46: =H46*AA46 -> 0 | AC46: =AB46*$P$7 -> 0 | AD46: =AA46/F46 -> 0.31666667 | AE46: =ROUND(AD46,3) -> 0.317 | AF46: =AE46*$P$7 -> 7.291 | AG46: =ROUND(AF46,2) -> 7.29 | AI46: =ROUND(AO46,2) -> 131.25 | AK46: =IF($AD$3,AM46+AG46,AM46) -> 131.25 | AM46: =IF($AD$4,X46-($AM$7/100*X46),X46) -> 131.25 | AO46: =IF($AD$5,AK46-((AK46*1.18031)-AK46),AK46) -> 131.25
A47: SUW28 | C47: Герметик универсальный (белый) 280 мл. | D47: 300 | E47: - | F47: 24 | G47: =AI47 -> 128.75 | I47: =H47*F47 -> 0 | J47: =G47*I47 -> 0 | L47: 4660447835953 | M47: 14627147354778 | P47: =$P$9 -> 0 | Q47: =IF(P47>18,"ПЕРЕБОР","-") -> - | R47: 103 | T47: 1.25 | U47: =R47*T47 -> 128.75 | V47: =P47*0.01 -> 0 | W47: =U47-(U47*V47) -> 128.75 | X47: =ROUND(W47,2) -> 128.75 | AA47: 7.6 | AB47: =H47*AA47 -> 0 | AC47: =AB47*$P$7 -> 0 | AD47: =AA47/F47 -> 0.31666667 | AE47: =ROUND(AD47,3) -> 0.317 | AF47: =AE47*$P$7 -> 7.291 | AG47: =ROUND(AF47,2) -> 7.29 | AI47: =ROUND(AO47,2) -> 128.75 | AK47: =IF($AD$3,AM47+AG47,AM47) -> 128.75 | AM47: =IF($AD$4,X47-($AM$7/100*X47),X47) -> 128.75 | AO47: =IF($AD$5,AK47-((AK47*1.18031)-AK47),AK47) -> 128.75
A48: SUT28 | C48: Герметик универсальный (бесцветный) 280 мл. | D48: 300 | E48: - | F48: 24 | G48: =AI48 -> 128.75 | I48: =H48*F48 -> 0 | J48: =G48*I48 -> 0 | L48: 4660447835977 | M48: 4627168563466 | P48: =$P$9 -> 0 | Q48: =IF(P48>18,"ПЕРЕБОР","-") -> - | R48: 103 | T48: 1.25 | U48: =R48*T48 -> 128.75 | V48: =P48*0.01 -> 0 | W48: =U48-(U48*V48) -> 128.75 | X48: =ROUND(W48,2) -> 128.75 | AA48: 7.6 | AB48: =H48*AA48 -> 0 | AC48: =AB48*$P$7 -> 0 | AD48: =AA48/F48 -> 0.31666667 | AE48: =ROUND(AD48,3) -> 0.317 | AF48: =AE48*$P$7 -> 7.291 | AG48: =ROUND(AF48,2) -> 7.29 | AI48: =ROUND(AO48,2) -> 128.75 | AK48: =IF($AD$3,AM48+AG48,AM48) -> 128.75 | AM48: =IF($AD$4,X48-($AM$7/100*X48),X48) -> 128.75 | AO48: =IF($AD$5,AK48-((AK48*1.18031)-AK48),AK48) -> 128.75
A49: SUB28 | C49: Герметик универсальный (чёрный) 280 мл. | D49: 300 | E49: - | F49: 24 | G49: =AI49 -> 128.75 | I49: =H49*F49 -> 0 | J49: =G49*I49 -> 0 | L49: 4660447835991 | M49: 4673743520423 | P49: =$P$9 -> 0 | Q49: =IF(P49>18,"ПЕРЕБОР","-") -> - | R49: 103 | T49: 1.25 | U49: =R49*T49 -> 128.75 | V49: =P49*0.01 -> 0 | W49: =U49-(U49*V49) -> 128.75 | X49: =ROUND(W49,2) -> 128.75 | AA49: 7.6 | AB49: =H49*AA49 -> 0 | AC49: =AB49*$P$7 -> 0 | AD49: =AA49/F49 -> 0.31666667 | AE49: =ROUND(AD49,3) -> 0.317 | AF49: =AE49*$P$7 -> 7.291 | AG49: =ROUND(AF49,2) -> 7.29 | AI49: =ROUND(AO49,2) -> 128.75 | AK49: =IF($AD$3,AM49+AG49,AM49) -> 128.75 | AM49: =IF($AD$4,X49-($AM$7/100*X49),X49) -> 128.75 | AO49: =IF($AD$5,AK49-((AK49*1.18031)-AK49),AK49) -> 128.75
... A51: ASA28 | C51: Герметик акриловый (белый) 280 мл. | D51: 420 | E51: - | F51: 24 | G51: =AI51 -> 136.25 | I51: =H51*F51 -> 0 | J51: =G51*I51 -> 0 | L51: 4660447835861 | M51: 14627155469792 | P51: =$P$9 -> 0 | Q51: =IF(P51>18,"ПЕРЕБОР","-") -> - | R51: 109 | T51: 1.25 | U51: =R51*T51 -> 136.25 | V51: =P51*0.01 -> 0 | W51: =U51-(U51*V51) -> 136.25 | X51: =ROUND(W51,2) -> 136.25 | AA51: 11.92 | AB51: =H51*AA51 -> 0 | AC51: =AB51*$P$7 -> 0 | AD51: =AA51/F51 -> 0.49666667 | AE51: =ROUND(AD51,3) -> 0.497 | AF51: =AE51*$P$7 -> 11.431 | AG51: =ROUND(AF51,2) -> 11.43 | AI51: =ROUND(AO51,2) -> 136.25 | AK51: =IF($AD$3,AM51+AG51,AM51) -> 136.25 | AM51: =IF($AD$4,X51-($AM$7/100*X51),X51) -> 136.25 | AO51: =IF($AD$5,AK51-((AK51*1.18031)-AK51),AK51) -> 136.25
C52: Специализированные герметики KRONbuild | O52: Специализированные герметики | Q52: =IF(P52>18,"ПЕРЕБОР","-") -> -
A53: PSG78 | C53: Герметик полиуретановый PU-40 (серый) 600 мл. | D53: 870 | E53: - | F53: 20 | G53: =AI53 -> 315 | I53: =H53*F53 -> 0 | J53: =G53*I53 -> 0 | L53: 4660447836110 | M53: 14627181321927 | P53: =$P$9 -> 0 | Q53: =IF(P53>18,"ПЕРЕБОР","-") -> - | R53: 252 | T53: 1.25 | U53: =R53*T53 -> 315 | V53: =P53*0.01 -> 0 | W53: =U53-(U53*V53) -> 315 | X53: =ROUND(W53,2) -> 315 | AA53: 17.8 | AB53: =H53*AA53 -> 0 | AC53: =AB53*$P$7 -> 0 | AD53: =AA53/F53 -> 0.89 | AE53: =ROUND(AD53,3) -> 0.89 | AF53: =AE53*$P$7 -> 20.47 | AG53: =ROUND(AF53,2) -> 20.47 | AI53: =ROUND(AO53,2) -> 315 | AK53: =IF($AD$3,AM53+AG53,AM53) -> 315 | AM53: =IF($AD$4,X53-($AM$7/100*X53),X53) -> 315 | AO53: =IF($AD$5,AK53-((AK53*1.18031)-AK53),AK53) -> 315
A54: PSB78 | C54: Герметик полиуретановый PU-40 (черный) 600 мл. | D54: 870 | E54: - | F54: 20 | G54: =AI54 -> 315 | I54: =H54*F54 -> 0 | J54: =G54*I54 -> 0 | L54: 4660447836127 | M54: 14627181322351 | P54: =$P$9 -> 0 | Q54: =IF(P54>18,"ПЕРЕБОР","-") -> - | R54: 252 | T54: 1.25 | U54: =R54*T54 -> 315 | V54: =P54*0.01 -> 0 | W54: =U54-(U54*V54) -> 315 | X54: =ROUND(W54,2) -> 315 | AA54: 17.8 | AB54: =H54*AA54 -> 0 | AC54: =AB54*$P$7 -> 0 | AD54: =AA54/F54 -> 0.89 | AE54: =ROUND(AD54,3) -> 0.89 | AF54: =AE54*$P$7 -> 20.47 | AG54: =ROUND(AF54,2) -> 20.47 | AI54: =ROUND(AO54,2) -> 315 | AK54: =IF($AD$3,AM54+AG54,AM54) -> 315 | AM54: =IF($AD$4,X54-($AM$7/100*X54),X54) -> 315 | AO54: =IF($AD$5,AK54-((AK54*1.18031)-AK54),AK54) -> 315
A55: PSW78 | C55: Герметик полиуретановый PU-40 (белый) 600 мл. | D55: 870 | E55: - | F55: 20 | G55: =AI55 -> 315 | I55: =H55*F55 -> 0 | J55: =G55*I55 -> 0 | L55: 4660447836103 | M55: 14627181322375 | P55: =$P$9 -> 0 | Q55: =IF(P55>18,"ПЕРЕБОР","-") -> - | R55: 252 | T55: 1.25 | U55: =R55*T55 -> 315 | V55: =P55*0.01 -> 0 | W55: =U55-(U55*V55) -> 315 | X55: =ROUND(W55,2) -> 315 | AA55: 17.8 | AB55: =H55*AA55 -> 0 | AC55: =AB55*$P$7 -> 0 | AD55: =AA55/F55 -> 0.89 | AE55: =ROUND(AD55,3) -> 0.89 | AF55: =AE55*$P$7 -> 20.47 | AG55: =ROUND(AF55,2) -> 20.47 | AI55: =ROUND(AO55,2) -> 315 | AK55: =IF($AD$3,AM55+AG55,AM55) -> 315 | AM55: =IF($AD$4,X55-($AM$7/100*X55),X55) -> 315 | AO55: =IF($AD$5,AK55-((AK55*1.18031)-AK55),AK55) -> 315
A56: WS650 | C56: Герметик атмосферостойкий силиконовый (черный) | D56: 870 | E56: - | F56: 20 | G56: =AI56 -> 341.25 | I56: =H56*F56 -> 0 | J56: =G56*I56 -> 0 | L56: 4660447836011 | M56: 4673732414207 | P56: =$P$9 -> 0 | Q56: =IF(P56>18,"ПЕРЕБОР","-") -> - | R56: 273 | T56: 1.25 | U56: =R56*T56 -> 341.25 | V56: =P56*0.01 -> 0 | W56: =U56-(U56*V56) -> 341.25 | X56: =ROUND(W56,2) -> 341.25 | AA56: 17.8 | AB56: =H56*AA56 -> 0 | AC56: =AB56*$P$7 -> 0 | AD56: =AA56/F56 -> 0.89 | AE56: =ROUND(AD56,3) -> 0.89 | AF56: =AE56*$P$7 -> 20.47 | AG56: =ROUND(AF56,2) -> 20.47 | AI56: =ROUND(AO56,2) -> 341.25 | AK56: =IF($AD$3,AM56+AG56,AM56) -> 341.25 | AM56: =IF($AD$4,X56-($AM$7/100*X56),X56) -> 341.25 | AO56: =IF($AD$5,AK56-((AK56*1.18031)-AK56),AK56) -> 341.25
A57: SHR30 | C57: Герметик высокотемпературный 300°C (красный) 300 мл. | D57: 370 | E57: - | F57: 24 | G57: =AI57 -> 298.75 | I57: =H57*F57 -> 0 | J57: =G57*I57 -> 0 | L57: 4660447836134 | M57: 4673743522175 | P57: =$P$9 -> 0 | Q57: =IF(P57>18,"ПЕРЕБОР","-") -> - | R57: 239 | T57: 1.25 | U57: =R57*T57 -> 298.75 | V57: =P57*0.01 -> 0 | W57: =U57-(U57*V57) -> 298.75 | X57: =ROUND(W57,2) -> 298.75 | AA57: 9.28 | AB57: =H57*AA57 -> 0 | AC57: =AB57*$P$7 -> 0 | AD57: =AA57/F57 -> 0.38666667 | AE57: =ROUND(AD57,3) -> 0.387 | AF57: =AE57*$P$7 -> 8.901 | AG57: =ROUND(AF57,2) -> 8.9 | AI57: =ROUND(AO57,2) -> 298.75 | AK57: =IF($AD$3,AM57+AG57,AM57) -> 298.75 | AM57: =IF($AD$4,X57-($AM$7/100*X57),X57) -> 298.75 | AO57: =IF($AD$5,AK57-((AK57*1.18031)-AK57),AK57) -> 298.75
A58: SAT30 | C58: Герметик аквариумный (бесцветный) 280 мл. | D58: 300 | E58: - | F58: 24 | G58: =AI58 -> 206.25 | I58: =H58*F58 -> 0 | J58: =G58*I58 -> 0 | L58: 4660447836141 | M58: 4673732414573 | P58: =$P$9 -> 0 | Q58: =IF(P58>18,"ПЕРЕБОР","-") -> - | R58: 165 | T58: 1.25 | U58: =R58*T58 -> 206.25 | V58: =P58*0.01 -> 0 | W58: =U58-(U58*V58) -> 206.25 | X58: =ROUND(W58,2) -> 206.25 | AA58: 7.6 | AB58: =H58*AA58 -> 0 | AC58: =AB58*$P$7 -> 0 | AD58: =AA58/F58 -> 0.31666667 | AE58: =ROUND(AD58,3) -> 0.317 | AF58: =AE58*$P$7 -> 7.291 | AG58: =ROUND(AF58,2) -> 7.29 | AI58: =ROUND(AO58,2) -> 206.25 | AK58: =IF($AD$3,AM58+AG58,AM58) -> 206.25 | AM58: =IF($AD$4,X58-($AM$7/100*X58),X58) -> 206.25 | AO58: =IF($AD$5,AK58-((AK58*1.18031)-AK58),AK58) -> 206.25
A59: SAB30 | C59: Герметик аквариумный (чёрный) 280 мл. | D59: 300 | E59: - | F59: 24 | G59: =AI59 -> 206.25 | I59: =H59*F59 -> 0 | J59: =G59*I59 -> 0 | L59: 4660447836158 | M59: 4673732414887 | P59: =$P$9 -> 0 | Q59: =IF(P59>18,"ПЕРЕБОР","-") -> - | R59: 165 | T59: 1.25 | U59: =R59*T59 -> 206.25 | V59: =P59*0.01 -> 0 | W59: =U59-(U59*V59) -> 206.25 | X59: =ROUND(W59,2) -> 206.25 | AA59: 7.6 | AB59: =H59*AA59 -> 0 | AC59: =AB59*$P$7 -> 0 | AD59: =AA59/F59 -> 0.31666667 | AE59: =ROUND(AD59,3) -> 0.317 | AF59: =AE59*$P$7 -> 7.291 | AG59: =ROUND(AF59,2) -> 7.29 | AI59: =ROUND(AO59,2) -> 206.25 | AK59: =IF($AD$3,AM59+AG59,AM59) -> 206.25 | AM59: =IF($AD$4,X59-($AM$7/100*X59),X59) -> 206.25 | AO59: =IF($AD$5,AK59-((AK59*1.18031)-AK59),AK59) -> 206.25
C60: Жидкие гвозди KRONbuild | O60: Жидкие гвозди | Q60: =IF(P60>18,"ПЕРЕБОР","-") -> -
A61: LNB39 | C61: Клей монтажный "Жидкие гвозди" (бежевый) | D61: 390 | E61: - | F61: 24 | G61: =AI61 -> 185 | I61: =H61*F61 -> 0 | J61: =G61*I61 -> 0 | L61: 4627181328561 | M61: 4627181328578 | P61: =$P$9 -> 0 | Q61: =IF(P61>18,"ПЕРЕБОР","-") -> - | R61: 148 | T61: 1.25 | U61: =R61*T61 -> 185 | V61: =P61*0.01 -> 0 | W61: =U61-(U61*V61) -> 185 | X61: =ROUND(W61,2) -> 185 | AA61: 9.76 | AB61: =H61*AA61 -> 0 | AC61: =AB61*$P$7 -> 0 | AD61: =AA61/F61 -> 0.40666667 | AE61: =ROUND(AD61,3) -> 0.407 | AF61: =AE61*$P$7 -> 9.361 | AG61: =ROUND(AF61,2) -> 9.36 | AI61: =ROUND(AO61,2) -> 185 | AK61: =IF($AD$3,AM61+AG61,AM61) -> 185 | AM61: =IF($AD$4,X61-($AM$7/100*X61),X61) -> 185 | AO61: =IF($AD$5,AK61-((AK61*1.18031)-AK61),AK61) -> 185
A62: LNW39 | C62: Клей монтажный "Жидкие гвозди" (белый) | D62: 450 | E62: - | F62: 24 | G62: =AI62 -> 185 | I62: =H62*F62 -> 0 | J62: =G62*I62 -> 0 | L62: 4673743522847 | M62: 4673743522854 | P62: =$P$9 -> 0 | Q62: =IF(P62>18,"ПЕРЕБОР","-") -> - | R62: 148 | T62: 1.25 | U62: =R62*T62 -> 185 | V62: =P62*0.01 -> 0 | W62: =U62-(U62*V62) -> 185 | X62: =ROUND(W62,2) -> 185 | AA62: 11.2 | AB62: =H62*AA62 -> 0 | AC62: =AB62*$P$7 -> 0 | AD62: =AA62/F62 -> 0.46666667 | AE62: =ROUND(AD62,3) -> 0.467 | AF62: =AE62*$P$7 -> 10.741 | AG62: =ROUND(AF62,2) -> 10.74 | AI62: =ROUND(AO62,2) -> 185 | AK62: =IF($AD$3,AM62+AG62,AM62) -> 185 | AM62: =IF($AD$4,X62-($AM$7/100*X62),X62) -> 185 | AO62: =IF($AD$5,AK62-((AK62*1.18031)-AK62),AK62) -> 185
A63: MSC36 | C63: Клей-герметик на основе гибридных полимеров Crystal (прозрачный) | D63: 360 | E63: - | F63: 24 | G63: =AI63 -> 356.25 | I63: =H63*F63 -> 0 | J63: =G63*I63 -> 0 | L63: 4660447836004 | M63: 4627181328554 | P63: =$P$9 -> 0 | Q63: =IF(P63>18,"ПЕРЕБОР","-") -> - | R63: 285 | T63: 1.25 | U63: =R63*T63 -> 356.25 | V63: =P63*0.01 -> 0 | W63: =U63-(U63*V63) -> 356.25 | X63: =ROUND(W63,2) -> 356.25 | AA63: 9.04 | AB63: =H63*AA63 -> 0 | AC63: =AB63*$P$7 -> 0 | AD63: =AA63/F63 -> 0.37666667 | AE63: =ROUND(AD63,3) -> 0.377 | AF63: =AE63*$P$7 -> 8.671 | AG63: =ROUND(AF63,2) -> 8.67 | AI63: =ROUND(AO63,2) -> 356.25 | AK63: =IF($AD$3,AM63+AG63,AM63) -> 356.25 | AM63: =IF($AD$4,X63-($AM$7/100*X63),X63) -> 356.25 | AO63: =IF($AD$5,AK63-((AK63*1.18031)-AK63),AK63) -> 356.25
C64: Герметик акриловый пароизоляционный KRONBuild | O64: Герметик пароизоляционный | Q64: =IF(P64>18,"ПЕРЕБОР","-") -> -
A65: ASIW7KG | C65: Герметик акриловый пароизоляционный KRONBuild белый 7кг | D65: 7000 | E65: - | F65: 1 | G65: =AI65 -> 1265 | I65: =H65*F65 -> 0 | J65: =G65*I65 -> 0 | L65: 4660447836035 | M65: - | P65: =$P$9 -> 0 | Q65: =IF(P65>18,"ПЕРЕБОР","-") -> - | R65: 1012 | T65: 1.25 | U65: =R65*T65 -> 1265 | V65: =P65*0.01 -> 0 | W65: =U65-(U65*V65) -> 1265 | X65: =ROUND(W65,2) -> 1265 | AA65: 7 | AB65: =H65*AA65 -> 0 | AC65: =AB65*$P$7 -> 0 | AD65: =AA65/F65 -> 7 | AE65: =ROUND(AD65,3) -> 7 | AF65: =AE65*$P$7 -> 161 | AG65: =ROUND(AF65,2) -> 161 | AI65: =ROUND(AO65,2) -> 1265 | AK65: =IF($AD$3,AM65+AG65,AM65) -> 1265 | AM65: =IF($AD$4,X65-($AM$7/100*X65),X65) -> 1265 | AO65: =IF($AD$5,AK65-((AK65*1.18031)-AK65),AK65) -> 1265
A66: ASIG7KG | C66: Герметик акриловый пароизоляционный KRONBuild серый 7кг | D66: 7000 | E66: - | F66: 1 | G66: =AI66 -> 1265 | I66: =H66*F66 -> 0 | J66: =G66*I66 -> 0 | L66: 4660447836059 | M66: - | P66: =$P$9 -> 0 | Q66: =IF(P66>18,"ПЕРЕБОР","-") -> - | R66: 1012 | T66: 1.25 | U66: =R66*T66 -> 1265 | V66: =P66*0.01 -> 0 | W66: =U66-(U66*V66) -> 1265 | X66: =ROUND(W66,2) -> 1265 | AA66: 7 | AB66: =H66*AA66 -> 0 | AC66: =AB66*$P$7 -> 0 | AD66: =AA66/F66 -> 7 | AE66: =ROUND(AD66,3) -> 7 | AF66: =AE66*$P$7 -> 161 | AG66: =ROUND(AF66,2) -> 161 | AI66: =ROUND(AO66,2) -> 1265 | AK66: =IF($AD$3,AM66+AG66,AM66) -> 1265 | AM66: =IF($AD$4,X66-($AM$7/100*X66),X66) -> 1265 | AO66: =IF($AD$5,AK66-((AK66*1.18031)-AK66),AK66) -> 1265
A67: ASIW930 | C67: Герметик акриловый пароизоляционный KRONBuild белый 600мл | D67: 930 | E67: - | F67: 20 | G67: =AI67 -> 206.25 | I67: =H67*F67 -> 0 | J67: =G67*I67 -> 0 | L67: 4660447836028 | M67: 4673768182651 | P67: =$P$9 -> 0 | Q67: =IF(P67>18,"ПЕРЕБОР","-") -> - | R67: 165 | T67: 1.25 | U67: =R67*T67 -> 206.25 | V67: =P67*0.01 -> 0 | W67: =U67-(U67*V67) -> 206.25 | X67: =ROUND(W67,2) -> 206.25 | AA67: 19 | AB67: =H67*AA67 -> 0 | AC67: =AB67*$P$7 -> 0 | AD67: =AA67/F67 -> 0.95 | AE67: =ROUND(AD67,3) -> 0.95 | AF67: =AE67*$P$7 -> 21.85 | AG67: =ROUND(AF67,2) -> 21.85 | AI67: =ROUND(AO67,2) -> 206.25 | AK67: =IF($AD$3,AM67+AG67,AM67) -> 206.25 | AM67: =IF($AD$4,X67-($AM$7/100*X67),X67) -> 206.25 | AO67: =IF($AD$5,AK67-((AK67*1.18031)-AK67),AK67) -> 206.25
A68: ASIG930 | C68: Герметик акриловый пароизоляционный KRONBuild серый 600мл | D68: 930 | E68: - | F68: 20 | G68: =AI68 -> 206.25 | I68: =H68*F68 -> 0 | J68: =G68*I68 -> 0 | L68: 4660447836042 | M68: 4673768182675 | P68: =$P$9 -> 0 | Q68: =IF(P68>18,"ПЕРЕБОР","-") -> - | R68: 165 | T68: 1.25 | U68: =R68*T68 -> 206.25 | V68: =P68*0.01 -> 0 | W68: =U68-(U68*V68) -> 206.25 | X68: =ROUND(W68,2) -> 206.25 | AA68: 19 | AB68: =H68*AA68 -> 0 | AC68: =AB68*$P$7 -> 0 | AD68: =AA68/F68 -> 0.95 | AE68: =ROUND(AD68,3) -> 0.95 | AF68: =AE68*$P$7 -> 21.85 | AG68: =ROUND(AF68,2) -> 21.85 | AI68: =ROUND(AO68,2) -> 206.25 | AK68: =IF($AD$3,AM68+AG68,AM68) -> 206.25 | AM68: =IF($AD$4,X68-($AM$7/100*X68),X68) -> 206.25 | AO68: =IF($AD$5,AK68-((AK68*1.18031)-AK68),AK68) -> 206.25
C69: Герметик акриловый паропроницаемый KRONBuild | O69: Герметик паропроницаемый | Q69: =IF(P69>18,"ПЕРЕБОР","-") -> -
A70: ASW7KG | C70: Герметик акриловый паропроницаемый KRONBuild белый 7кг | D70: 7000 | E70: - | F70: 1 | G70: =AI70 -> 1280 | I70: =H70*F70 -> 0 | J70: =G70*I70 -> 0 | L70: 4660447836073 | M70: - | P70: =$P$9 -> 0 | Q70: =IF(P70>18,"ПЕРЕБОР","-") -> - | R70: 1024 | T70: 1.25 | U70: =R70*T70 -> 1280 | V70: =P70*0.01 -> 0 | W70: =U70-(U70*V70) -> 1280 | X70: =ROUND(W70,2) -> 1280 | AA70: 7 | AB70: =H70*AA70 -> 0 | AC70: =AB70*$P$7 -> 0 | AD70: =AA70/F70 -> 7 | AE70: =ROUND(AD70,3) -> 7 | AF70: =AE70*$P$7 -> 161 | AG70: =ROUND(AF70,2) -> 161 | AI70: =ROUND(AO70,2) -> 1280 | AK70: =IF($AD$3,AM70+AG70,AM70) -> 1280 | AM70: =IF($AD$4,X70-($AM$7/100*X70),X70) -> 1280 | AO70: =IF($AD$5,AK70-((AK70*1.18031)-AK70),AK70) -> 1280
A71: ASG7KG | C71: Герметик акриловый паропроницаемый KRONBuild серый 7кг | D71: 7000 | E71: - | F71: 1 | G71: =AI71 -> 1280 | I71: =H71*F71 -> 0 | J71: =G71*I71 -> 0 | L71: 4660447836097 | M71: - | P71: =$P$9 -> 0 | Q71: =IF(P71>18,"ПЕРЕБОР","-") -> - | R71: 1024 | T71: 1.25 | U71: =R71*T71 -> 1280 | V71: =P71*0.01 -> 0 | W71: =U71-(U71*V71) -> 1280 | X71: =ROUND(W71,2) -> 1280 | AA71: 7 | AB71: =H71*AA71 -> 0 | AC71: =AB71*$P$7 -> 0 | AD71: =AA71/F71 -> 7 | AE71: =ROUND(AD71,3) -> 7 | AF71: =AE71*$P$7 -> 161 | AG71: =ROUND(AF71,2) -> 161 | AI71: =ROUND(AO71,2) -> 1280 | AK71: =IF($AD$3,AM71+AG71,AM71) -> 1280 | AM71: =IF($AD$4,X71-($AM$7/100*X71),X71) -> 1280 | AO71: =IF($AD$5,AK71-((AK71*1.18031)-AK71),AK71) -> 1280
A72: ASW930 | C72: Герметик акриловый паропроницаемый KRONBuild белый 600мл | D72: 930 | E72: - | F72: 20 | G72: =AI72 -> 206.25 | I72: =H72*F72 -> 0 | J72: =G72*I72 -> 0 | L72: 4660447836066 | M72: 4673768182613 | P72: =$P$9 -> 0 | Q72: =IF(P72>18,"ПЕРЕБОР","-") -> - | R72: 165 | T72: 1.25 | U72: =R72*T72 -> 206.25 | V72: =P72*0.01 -> 0 | W72: =U72-(U72*V72) -> 206.25 | X72: =ROUND(W72,2) -> 206.25 | AA72: 19 | AB72: =H72*AA72 -> 0 | AC72: =AB72*$P$7 -> 0 | AD72: =AA72/F72 -> 0.95 | AE72: =ROUND(AD72,3) -> 0.95 | AF72: =AE72*$P$7 -> 21.85 | AG72: =ROUND(AF72,2) -> 21.85 | AI72: =ROUND(AO72,2) -> 206.25 | AK72: =IF($AD$3,AM72+AG72,AM72) -> 206.25 | AM72: =IF($AD$4,X72-($AM$7/100*X72),X72) -> 206.25 | AO72: =IF($AD$5,AK72-((AK72*1.18031)-AK72),AK72) -> 206.25
A73: ASG930 | C73: Герметик акриловый паропроницаемый KRONBuild серый 600мл | D73: 930 | E73: - | F73: 20 | G73: =AI73 -> 206.25 | I73: =H73*F73 -> 0 | J73: =G73*I73 -> 0 | L73: 4660447836080 | M73: 4673768182637 | P73: =$P$9 -> 0 | Q73: =IF(P73>18,"ПЕРЕБОР","-") -> - | R73: 165 | T73: 1.25 | U73: =R73*T73 -> 206.25 | V73: =P73*0.01 -> 0 | W73: =U73-(U73*V73) -> 206.25 | X73: =ROUND(W73,2) -> 206.25 | AA73: 19 | AB73: =H73*AA73 -> 0 | AC73: =AB73*$P$7 -> 0 | AD73: =AA73/F73 -> 0.95 | AE73: =ROUND(AD73,3) -> 0.95 | AF73: =AE73*$P$7 -> 21.85 | AG73: =ROUND(AF73,2) -> 21.85 | AI73: =ROUND(AO73,2) -> 206.25 | AK73: =IF($AD$3,AM73+AG73,AM73) -> 206.25 | AM73: =IF($AD$4,X73-($AM$7/100*X73),X73) -> 206.25 | AO73: =IF($AD$5,AK73-((AK73*1.18031)-AK73),AK73) -> 206.25
C74: Эмали, грунт KRONbuild | O74: Эмали, грунт | Q74: =IF(P74>18,"ПЕРЕБОР","-") -> -
A75: SP1018G | C75: Эмаль акриловая RAL 1018 желтая глянец 520 мл. | D75: 310 | E75: - | F75: 12 | G75: =AI75 -> 172.5 | I75: =H75*F75 -> 0 | J75: =G75*I75 -> 0 | L75: 4673759126800 | M75: 4673759126817 | P75: =$P$9 -> 0 | Q75: =IF(P75>18,"ПЕРЕБОР","-") -> - | R75: 138 | T75: 1.25 | U75: =R75*T75 -> 172.5 | V75: =P75*0.01 -> 0 | W75: =U75-(U75*V75) -> 172.5 | X75: =ROUND(W75,2) -> 172.5 | AA75: 4.79 | AB75: =H75*AA75 -> 0 | AC75: =AB75*$P$7 -> 0 | AD75: =AA75/F75 -> 0.39916667 | AE75: =ROUND(AD75,3) -> 0.399 | AF75: =AE75*$P$7 -> 9.177 | AG75: =ROUND(AF75,2) -> 9.18 | AI75: =ROUND(AO75,2) -> 172.5 | AK75: =IF($AD$3,AM75+AG75,AM75) -> 172.5 | AM75: =IF($AD$4,X75-($AM$7/100*X75),X75) -> 172.5 | AO75: =IF($AD$5,AK75-((AK75*1.18031)-AK75),AK75) -> 172.5
A76: SP3020G | C76: Эмаль акриловая RAL 3020 красная глянец 520 мл. | D76: 310 | E76: - | F76: 12 | G76: =AI76 -> 172.5 | I76: =H76*F76 -> 0 | J76: =G76*I76 -> 0 | L76: 4673759126749 | M76: 4673759126756 | P76: =$P$9 -> 0 | Q76: =IF(P76>18,"ПЕРЕБОР","-") -> - | R76: 138 | T76: 1.25 | U76: =R76*T76 -> 172.5 | V76: =P76*0.01 -> 0 | W76: =U76-(U76*V76) -> 172.5 | X76: =ROUND(W76,2) -> 172.5 | AA76: 4.79 | AB76: =H76*AA76 -> 0 | AC76: =AB76*$P$7 -> 0 | AD76: =AA76/F76 -> 0.39916667 | AE76: =ROUND(AD76,3) -> 0.399 | AF76: =AE76*$P$7 -> 9.177 | AG76: =ROUND(AF76,2) -> 9.18 | AI76: =ROUND(AO76,2) -> 172.5 | AK76: =IF($AD$3,AM76+AG76,AM76) -> 172.5 | AM76: =IF($AD$4,X76-($AM$7/100*X76),X76) -> 172.5 | AO76: =IF($AD$5,AK76-((AK76*1.18031)-AK76),AK76) -> 172.5
A77: SP5005G | C77: Эмаль акриловая RAL 5005 синяя глянец 520 мл. | D77: 310 | E77: - | F77: 12 | G77: =AI77 -> 172.5 | I77: =H77*F77 -> 0 | J77: =G77*I77 -> 0 | L77: 4673759126763 | M77: 4673759126770 | P77: =$P$9 -> 0 | Q77: =IF(P77>18,"ПЕРЕБОР","-") -> - | R77: 138 | T77: 1.25 | U77: =R77*T77 -> 172.5 | V77: =P77*0.01 -> 0 | W77: =U77-(U77*V77) -> 172.5 | X77: =ROUND(W77,2) -> 172.5 | AA77: 4.79 | AB77: =H77*AA77 -> 0 | AC77: =AB77*$P$7 -> 0 | AD77: =AA77/F77 -> 0.39916667 | AE77: =ROUND(AD77,3) -> 0.399 | AF77: =AE77*$P$7 -> 9.177 | AG77: =ROUND(AF77,2) -> 9.18 | AI77: =ROUND(AO77,2) -> 172.5 | AK77: =IF($AD$3,AM77+AG77,AM77) -> 172.5 | AM77: =IF($AD$4,X77-($AM$7/100*X77),X77) -> 172.5 | AO77: =IF($AD$5,AK77-((AK77*1.18031)-AK77),AK77) -> 172.5
A78: SP6018G | C78: Эмаль акриловая RAL 6018 светло-зеленая глянец 520 мл. | D78: 310 | E78: - | F78: 12 | G78: =AI78 -> 172.5 | I78: =H78*F78 -> 0 | J78: =G78*I78 -> 0 | L78: 4673759126886 | M78: 4673759126893 | P78: =$P$9 -> 0 | Q78: =IF(P78>18,"ПЕРЕБОР","-") -> - | R78: 138 | T78: 1.25 | U78: =R78*T78 -> 172.5 | V78: =P78*0.01 -> 0 | W78: =U78-(U78*V78) -> 172.5 | X78: =ROUND(W78,2) -> 172.5 | AA78: 4.79 | AB78: =H78*AA78 -> 0 | AC78: =AB78*$P$7 -> 0 | AD78: =AA78/F78 -> 0.39916667 | AE78: =ROUND(AD78,3) -> 0.399 | AF78: =AE78*$P$7 -> 9.177 | AG78: =ROUND(AF78,2) -> 9.18 | AI78: =ROUND(AO78,2) -> 172.5 | AK78: =IF($AD$3,AM78+AG78,AM78) -> 172.5 | AM78: =IF($AD$4,X78-($AM$7/100*X78),X78) -> 172.5 | AO78: =IF($AD$5,AK78-((AK78*1.18031)-AK78),AK78) -> 172.5
A79: SP7046G | C79: Эмаль акриловая RAL 7046 темно-серая глянец 520 мл. | D79: 310 | E79: - | F79: 12 | G79: =AI79 -> 172.5 | I79: =H79*F79 -> 0 | J79: =G79*I79 -> 0 | L79: 4673759126862 | M79: 4673759126879 | P79: =$P$9 -> 0 | Q79: =IF(P79>18,"ПЕРЕБОР","-") -> - | R79: 138 | T79: 1.25 | U79: =R79*T79 -> 172.5 | V79: =P79*0.01 -> 0 | W79: =U79-(U79*V79) -> 172.5 | X79: =ROUND(W79,2) -> 172.5 | AA79: 4.79 | AB79: =H79*AA79 -> 0 | AC79: =AB79*$P$7 -> 0 | AD79: =AA79/F79 -> 0.39916667 | AE79: =ROUND(AD79,3) -> 0.399 | AF79: =AE79*$P$7 -> 9.177 | AG79: =ROUND(AF79,2) -> 9.18 | AI79: =ROUND(AO79,2) -> 172.5 | AK79: =IF($AD$3,AM79+AG79,AM79) -> 172.5 | AM79: =IF($AD$4,X79-($AM$7/100*X79),X79) -> 172.5 | AO79: =IF($AD$5,AK79-((AK79*1.18031)-AK79),AK79) -> 172.5
A80: SP8012G | C80: Эмаль акриловая RAL 8012 коричневая глянец 520 мл. | D80: 310 | E80: - | F80: 12 | G80: =AI80 -> 172.5 | I80: =H80*F80 -> 0 | J80: =G80*I80 -> 0 | L80: 4673759126909 | M80: 4673759126916 | P80: =$P$9 -> 0 | Q80: =IF(P80>18,"ПЕРЕБОР","-") -> - | R80: 138 | T80: 1.25 | U80: =R80*T80 -> 172.5 | V80: =P80*0.01 -> 0 | W80: =U80-(U80*V80) -> 172.5 | X80: =ROUND(W80,2) -> 172.5 | AA80: 4.79 | AB80: =H80*AA80 -> 0 | AC80: =AB80*$P$7 -> 0 | AD80: =AA80/F80 -> 0.39916667 | AE80: =ROUND(AD80,3) -> 0.399 | AF80: =AE80*$P$7 -> 9.177 | AG80: =ROUND(AF80,2) -> 9.18 | AI80: =ROUND(AO80,2) -> 172.5 | AK80: =IF($AD$3,AM80+AG80,AM80) -> 172.5 | AM80: =IF($AD$4,X80-($AM$7/100*X80),X80) -> 172.5 | AO80: =IF($AD$5,AK80-((AK80*1.18031)-AK80),AK80) -> 172.5
A81: SP9003G | C81: Эмаль акриловая RAL 9003 белая глянец 520 мл. | D81: 310 | E81: - | F81: 12 | G81: =AI81 -> 172.5 | I81: =H81*F81 -> 0 | J81: =G81*I81 -> 0 | L81: 4673759126701 | M81: 4673759126718 | P81: =$P$9 -> 0 | Q81: =IF(P81>18,"ПЕРЕБОР","-") -> - | R81: 138 | T81: 1.25 | U81: =R81*T81 -> 172.5 | V81: =P81*0.01 -> 0 | W81: =U81-(U81*V81) -> 172.5 | X81: =ROUND(W81,2) -> 172.5 | AA81: 4.79 | AB81: =H81*AA81 -> 0 | AC81: =AB81*$P$7 -> 0 | AD81: =AA81/F81 -> 0.39916667 | AE81: =ROUND(AD81,3) -> 0.399 | AF81: =AE81*$P$7 -> 9.177 | AG81: =ROUND(AF81,2) -> 9.18 | AI81: =ROUND(AO81,2) -> 172.5 | AK81: =IF($AD$3,AM81+AG81,AM81) -> 172.5 | AM81: =IF($AD$4,X81-($AM$7/100*X81),X81) -> 172.5 | AO81: =IF($AD$5,AK81-((AK81*1.18031)-AK81),AK81) -> 172.5
A82: SP9003M | C82: Эмаль акриловая RAL 9003 белая матовая 520 мл. | D82: 310 | E82: - | F82: 12 | G82: =AI82 -> 172.5 | I82: =H82*F82 -> 0 | J82: =G82*I82 -> 0 | L82: 4673759126725 | M82: 4673759126732 | P82: =$P$9 -> 0 | Q82: =IF(P82>18,"ПЕРЕБОР","-") -> - | R82: 138 | T82: 1.25 | U82: =R82*T82 -> 172.5 | V82: =P82*0.01 -> 0 | W82: =U82-(U82*V82) -> 172.5 | X82: =ROUND(W82,2) -> 172.5 | AA82: 4.79 | AB82: =H82*AA82 -> 0 | AC82: =AB82*$P$7 -> 0 | AD82: =AA82/F82 -> 0.39916667 | AE82: =ROUND(AD82,3) -> 0.399 | AF82: =AE82*$P$7 -> 9.177 | AG82: =ROUND(AF82,2) -> 9.18 | AI82: =ROUND(AO82,2) -> 172.5 | AK82: =IF($AD$3,AM82+AG82,AM82) -> 172.5 | AM82: =IF($AD$4,X82-($AM$7/100*X82),X82) -> 172.5 | AO82: =IF($AD$5,AK82-((AK82*1.18031)-AK82),AK82) -> 172.5
A83: SP9005G | C83: Эмаль акриловая RAL 9005 черная глянец 520 мл. | D83: 310 | E83: - | F83: 12 | G83: =AI83 -> 172.5 | I83: =H83*F83 -> 0 | J83: =G83*I83 -> 0 | L83: 4673759126664 | M83: 4673759126671 | P83: =$P$9 -> 0 | Q83: =IF(P83>18,"ПЕРЕБОР","-") -> - | R83: 138 | T83: 1.25 | U83: =R83*T83 -> 172.5 | V83: =P83*0.01 -> 0 | W83: =U83-(U83*V83) -> 172.5 | X83: =ROUND(W83,2) -> 172.5 | AA83: 4.79 | AB83: =H83*AA83 -> 0 | AC83: =AB83*$P$7 -> 0 | AD83: =AA83/F83 -> 0.39916667 | AE83: =ROUND(AD83,3) -> 0.399 | AF83: =AE83*$P$7 -> 9.177 | AG83: =ROUND(AF83,2) -> 9.18 | AI83: =ROUND(AO83,2) -> 172.5 | AK83: =IF($AD$3,AM83+AG83,AM83) -> 172.5 | AM83: =IF($AD$4,X83-($AM$7/100*X83),X83) -> 172.5 | AO83: =IF($AD$5,AK83-((AK83*1.18031)-AK83),AK83) -> 172.5
A84: SP9005M | C84: Эмаль акриловая RAL 9005 черная матовая 520 мл. | D84: 310 | E84: - | F84: 12 | G84: =AI84 -> 172.5 | I84: =H84*F84 -> 0 | J84: =G84*I84 -> 0 | L84: 4673759126688 | M84: 4673759126695 | P84: =$P$9 -> 0 | Q84: =IF(P84>18,"ПЕРЕБОР","-") -> - | R84: 138 | T84: 1.25 | U84: =R84*T84 -> 172.5 | V84: =P84*0.01 -> 0 | W84: =U84-(U84*V84) -> 172.5 | X84: =ROUND(W84,2) -> 172.5 | AA84: 4.79 | AB84: =H84*AA84 -> 0 | AC84: =AB84*$P$7 -> 0 | AD84: =AA84/F84 -> 0.39916667 | AE84: =ROUND(AD84,3) -> 0.399 | AF84: =AE84*$P$7 -> 9.177 | AG84: =ROUND(AF84,2) -> 9.18 | AI84: =ROUND(AO84,2) -> 172.5 | AK84: =IF($AD$3,AM84+AG84,AM84) -> 172.5 | AM84: =IF($AD$4,X84-($AM$7/100*X84),X84) -> 172.5 | AO84: =IF($AD$5,AK84-((AK84*1.18031)-AK84),AK84) -> 172.5
A85: SP3011G | C85: Эмаль акриловая RAL 3011 коричнево-красный глянец 520 мл. | D85: 310 | E85: - | F85: 12 | G85: =AI85 -> 172.5 | I85: =H85*F85 -> 0 | J85: =G85*I85 -> 0 | L85: 4673759127340 | M85: 4673759127357 | P85: =$P$9 -> 0 | Q85: =IF(P85>18,"ПЕРЕБОР","-") -> - | R85: 138 | T85: 1.25 | U85: =R85*T85 -> 172.5 | V85: =P85*0.01 -> 0 | W85: =U85-(U85*V85) -> 172.5 | X85: =ROUND(W85,2) -> 172.5 | AA85: 4.79 | AB85: =H85*AA85 -> 0 | AC85: =AB85*$P$7 -> 0 | AD85: =AA85/F85 -> 0.39916667 | AE85: =ROUND(AD85,3) -> 0.399 | AF85: =AE85*$P$7 -> 9.177 | AG85: =ROUND(AF85,2) -> 9.18 | AI85: =ROUND(AO85,2) -> 172.5 | AK85: =IF($AD$3,AM85+AG85,AM85) -> 172.5 | AM85: =IF($AD$4,X85-($AM$7/100*X85),X85) -> 172.5 | AO85: =IF($AD$5,AK85-((AK85*1.18031)-AK85),AK85) -> 172.5
A86: SP6005G | C86: Эмаль акриловая RAL 6005 зеленый мох глянец 520 мл. | D86: 310 | E86: - | F86: 12 | G86: =AI86 -> 172.5 | I86: =H86*F86 -> 0 | J86: =G86*I86 -> 0 | L86: 4673759127326 | M86: 4673759127333 | P86: =$P$9 -> 0 | Q86: =IF(P86>18,"ПЕРЕБОР","-") -> - | R86: 138 | T86: 1.25 | U86: =R86*T86 -> 172.5 | V86: =P86*0.01 -> 0 | W86: =U86-(U86*V86) -> 172.5 | X86: =ROUND(W86,2) -> 172.5 | AA86: 4.79 | AB86: =H86*AA86 -> 0 | AC86: =AB86*$P$7 -> 0 | AD86: =AA86/F86 -> 0.39916667 | AE86: =ROUND(AD86,3) -> 0.399 | AF86: =AE86*$P$7 -> 9.177 | AG86: =ROUND(AF86,2) -> 9.18 | AI86: =ROUND(AO86,2) -> 172.5 | AK86: =IF($AD$3,AM86+AG86,AM86) -> 172.5 | AM86: =IF($AD$4,X86-($AM$7/100*X86),X86) -> 172.5 | AO86: =IF($AD$5,AK86-((AK86*1.18031)-AK86),AK86) -> 172.5
... A113: SPSREM | C113: Удалитель наклеек 520 мл. | D113: 377 | E113: - | F113: 12 | G113: =AI113 -> 192.5 | I113: =H113*F113 -> 0 | J113: =G113*I113 -> 0 | L113: 4673743522304 | M113: 4673743522311 | P113: =$P$9 -> 0 | Q113: =IF(P113>18,"ПЕРЕБОР","-") -> - | R113: 154 | T113: 1.25 | U113: =R113*T113 -> 192.5 | V113: =P113*0.01 -> 0 | W113: =U113-(U113*V113) -> 192.5 | X113: =ROUND(W113,2) -> 192.5 | AA113: 4.77 | AB113: =H113*AA113 -> 0 | AC113: =AB113*$P$7 -> 0 | AD113: =AA113/F113 -> 0.3975 | AE113: =ROUND(AD113,3) -> 0.398 | AF113: =AE113*$P$7 -> 9.154 | AG113: =ROUND(AF113,2) -> 9.15 | AI113: =ROUND(AO113,2) -> 192.5 | AK113: =IF($AD$3,AM113+AG113,AM113) -> 192.5 | AM113: =IF($AD$4,X113-($AM$7/100*X113),X113) -> 192.5 | AO113: =IF($AD$5,AK113-((AK113*1.18031)-AK113),AK113) -> 192.5
C114: Эпоксидные клея KRONbuild | O114: Эпоксидные клея | Q114: =IF(P114>18,"ПЕРЕБОР","-") -> -
A115: EXP06 | C115: Эпоксидный клей (смола+отвердитель) в шприце 6мл. | D115: 27 | E115: - | F115: 12 | G115: =AI115 -> 68.75 | I115: =H115*F115 -> 0 | J115: =G115*I115 -> 0 | L115: 4673759125902 | M115: 4673759127203 | P115: =$P$9 -> 0 | Q115: =IF(P115>18,"ПЕРЕБОР","-") -> - | R115: 55 | T115: 1.25 | U115: =R115*T115 -> 68.75 | V115: =P115*0.01 -> 0 | W115: =U115-(U115*V115) -> 68.75 | X115: =ROUND(W115,2) -> 68.75 | AA115: 0.33 | AB115: =H115*AA115 -> 0 | AC115: =AB115*$P$7 -> 0 | AD115: =AA115/F115 -> 0.0275 | AE115: =ROUND(AD115,3) -> 0.028 | AF115: =AE115*$P$7 -> 0.644 | AG115: =ROUND(AF115,2) -> 0.64 | AI115: =ROUND(AO115,2) -> 68.75 | AK115: =IF($AD$3,AM115+AG115,AM115) -> 68.75 | AM115: =IF($AD$4,X115-($AM$7/100*X115),X115) -> 68.75 | AO115: =IF($AD$5,AK115-((AK115*1.18031)-AK115),AK115) -> 68.75
A116: EXP25 | C116: Эпоксидный клей (смола+отвердитель) в шприце 25мл. | D116: 59 | E116: - | F116: 12 | G116: =AI116 -> 120 | I116: =H116*F116 -> 0 | J116: =G116*I116 -> 0 | L116: 4673759125926 | M116: 4673759127210 | P116: =$P$9 -> 0 | Q116: =IF(P116>18,"ПЕРЕБОР","-") -> - | R116: 96 | T116: 1.25 | U116: =R116*T116 -> 120 | V116: =P116*0.01 -> 0 | W116: =U116-(U116*V116) -> 120 | X116: =ROUND(W116,2) -> 120 | AA116: 0.88 | AB116: =H116*AA116 -> 0 | AC116: =AB116*$P$7 -> 0 | AD116: =AA116/F116 -> 0.073333333 | AE116: =ROUND(AD116,3) -> 0.073 | AF116: =AE116*$P$7 -> 1.679 | AG116: =ROUND(AF116,2) -> 1.68 | AI116: =ROUND(AO116,2) -> 120 | AK116: =IF($AD$3,AM116+AG116,AM116) -> 120 | AM116: =IF($AD$4,X116-($AM$7/100*X116),X116) -> 120 | AO116: =IF($AD$5,AK116-((AK116*1.18031)-AK116),AK116) -> 120
C117: Супер клея KRONbuild | O117: Супер клея | Q117: =IF(P117>18,"ПЕРЕБОР","-") -> -
A118: CBR20 | C118: Супер-клей KRONbuild цианоакрилатный | D118: 20 | E118: - | F118: 20 | G118: =AI118 -> 108.75 | I118: =H118*F118 -> 0 | J118: =G118*I118 -> 0 | L118: 4673743520386 | M118: 4673743523301 | P118: =$P$9 -> 0 | Q118: =IF(P118>18,"ПЕРЕБОР","-") -> - | R118: 87 | T118: 1.25 | U118: =R118*T118 -> 108.75 | V118: =P118*0.01 -> 0 | W118: =U118-(U118*V118) -> 108.75 | X118: =ROUND(W118,2) -> 108.75 | AA118: 1 | AB118: =H118*AA118 -> 0 | AC118: =AB118*$P$7 -> 0 | AD118: =AA118/F118 -> 0.05 | AE118: =ROUND(AD118,3) -> 0.05 | AF118: =AE118*$P$7 -> 1.15 | AG118: =ROUND(AF118,2) -> 1.15 | AI118: =ROUND(AO118,2) -> 108.75 | AK118: =IF($AD$3,AM118+AG118,AM118) -> 108.75 | AM118: =IF($AD$4,X118-($AM$7/100*X118),X118) -> 108.75 | AO118: =IF($AD$5,AK118-((AK118*1.18031)-AK118),AK118) -> 108.75
A119: GSX03 | C119: Супер-клей гель KRONbuild цианоакрилатный | D119: 3 | E119: - | F119: 24 | G119: =AI119 -> 35 | I119: =H119*F119 -> 0 | J119: =G119*I119 -> 0 | L119: 4673743520409 | M119: 4673743523318 | P119: =$P$9 -> 0 | Q119: =IF(P119>18,"ПЕРЕБОР","-") -> - | R119: 28 | T119: 1.25 | U119: =R119*T119 -> 35 | V119: =P119*0.01 -> 0 | W119: =U119-(U119*V119) -> 35 | X119: =ROUND(W119,2) -> 35 | AA119: 0.504 | AB119: =H119*AA119 -> 0 | AC119: =AB119*$P$7 -> 0 | AD119: =AA119/F119 -> 0.021 | AE119: =ROUND(AD119,3) -> 0.021 | AF119: =AE119*$P$7 -> 0.483 | AG119: =ROUND(AF119,2) -> 0.48 | AI119: =ROUND(AO119,2) -> 35 | AK119: =IF($AD$3,AM119+AG119,AM119) -> 35 | AM119: =IF($AD$4,X119-($AM$7/100*X119),X119) -> 35 | AO119: =IF($AD$5,AK119-((AK119*1.18031)-AK119),AK119) -> 35
C120: Уплотнители самоклеящиеся KRONbuild | O120: Уплотнители | Q120: =IF(P120>18,"ПЕРЕБОР","-") -> - | Z120: Объем
A121: SD1412B | C121: Уплотнитель самокл. KRONbuild D 14*12 мм, длина 40м, черный | D121: 1833 | E121: - | F121: 6 | G121: =AI121 -> 1237.5 | I121: =H121*F121 -> 0 | J121: =G121*I121 -> 0 | L121: 4673759129467 | M121: 4673759129474 | O121: SD1412B | P121: =$P$9 -> 0 | Q121: =IF(P121>18,"ПЕРЕБОР","-") -> - | R121: 990 | T121: 1.25 | U121: =R121*T121 -> 1237.5 | V121: =P121*0.01 -> 0 | W121: =U121-(U121*V121) -> 1237.5 | X121: =ROUND(W121,2) -> 1237.5 | Z121: 0.08 | AA121: 11 | AB121: =H121*Z121 -> 0 | AC121: =AB121*$P$6 -> 0 | AD121: =Z121/F121 -> 0.013333333 | AE121: =ROUND(AD121,3) -> 0.013 | AF121: =AE121*$P$6 -> 71.5 | AG121: =ROUND(AF121,2) -> 71.5 | AI121: =ROUND(AO121,2) -> 1237.5 | AK121: =IF($AD$3,AM121+AG121,AM121) -> 1237.5 | AM121: =IF($AD$4,X121-($AM$7/100*X121),X121) -> 1237.5 | AO121: =IF($AD$5,AK121-((AK121*1.18031)-AK121),AK121) -> 1237.5 | AQ121: 990
A122: SD98W | C122: Уплотнитель самокл. KRONbuild D 9*8 мм, длина 100м, белый | D122: 1866 | E122: - | F122: 6 | G122: =AI122 -> 1228.31 | I122: =H122*F122 -> 0 | J122: =G122*I122 -> 0 | L122: 4673759129504 | M122: 4673759129511 | O122: SD98W | P122: =$P$9 -> 0 | Q122: =IF(P122>18,"ПЕРЕБОР","-") -> - | R122: 982.65 | T122: 1.25 | U122: =R122*T122 -> 1228.3125 | V122: =P122*0.01 -> 0 | W122: =U122-(U122*V122) -> 1228.3125 | X122: =ROUND(W122,2) -> 1228.31 | Z122: 0.08 | AA122: 11.2 | AB122: =H122*Z122 -> 0 | AC122: =AB122*$P$6 -> 0 | AD122: =Z122/F122 -> 0.013333333 | AE122: =ROUND(AD122,3) -> 0.013 | AF122: =AE122*$P$6 -> 71.5 | AG122: =ROUND(AF122,2) -> 71.5 | AI122: =ROUND(AO122,2) -> 1228.31 | AK122: =IF($AD$3,AM122+AG122,AM122) -> 1228.31 | AM122: =IF($AD$4,X122-($AM$7/100*X122),X122) -> 1228.31 | AO122: =IF($AD$5,AK122-((AK122*1.18031)-AK122),AK122) -> 1228.31
A123: SD98B | C123: Уплотнитель самокл. KRONbuild D 9*8 мм, длина 100м, черный | D123: 1866 | E123: - | F123: 6 | G123: =AI123 -> 1228.31 | I123: =H123*F123 -> 0 | J123: =G123*I123 -> 0 | L123: 4673759129528 | M123: 4673759129535 | O123: SD98B | P123: =$P$9 -> 0 | Q123: =IF(P123>18,"ПЕРЕБОР","-") -> - | R123: 982.65 | T123: 1.25 | U123: =R123*T123 -> 1228.3125 | V123: =P123*0.01 -> 0 | W123: =U123-(U123*V123) -> 1228.3125 | X123: =ROUND(W123,2) -> 1228.31 | Z123: 0.08 | AA123: 11.2 | AB123: =H123*Z123 -> 0 | AC123: =AB123*$P$6 -> 0 | AD123: =Z123/F123 -> 0.013333333 | AE123: =ROUND(AD123,3) -> 0.013 | AF123: =AE123*$P$6 -> 71.5 | AG123: =ROUND(AF123,2) -> 71.5 | AI123: =ROUND(AO123,2) -> 1228.31 | AK123: =IF($AD$3,AM123+AG123,AM123) -> 1228.31 | AM123: =IF($AD$4,X123-($AM$7/100*X123),X123) -> 1228.31 | AO123: =IF($AD$5,AK123-((AK123*1.18031)-AK123),AK123) -> 1228.31
A124: SD98BR | C124: Уплотнитель самокл. KRONbuild D 9*8 мм, длина 100м, коричневый | D124: 1866 | E124: - | F124: 6 | G124: =AI124 -> 1228.31 | I124: =H124*F124 -> 0 | J124: =G124*I124 -> 0 | L124: 4673759129542 | M124: 4673759129559 | O124: SD98BR | P124: =$P$9 -> 0 | Q124: =IF(P124>18,"ПЕРЕБОР","-") -> - | R124: 982.65 | T124: 1.25 | U124: =R124*T124 -> 1228.3125 | V124: =P124*0.01 -> 0 | W124: =U124-(U124*V124) -> 1228.3125 | X124: =ROUND(W124,2) -> 1228.31 | Z124: 0.08 | AA124: 11.2 | AB124: =H124*Z124 -> 0 | AC124: =AB124*$P$6 -> 0 | AD124: =Z124/F124 -> 0.013333333 | AE124: =ROUND(AD124,3) -> 0.013 | AF124: =AE124*$P$6 -> 71.5 | AG124: =ROUND(AF124,2) -> 71.5 | AI124: =ROUND(AO124,2) -> 1228.31 | AK124: =IF($AD$3,AM124+AG124,AM124) -> 1228.31 | AM124: =IF($AD$4,X124-($AM$7/100*X124),X124) -> 1228.31 | AO124: =IF($AD$5,AK124-((AK124*1.18031)-AK124),AK124) -> 1228.31
A125: SP955W | C125: Уплотнитель самокл. KRONbuild P 9*5,5 мм, длина 100м, белый | D125: 1566 | E125: - | F125: 6 | G125: =AI125 -> 1200 | I125: =H125*F125 -> 0 | J125: =G125*I125 -> 0 | L125: 4673759129382 | M125: 4673759129399 | O125: SP955W | P125: =$P$9 -> 0 | Q125: =IF(P125>18,"ПЕРЕБОР","-") -> - | R125: 960 | T125: 1.25 | U125: =R125*T125 -> 1200 | V125: =P125*0.01 -> 0 | W125: =U125-(U125*V125) -> 1200 | X125: =ROUND(W125,2) -> 1200 | Z125: 0.08 | AA125: 9.4 | AB125: =H125*Z125 -> 0 | AC125: =AB125*$P$6 -> 0 | AD125: =Z125/F125 -> 0.013333333 | AE125: =ROUND(AD125,3) -> 0.013 | AF125: =AE125*$P$6 -> 71.5 | AG125: =ROUND(AF125,2) -> 71.5 | AI125: =ROUND(AO125,2) -> 1200 | AK125: =IF($AD$3,AM125+AG125,AM125) -> 1200 | AM125: =IF($AD$4,X125-($AM$7/100*X125),X125) -> 1200 | AO125: =IF($AD$5,AK125-((AK125*1.18031)-AK125),AK125) -> 1200 | AQ125: 960
A126: SP955B | C126: Уплотнитель самокл. KRONbuild P 9*5,5 мм, длина 100м, черный | D126: 1566 | E126: - | F126: 6 | G126: =AI126 -> 1200 | I126: =H126*F126 -> 0 | J126: =G126*I126 -> 0 | L126: 4673759129405 | M126: 4673759129412 | O126: SP955B | P126: =$P$9 -> 0 | Q126: =IF(P126>18,"ПЕРЕБОР","-") -> - | R126: 960 | T126: 1.25 | U126: =R126*T126 -> 1200 | V126: =P126*0.01 -> 0 | W126: =U126-(U126*V126) -> 1200 | X126: =ROUND(W126,2) -> 1200 | Z126: 0.08 | AA126: 9.4 | AB126: =H126*Z126 -> 0 | AC126: =AB126*$P$6 -> 0 | AD126: =Z126/F126 -> 0.013333333 | AE126: =ROUND(AD126,3) -> 0.013 | AF126: =AE126*$P$6 -> 71.5 | AG126: =ROUND(AF126,2) -> 71.5 | AI126: =ROUND(AO126,2) -> 1200 | AK126: =IF($AD$3,AM126+AG126,AM126) -> 1200 | AM126: =IF($AD$4,X126-($AM$7/100*X126),X126) -> 1200 | AO126: =IF($AD$5,AK126-((AK126*1.18031)-AK126),AK126) -> 1200 | AQ126: 960
A127: SP955BR | C127: Уплотнитель самокл. KRONbuild P 9*5,5 мм, длина 100м, коричневый | D127: 1566 | E127: - | F127: 6 | G127: =AI127 -> 1200 | I127: =H127*F127 -> 0 | J127: =G127*I127 -> 0 | L127: 4673759129429 | M127: 4673759129436 | O127: SP955BR | P127: =$P$9 -> 0 | Q127: =IF(P127>18,"ПЕРЕБОР","-") -> - | R127: 960 | T127: 1.25 | U127: =R127*T127 -> 1200 | V127: =P127*0.01 -> 0 | W127: =U127-(U127*V127) -> 1200 | X127: =ROUND(W127,2) -> 1200 | Z127: 0.08 | AA127: 9.4 | AB127: =H127*Z127 -> 0 | AC127: =AB127*$P$6 -> 0 | AD127: =Z127/F127 -> 0.013333333 | AE127: =ROUND(AD127,3) -> 0.013 | AF127: =AE127*$P$6 -> 71.5 | AG127: =ROUND(AF127,2) -> 71.5 | AI127: =ROUND(AO127,2) -> 1200 | AK127: =IF($AD$3,AM127+AG127,AM127) -> 1200 | AM127: =IF($AD$4,X127-($AM$7/100*X127),X127) -> 1200 | AO127: =IF($AD$5,AK127-((AK127*1.18031)-AK127),AK127) -> 1200 | AQ127: 960
A128: SE94W | C128: Уплотнитель самокл. KRONbuild E 9*4 мм, длина 150м, белый | D128: 1966 | E128: - | F128: 6 | G128: =AI128 -> 1498.75 | I128: =H128*F128 -> 0 | J128: =G128*I128 -> 0 | L128: 4673759129320 | M128: 4673759129337 | O128: SE94W | P128: =$P$9 -> 0 | Q128: =IF(P128>18,"ПЕРЕБОР","-") -> - | R128: 1199 | T128: 1.25 | U128: =R128*T128 -> 1498.75 | V128: =P128*0.01 -> 0 | W128: =U128-(U128*V128) -> 1498.75 | X128: =ROUND(W128,2) -> 1498.75 | Z128: 0.08 | AA128: 11.8 | AB128: =H128*Z128 -> 0 | AC128: =AB128*$P$6 -> 0 | AD128: =Z128/F128 -> 0.013333333 | AE128: =ROUND(AD128,3) -> 0.013 | AF128: =AE128*$P$6 -> 71.5 | AG128: =ROUND(AF128,2) -> 71.5 | AI128: =ROUND(AO128,2) -> 1498.75 | AK128: =IF($AD$3,AM128+AG128,AM128) -> 1498.75 | AM128: =IF($AD$4,X128-($AM$7/100*X128),X128) -> 1498.75 | AO128: =IF($AD$5,AK128-((AK128*1.18031)-AK128),AK128) -> 1498.75 | AQ128: 1199
A129: SE94B | C129: Уплотнитель самокл. KRONbuild E 9*4 мм, длина 150м, черный | D129: 1966 | E129: - | F129: 6 | G129: =AI129 -> 1498.75 | I129: =H129*F129 -> 0 | J129: =G129*I129 -> 0 | L129: 4673759129344 | M129: 4673759129351 | O129: SE94B | P129: =$P$9 -> 0 | Q129: =IF(P129>18,"ПЕРЕБОР","-") -> - | R129: 1199 | T129: 1.25 | U129: =R129*T129 -> 1498.75 | V129: =P129*0.01 -> 0 | W129: =U129-(U129*V129) -> 1498.75 | X129: =ROUND(W129,2) -> 1498.75 | Z129: 0.08 | AA129: 11.8 | AB129: =H129*Z129 -> 0 | AC129: =AB129*$P$6 -> 0 | AD129: =Z129/F129 -> 0.013333333 | AE129: =ROUND(AD129,3) -> 0.013 | AF129: =AE129*$P$6 -> 71.5 | AG129: =ROUND(AF129,2) -> 71.5 | AI129: =ROUND(AO129,2) -> 1498.75 | AK129: =IF($AD$3,AM129+AG129,AM129) -> 1498.75 | AM129: =IF($AD$4,X129-($AM$7/100*X129),X129) -> 1498.75 | AO129: =IF($AD$5,AK129-((AK129*1.18031)-AK129),AK129) -> 1498.75 | AQ129: 1199
...

Sheet Описание продукции
B2: Профессиональная монтажная пена KRONbuild MASTERS 80 (Лето, Зима) | D2: KRONbuild Masters профессиональная монтажная пена с превосходной структурой ячеек и хорошей механической прочностью, данная линейка монтажной пены KRONbuild Masters подходит для выполнения таких работ как: – монтажа окон и дверей; – заполнения швов и зазоров; – пустот и сквозных трещин; – изоляции линий горячего и холодного водоснабжения. | E2: • Зима –18° до 30° С. Лето от +5 до + 30° С. • Выход до 80 литров • Объем: 850 мл • Вес: 1000 гр. • Срок годности 18 месяцев
B3: Профессиональная монтажная пена KRONbuild HANDGUN 65 (Всесезонная) | D3: Профессиональная монтажная пена KRONbuild HANDGUN 65 можно использовать как с пистолетом для пены, так и как бытовую пену с трубочкой, подходит для выполнения таких общестроительных работ, как: – обеспечения тепло- и звукоизоляции; – заполнение трещин в холодных помещениях (утепление) и щелей в кровельных материалах; – пеной заделывают места примыкания вытяжек и кондиционеров, щели между трубами; – заполнение пустот вокруг труб отопления, водопроводных труб, на стыках и сгибах, заполнения пустот в стенах. | E3: • Зима от –18°до +30° С. Лето от +5 до +30°С. • Выход до 65 литров • Объём: 850 мл • Вес: 800 гр. • Срок годности 18 месяцев
B4: Профессиональная монтажная пена KRONbuild PRO 70 (Всесезонная, Лето, Зима) | D4: KRONbuild Pro монтажная пена с превосходной структурой ячеек и хорошей механической прочностью, данная линейка монтажной пены KRONbuild Pro подходит для выполнения таких работ как: – монтажа окон и дверей; – заполнения швов и зазоров; – пустот и сквозных трещин; – изоляции линий горячего и холодного водоснабжения. | E4: • Зима –18° до 30° С. Лето от +5 до + 30° С. • Выход до 70 литров • Объем: 850 мл • Вес: 950 гр. • Срок годности 18 месяцев
B5: Профессиональная монтажная пена KRONbuild Ultra 65 (Лето, Зима) | D5: KRONbuild монтажная пена с улучшенной адгезией и хорошей механической прочностью, данная линейка монтажной пены KRONbuild подходит для выполнения таких работ: – монтажа окон и дверей; – обеспечения тепло и звукоизоляции; – монтажа строительных конструкций; – заполнение трещин в холодных помещениях (утепление); – заполнение трещин и щелей в кровельных материалах; – пеной заделывают места примыкания вытяжек и кондиционеров, щели между трубами; – заполнение пустот вокруг труб отопления, водопроводных труб, на стыках и изгиба, заполнения пустот в стенах. | E5: • Зима –18° до 30° С. Лето от +5 до + 30° С. • Выход до 65 литров • Объем: 850 мл • Вес: 850 гр. • Срок годности 18 месяцев
B6: Профессиональная монтажная пена KRONBuild Standart 65 (Всесезонная, Лето, Зима) | D6: Монтажная пена KRONbuild подходит для выполнения таких общестроительных работ, как: – обеспечения тепло- и звукоизоляции; – заполнение трещин в холодных помещениях (утепление) и щелей в кровельных материалах; – пеной заделывают места примыкания вытяжек и кондиционеров, щели между трубами; – заполнение пустот вокруг труб отопления, водопроводных труб, на стыках и сгибах, заполнения пустот в стенах. | E6: • Зима от –18°до +30° С. Лето от +5 до +30°С. • Выход до 65 литров • Объём: 850 мл • Вес: 800 гр. • Срок годности 18 месяцев
B7: Профессиональная монтажная пена KRONbuild 65 (всесезонная) | D7: KRONbuild монтажная пена с хорошей механической прочностью, также KRONbuild обладает отличной адгезией к большинству строительных материалов: – обеспечение тепло- и звукоизоляции; – заполнение трещин в холодных помещениях (утепление) и щелей в кровельных материалах; – заделка щелей, – заполнение пустот вокруг труб отопления, водопроводных труб, на стыках и изгибах; – заполнение пустот в стенах. | E7: • Температура применения от –10С° +30С° • Выход до 65 литров • Объём: 850 мл • Вес: 850 гр. • Срок годности 18 месяцев.
B8: Профессиональная монтажная пена KRONbuild ONE (всесезонная) | D8: KRONbuild монтажная пена с хорошей механической прочностью, также KRONbuild обладает отличной адгезией к большинству строительных материалов: – обеспечение тепло- и звукоизоляции; – заполнение трещин в холодных помещениях (утепление) и щелей в кровельных материалах; – заделка щелей, – заполнение пустот вокруг труб отопления, водопроводных труб, на стыках и изгибах; – заполнение пустот в стенах. | E8: • Температура применения от –10С° +30С° • Выход до 65 литров • Объём: 850 мл • Вес: 770 гр. • Срок годности 18 месяцев.
B9: Напыляемый утеплитель + насадка-распылитель | D9: Напыляемый утеплитель KRONbuild - однокомпонентная полиуретановая теплоизоляция. Используется на объектах жилого и производственного назначения. Применяется при устройстве систем внутренней и наружной теплоизоляции фасадов. Теплозвукоизоляция: - Труднодоступных мест; - Полов, наружных и внутренних стен; - Конструкций крыш, перегородок и фундаментов; - Труб, воздуховодов, контейнеров; - Чердаков, лоджий, террас, мансард. | E9: • Температура применения от +5С° +30С° • Объём: 850 мл • Вес: 900 гр. • Срок годности 18 месяцев.
B10: Цемент-пена | D10: Цемент-пена KRONbuild - однокомпонентная полиуретановая профессиональная композиция клей-цемент, имеющая специфическое растекание, обеспечивающее минимальное расширение и заполнение неровностей. Позволяет снизить толщину соединительной прокладки по 1-2мм. Улучшает теплоизоляционные свойства кладки, т.к. устраняются потери тепла. Увеличивается скорость кладки и экономится время. Процесс более технологичен и практически безотходен. Затвердевает под воздействием влаги из воздуха. Первичное схватывание через 2 часа. Полное отверждение через 24 часа. | E10: • Температура применения от +5С° +30С° • Объём: 850 мл • Вес: 900 гр. • Срок годности 18 месяцев.
B11: Профессиональная монтажная пена KRONbuild Огнестойкая B1 | D11: KRONbuild огнестойкая монтажная пена подходит для выполнения таких работ, как: – тепло- и звукоизоляция монтажных швов при установке – огнеупорных дверей, окон, люков, клапанов; – заполнение швов и зазоров в огнеупорных стенах, перекрытиях, перегородках; – герметизация и заполнение швов и зазоров в конструкциях с повышенным классом огнестойкости. | E11: • Температура применения от +5С° +30С° • Объём: 850 мл • Вес: 850 гр. • Срок годности 18 месяцев.
B12: Клей-пена KRONbuild | D12: Клей-пена KRONbuild подходит для выполнения таких общестроительных работ, как: – крепление теплоизоляционных плит из пенополистирола (EPS и XPS),пенополиуретана (PUR и PIR), минеральной ваты; на бетонные, кирпичные, каменные, оштукатуренные, битумные, металлические и деревянные поверхности в различных системах наружной и внутренней теплоизоляции; – при теплоизоляции кровель, а также уплотнения стыков между плитами при этих работах, – для сторительства жилых и не жилых зданий и сооружений малой этажности из пено- и газоблоков, отсевблоков, шлакоболков, арболитовых блоков. | E12: • Температура применения от –10С° +30С° • Объём: 850 мл • Вес: 800 гр. • Срок годности 18 месяцев.
B13: Бытовая всесезонная монтажная пена KRONbuild ONE 65 | D13: KRONbuild монтажная пена с хорошей механической прочностью, также KRONbuild обладает отличной адгезией к большинству строительных материалов: – обеспечение тепло- и звукоизоляции; – заполнение трещин в холодных помещениях (утепление) и щелей в кровельных материалах; – заделка щелей, – заполнение пустот вокруг труб отопления, водопроводных труб, на стыках и изгибах; – заполнение пустот в стенах. | E13: • Температура применения от –10С° +30С° • Выход до 65 литров • Объём: 850 мл • Вес: 770 гр. • Срок годности 18 месяцев.
... B38: Атмосферостойкий силиконовый герметик WS-650 | D38: Атмосферостойкий силиконовый герметик KRONbuild WS-650 нейтральной вулканизации, однокомпонентный среднемодульный, разработанный для защиты швов в структурных светопрозрачных конструкциях от атмосферных воздействий подходит для таких работ как: – структурное и полуструктурное остекление; – герметизация компенсационных швов или иных подвижных швов при общестроительных фасадных работах; – кровельных работ; – герметизация швов облицовки фасада из натурального камня, гранита | E38: • Объём: 600 мл • Вес: 780 гр. • Срок годности 18 месяцев • Температурный режим транспортировки –20 до +50С
